Workbook

Sheet Sheet1
A1: 1
A2: Pucha Wholesaler LLC
A3: January 1-December 23, 2025
B5: Transaction date | C5: Transaction type | D5: Num | E5: Product/Service full name | F5: Memo/Description | G5: Quantity | H5: Rate | I5: Amount | J5: Balance
A6: Amazon
A7: Amazon | B7: 06/02/2025 | C7: Bill | E7: Display Strip | F7: Used for product displays at retail stores | G7: 8 | H7: 5.41 | I7: 43.28 | J7: 43.28
A8: Amazon | B8: 06/04/2025 | C8: Expense | E8: Display Strip | F8: AMAZON MKTPL*N647V 06-03 Amzn.com/bill WA 6953 DEBIT CARD PURCHASE | G8: 8 | H8: 5.41 | I8: 43.28 | J8: 86.56
A9: Total for Amazon | I9: =I7+I8 -> 86.56
A10: Arjo Vision Trading Company LLC
A11: Arjo Vision Trading Company LLC | B11: 03/19/2025 | C11: Bill | D11: 295 | E11: Volt yellow Guarana 16fl oz /15 | F11: Volt yellow Guarana lata 16fl oz /15 | G11: 15 | H11: 16.0226 | I11: 240.34 | J11: 240.34
A12: Total for Arjo Vision Trading Company LLC | I12: =I11 -> 240.34
A13: Belmont International Trading Corp
A14: Belmont International Trading Corp | B14: 04/28/2025 | C14: Bill | D14: 64308 | E14: Belmont Yuyo Marino FROZEN 2.2lb x 8 | F14: Belmont Yuyo Marino FROZEN 2.2lb x 8 / 1FP-36 | G14: 1 | H14: 54 | I14: 54 | J14: 54
A15: Belmont International Trading Corp | B15: 04/28/2025 | C15: Bill | D15: 64308 | E15: Belmont Chirimoya pulpa 14oz x 20 | F15: Belmont Chirimoya pulpa 14oz x 20 / 859174003153 | G15: 1 | H15: 48 | I15: 48 | J15: 102
A16: Belmont International Trading Corp | B16: 04/28/2025 | C16: Bill | D16: 64308 | E16: Belmont Aji Amarillo entero 1Lb x 18 FROZEN | F16: BELMONT - Belmont Aji Amarillo entero 1Lb x 18 bolsas FROZEN | G16: 6 | H16: 45 | I16: 270 | J16: 372
A17: Belmont International Trading Corp | B17: 04/28/2025 | C17: Bill | D17: 64308 | E17: Belmont Choclo desgranado 1Lb x 30 FROZEN | F17: BELMONT - Belmont Choclo desgranado 1Lb x 30 bolsas FROZEN / 1FP-08 | G17: 6 | H17: 72.5 | I17: 435 | J17: 807
A18: Belmont International Trading Corp | B18: 04/28/2025 | C18: Bill | D18: 64308 | E18: Belmont Aji Limo 14oz x 9 FROZEN | F18: BELMONT - Belmont Aji Limo 14oz x 9 bolsas FROZEN | G18: 1 | H18: 20.9 | I18: 20.9 | J18: 827.9
A19: Belmont International Trading Corp | B19: 04/28/2025 | C19: Bill | D19: 64308 | E19: Belmont Aji Amarillo pasta 8oz x 12 | F19: BELMONT - Belmont Aji Amarillo pasta 8oz x 12 frascos de vidrio / PA-02 | G19: 3 | H19: 23.5 | I19: 70.5 | J19: 898.4
A20: Belmont International Trading Corp | B20: 04/28/2025 | C20: Bill | D20: 64308 | E20: Belmont Aji Panca pasta 8oz x 12 | F20: BELMONT - Belmont Aji Panca pasta 8oz x 12 frascos de vidrio / PA-08 | G20: 2 | H20: 23.5 | I20: 47 | J20: 945.4
A21: Belmont International Trading Corp | B21: 04/28/2025 | C21: Bill | D21: 64308 | E21: AJINOSIYAO 500ml x 24 | F21: TA- PERU - CONDIMENT PRODUCTS - AJI NO Siyau- 24 / 500 ml - 00999 | G21: 1 | H21: 50.4 | I21: 50.4 | J21: 995.8
A22: Belmont International Trading Corp | B22: 04/28/2025 | C22: Bill | D22: 64308 | E22: Ajinomoto Bolsa 250gr x 60 | F22: TA- PERU - CONDIMENT PRODUCTS - MSG -AJINOMOTO- 60 / 250gr - 00995 | G22: 1 | H22: 90 | I22: 90 | J22: 1085.8
A23: Belmont International Trading Corp | B23: 04/28/2025 | C23: Bill | D23: 64308 | E23: Chocolate Cuzco con canela y clavo 4 x 12 | F23: Chocolate Cuzco con canela y clavo 4 x 12 | G23: 1 | H23: 30 | I23: 30 | J23: 1115.8
A24: Belmont International Trading Corp | B24: 04/28/2025 | C24: Bill | D24: 64308 | E24: Chocolate Cuzco regular 4 x 12 | F24: Chocolate Cuzco regular 4 x 12 / 859174003672 / AB-07 | G24: 1 | H24: 30 | I24: 30 | J24: 1145.8
A25: Belmont International Trading Corp | B25: 04/28/2025 | C25: Bill | D25: 64308 | E25: AjiNomoto Bolsa 1Kg x 18 | F25: AjiNomoto Bolsa 1Kg x 18 / 7754487118804 / 00803 / AB-11 | G25: 1 | H25: 109 | I25: 109 | J25: 1254.8
... A155: Belmont International Trading Corp | B155: 12/11/2025 | C155: Bill | D155: 75131 | E155: Galletas Morochas 30gr 6x 30 | F155: PCH- Galletas Morochas 30gr 6x 30 / 7613035803121 / DD-05 | G155: 4 | H155: 63.9 | I155: 255.6 | J155: 24582.44
A156: Total for Belmont International Trading Corp | I156: =I14+I15+I16+I17+I18+I19+I20+I21+I22+I23+I24+I25+I26+I27+I28+I29+I30+I31+I32+I33+I34+I35+I36+I37+I38+I39+I40+I41+I42+I43+I44+I45+I46+I47+I48+I49+I50+I51+I52+I53+I54+I55+I56+I57+I58+I59+I60+I61+I62+I63+I64+I65+I66+I67+I68+I69+I70+I71+I72+I73+I74+I75+I76+I77+I78+I79+I80+I81+I82+I83+I84+I85+I86+I87+I88+I89+I90+I91+I92+I93+I94+I95+I96+I97+I98+I99+I100+I101+I102+I103+I104+I105+I106+I107+I108+I109+I110+I111+I112+I113+I114+I115+I116+I117+I118+I119+I120+I121+I122+I123+I124+I125+I126+I127+I128+I129+I130+I131+I132+I133+I134+I135+I136+I137+I138+I139+I140+I141+I142+I143+I144+I145+I146+I147+I148+I149+I150+I151+I152+I153+I154+I155 -> 24582.44
A157: Continental Food and Beverage, inc
A158: Continental Food and Beverage, inc | B158: 03/03/2025 | C158: Bill | E158: Inca Kola Plastico 2Lt x 8 | F158: Plastico 2Lt | G158: 840 | H158: 12.73 | I158: 10693.2 | J158: 10693.2
A159: Continental Food and Beverage, inc | B159: 03/03/2025 | C159: Bill | E159: Inca Kola Regular x 24 Latas | F159: Regular | G159: 104 | H159: 10.06 | I159: 1046.24 | J159: 11739.44
A160: Continental Food and Beverage, inc | B160: 03/03/2025 | C160: Bill | E160: Inca Kola Vidrio x 24 | F160: Vidrio | G160: 70 | H160: 22.5 | I160: 1575 | J160: 13314.44
A161: Continental Food and Beverage, inc | B161: 03/03/2025 | C161: Bill | E161: Inca Kola Regular x 12 latas | F161: Regular lata x 12 | G161: 416 | H161: 4.985 | I161: 2073.76 | J161: 15388.2
A162: Continental Food and Beverage, inc | B162: 03/03/2025 | C162: Bill | E162: Inca Kola Diet Lata 12oz x 24 | F162: Diet | G162: 104 | H162: 11.94 | I162: 1241.76 | J162: 16629.96
A163: Continental Food and Beverage, inc | B163: 03/13/2025 | C163: Vendor Credit | E163: Inca Kola Plastico 2Lt x 8 | F163: Plastico 2Lt | G163: -80 | H163: 12.73 | I163: -1018.4 | J163: 15611.56
A164: Continental Food and Beverage, inc | B164: 03/13/2025 | C164: Vendor Credit | E164: Product Adjustment | F164: Used for credit memos related to price differences or missing/ damaged inventory | G164: -1 | H164: 204.88 | I164: -204.88 | J164: 15406.68
A165: Continental Food and Beverage, inc | B165: 04/09/2025 | C165: Bill | E165: Inca Kola Regular x 12 latas | F165: - BEBIDAS - INCA KOLA - REGULAR LATA 12 OZ / 12 | G165: 1664 | H165: 5.235 | I165: 8711.04 | J165: 24117.72
A166: Continental Food and Beverage, inc | B166: 04/09/2025 | C166: Bill | E166: Inca Kola Regular x 24 Latas | F166: - BEBIDAS - INCA KOLA - REGULAR- LATA 12 OZ / 24 | G166: 104 | H166: 12.44 | I166: 1293.76 | J166: 25411.48
A167: Continental Food and Beverage, inc | B167: 04/28/2025 | C167: Bill | E167: Inca Kola Regular x 12 latas | F167: - BEBIDAS - INCA KOLA - REGULAR LATA 12 OZ / 12 | G167: 416 | H167: 5.235 | I167: 2177.76 | J167: 27589.24
A168: Continental Food and Beverage, inc | B168: 04/28/2025 | C168: Bill | E168: Inca Kola Diet Lata 12oz x 24 | F168: INCA KOLA - BEBIDAS - INCA KOLA - DIET- LATA 12 OZ / 24 | G168: 208 | H168: 12.44 | I168: 2587.52 | J168: 30176.76
A169: Continental Food and Beverage, inc | B169: 04/28/2025 | C169: Bill | E169: Kola Inglesa 12oz x 24 | F169: - BEBIDAS - KOLA INGLESA - VIDRIO- VIDRIO / 24 | G169: 50 | H169: 16 | I169: 800 | J169: 30976.76
A170: Continental Food and Beverage, inc | B170: 05/14/2025 | C170: Vendor Credit | E170: Inca Kola Diet Lata 12oz x 24 | F170: INCA KOLA - BEBIDAS - INCA KOLA - DIET- LATA 12 OZ / 24 | G170: -8 | H170: 12.44 | I170: -99.52 | J170: 30877.24
A171: Continental Food and Beverage, inc | B171: 07/08/2025 | C171: Bill | D171: 70933 | E171: Inca Kola Plastico 2Lt x 8 | F171: - BEBIDAS - INCA KOLA - PLASTICO 2LT- / 8 | G171: 240 | H171: 13.28 | I171: 3187.2 | J171: 34064.44
A172: Continental Food and Beverage, inc | B172: 07/08/2025 | C172: Bill | D172: 70933 | E172: Inca Kola Regular x 12 latas | F172: - BEBIDAS - INCA KOLA - REGULAR LATA 12 OZ / 12 | G172: 824 | H172: 5.235 | I172: 4313.64 | J172: 38378.08
A173: Continental Food and Beverage, inc | B173: 07/08/2025 | C173: Bill | D173: 70933 | E173: Inca Kola Regular x 24 Latas | F173: - BEBIDAS - INCA KOLA - REGULAR- LATA 12 OZ / 24 | G173: 312 | H173: 10.56 | I173: 3294.72 | J173: 41672.8
A174: Continental Food and Beverage, inc | B174: 08/21/2025 | C174: Bill | D174: 71340 | E174: Inca Kola Plastico 2Lt x 8 | F174: - BEBIDAS - INCA KOLA - PLASTICO 2LT- / 8 | G174: 240 | H174: 13.28 | I174: 3187.2 | J174: 44860
A175: Continental Food and Beverage, inc | B175: 08/21/2025 | C175: Bill | D175: 71340 | E175: Inca Kola Regular x 12 latas | F175: - BEBIDAS - INCA KOLA - REGULAR LATA 12 OZ / 12 | G175: 832 | H175: 5.235 | I175: 4355.52 | J175: 49215.52
A176: Continental Food and Beverage, inc | B176: 08/21/2025 | C176: Bill | D176: 71340 | E176: Inca Kola Diet Lata 12oz x 24 | F176: INCA KOLA - BEBIDAS - INCA KOLA - DIET- LATA 12 OZ / 24 | G176: 100 | H176: 12.44 | I176: 1244 | J176: 50459.52
A177: Continental Food and Beverage, inc | B177: 08/21/2025 | C177: Bill | D177: 71340 | E177: Inca Kola Vidrio x 24 | F177: - BEBIDAS - INCA KOLA - VIDRIO- 10 OZ / 24 | G177: 70 | H177: 24.25 | I177: 1697.5 | J177: 52157.02
A178: Continental Food and Beverage, inc | B178: 08/21/2025 | C178: Bill | D178: 71340 | E178: Kola Inglesa 12oz x 24 | F178: - BEBIDAS - KOLA INGLESA - VIDRIO- VIDRIO / 24 | G178: 50 | H178: 16 | I178: 800 | J178: 52957.02
A179: Continental Food and Beverage, inc | B179: 09/30/2025 | C179: Vendor Credit | D179: 10823 | E179: Inca Kola Regular x 24 Latas | F179: - BEBIDAS - INCA KOLA - REGULAR- LATA 12 OZ / 24 | G179: -100 | H179: 10.56 | I179: -1056 | J179: 51901.02
A180: Continental Food and Beverage, inc | B180: 09/30/2025 | C180: Vendor Credit | D180: 10823 | E180: Inca Kola Regular x 12 latas | F180: - BEBIDAS - INCA KOLA - REGULAR LATA 12 OZ / 12 | G180: -824 | H180: 5.235 | I180: -4313.64 | J180: 47587.38
A181: Continental Food and Beverage, inc | B181: 09/30/2025 | C181: Vendor Credit | D181: 10823 | E181: Inca Kola Regular x 12 latas | F181: - BEBIDAS - INCA KOLA - REGULAR LATA 12 OZ / 12 | G181: -832 | H181: 5.235 | I181: -4355.52 | J181: 43231.86
A182: Continental Food and Beverage, inc | B182: 10/01/2025 | C182: Bill | D182: 0071667 | E182: Inca Kola Plastico 2Lt x 8 | F182: - BEBIDAS - INCA KOLA - PLASTICO 2LT- / 8 | G182: 160 | H182: 13.28 | I182: 2124.8 | J182: 45356.66
... A184: Continental Food and Beverage, inc | B184: 10/01/2025 | C184: Bill | D184: 0071667 | E184: Paneton TODINNO 900gr x 6 | F184: CF&B Paneton TODINNO 900gr x 6 | G184: 100 | H184: 38 | I184: 3800 | J184: 53512.18
A185: Continental Food and Beverage, inc | B185: 11/01/2025 | C185: Vendor Credit | E185: Inca Kola Regular x 12 latas | F185: - BEBIDAS - INCA KOLA - REGULAR LATA 12 OZ / 12 | G185: -208 | H185: 5.235 | I185: -1088.88 | J185: 52423.3
A186: Continental Food and Beverage, inc | B186: 11/04/2025 | C186: Bill | D186: 0071969 | E186: Inca Kola Plastico 2Lt x 8 | F186: - BEBIDAS - INCA KOLA - PLASTICO 2LT- / 8 | G186: 240 | H186: 13.28 | I186: 3187.2 | J186: 55610.5
A187: Continental Food and Beverage, inc | B187: 11/04/2025 | C187: Bill | D187: 0071969 | E187: Paneton TODINNO 900gr x 6 | F187: CF&B Paneton TODINNO 900gr x 6 | G187: 50 | H187: 38 | I187: 1900 | J187: 57510.5
A188: Continental Food and Beverage, inc | B188: 11/04/2025 | C188: Bill | D188: 0071969 | E188: Inca Kola Regular x 24 Latas | F188: - BEBIDAS - INCA KOLA - REGULAR- LATA 12 OZ / 24 | G188: 104 | H188: 10.56 | I188: 1098.24 | J188: 58608.74
A189: Continental Food and Beverage, inc | B189: 11/04/2025 | C189: Bill | D189: 0071969 | E189: Inca Kola Vidrio x 24 | F189: - BEBIDAS - INCA KOLA - VIDRIO- 10 OZ / 24 | G189: 70 | H189: 24.25 | I189: 1697.5 | J189: 60306.24
A190: Continental Food and Beverage, inc | B190: 11/04/2025 | C190: Bill | D190: 0071969 | E190: Inca Kola Regular x 12 latas | F190: - BEBIDAS - INCA KOLA - REGULAR LATA 12 OZ / 12 | G190: 208 | H190: 5.235 | I190: 1088.88 | J190: 61395.12
A191: Continental Food and Beverage, inc | B191: 11/04/2025 | C191: Bill | D191: 0071969 | E191: Galleta Costa Chocolate Cookies x 24 | F191: Galleta Costa Chocolate Cookies x 24 | G191: 1 | H191: 0 | I191: 0 | J191: 61395.12
A192: Continental Food and Beverage, inc | B192: 11/04/2025 | C192: Bill | D192: 0071969 | E192: Galleta Costa Lemon Cookies 140gr x 24 | F192: Galleta Costa Lemon Cookies 140gr x 24 | G192: 1 | H192: 0 | I192: 0 | J192: 61395.12
A193: Continental Food and Beverage, inc | B193: 11/04/2025 | C193: Bill | D193: 0071969 | E193: Galleta Costa Butter Cookies 140gr x 24 | F193: Galleta Costa Butter Cookies 140gr x 24 | G193: 1 | H193: 0 | I193: 0 | J193: 61395.12
A194: Continental Food and Beverage, inc | B194: 11/04/2025 | C194: Bill | D194: 0071969 | E194: Galleta Costa Coconut Cookies 125gr x 28 | F194: Galleta Costa Coconut Cookies 125gr x 28 | G194: 1 | H194: 0 | I194: 0 | J194: 61395.12
A195: Continental Food and Beverage, inc | B195: 11/04/2025 | C195: Bill | D195: 0071969 | E195: Vivo Mifrut Pear 100% frut pouch | F195: Vivo Mifrut Pear 100% frut pouch | G195: 1 | H195: 0 | I195: 0 | J195: 61395.12
A196: Continental Food and Beverage, inc | B196: 11/04/2025 | C196: Bill | D196: 0071969 | E196: Vivo Mifrut Apple 100% frut pouch | F196: Vivo Mifrut Apple 100% frut pouch | G196: 1 | H196: 0 | I196: 0 | J196: 61395.12
A197: Continental Food and Beverage, inc | B197: 11/04/2025 | C197: Bill | D197: 0071969 | E197: Vivo Mifrut Banana 100% frut pouch | F197: Vivo Mifrut Banana 100% frut pouch | G197: 1 | H197: 0 | I197: 0 | J197: 61395.12
A198: Total for Continental Food and Beverage, inc | I198: =I158+I159+I160+I161+I162+I163+I164+I165+I166+I167+I168+I169+I170+I171+I172+I173+I174+I175+I176+I177+I178+I179+I180+I181+I182+I183+I184+I185+I186+I187+I188+I189+I190+I191+I192+I193+I194+I195+I196+I197 -> 61395.12
A199: Fiesta Mart #60
A200: Fiesta Mart #60 | B200: 11/13/2025 | C200: Bill | D200: 824277 | E200: Paneton Donofrio 6/31.04 oz | F200: Paneton Donofrio 6/31.04 oz | G200: 15 | H200: 65.94 | I200: 989.1 | J200: 989.1
A201: Fiesta Mart #60 | B201: 12/18/2025 | C201: Bill | E201: Paneton Donofrio 6/31.04 oz | F201: Paneton Donofrio 6/31.04 oz | G201: 12 | H201: 47.94 | I201: 575.28 | J201: 1564.38
A202: Total for Fiesta Mart #60 | I202: =I200+I201 -> 1564.38
A203: GUIXENS FOOD GROUP, INC.
A204: GUIXENS FOOD GROUP, INC. | B204: 10/29/2025 | C204: Bill | D204: 407638 | E204: Paneton Donofrio 6/31.04 oz | F204: Paneton Donofrio 6/31.04 oz | G204: 40 | H204: 50.1535 | I204: 2006.14 | J204: 2006.14
A205: Total for GUIXENS FOOD GROUP, INC. | I205: =I204 -> 2006.14
A206: Lam's Foods Inc.
A207: Lam's Foods Inc. | B207: 10/03/2025 | C207: Bill | D207: 32400 | E207: Lam's Chifles salado en tiras 2.5oz x 24 | F207: Lam's Chifles salado en tiras 2.5oz x 24 | G207: 48 | H207: 30 | I207: 1440 | J207: 1440
A208: Lam's Foods Inc. | B208: 10/03/2025 | C208: Bill | D208: 32400 | E208: Lam's Chifles dulce en tiras 2.1oz x 24 | F208: Lam's Chifles dulce en tiras 2.1oz x 24 | G208: 12 | H208: 30 | I208: 360 | J208: 1800
A209: Lam's Foods Inc. | B209: 10/03/2025 | C209: Bill | D209: 32400 | E209: Lam's Patacones / Tostones picante 4oz x 24 | F209: Lam's Patacones / Tostones picante 4oz x 24 | G209: 4 | H209: 36 | I209: 144 | J209: 1944
A210: Lam's Foods Inc. | B210: 10/03/2025 | C210: Bill | D210: 32400 | E210: Lam's Patacones / Tostones Regular 4oz x 24 | F210: Lam's Patacones / Tostones Regular 4oz x 24 | G210: 4 | H210: 36 | I210: 144 | J210: 2088
A211: Lam's Foods Inc. | B211: 10/03/2025 | C211: Bill | D211: 32400 | E211: Lam's Patacones / Tostones Dulce 4oz x 24 | F211: Lam's Patacones / Tostones Dulce 4oz x 24 | G211: 4 | H211: 36 | I211: 144 | J211: 2232
A212: Total for Lam's Foods Inc. | I212: =I207+I208+I209+I210+I211 -> 2232
A213: La Sorpresa Store
A214: La Sorpresa Store | B214: 08/26/2025 | C214: Bill | E214: Los Nietitos - Dulce de Leche | F214: dulce de leche | G214: 1 | H214: 75 | I214: 75 | J214: 75
A215: La Sorpresa Store | B215: 08/26/2025 | C215: Bill | E215: Conaprole - Dulce de Leche - Milk Caramel Spread | F215: Conaprole - Dulce de Leche - Milk Caramel Spread | G215: 1 | H215: 148 | I215: 148 | J215: 223
A216: Total for La Sorpresa Store | I216: =I214+I215 -> 223
A217: Peru Chef
A218: Peru Chef | B218: 03/26/2025 | C218: Bill | E218: Peru Chef Maracuya jugo / Passion friut juice 1Lt x 12 | F218: Peru Chef Passion friut juice 1Lt x 12 | G218: 1 | H218: 32.5 | I218: 32.5 | J218: 32.5
A219: Peru Chef | B219: 03/26/2025 | C219: Bill | E219: Peru Chef Emoliente bebida 1Lt x 12 | F219: Peru Chef Emoliente 1Lt x 12 | G219: 1 | H219: 30 | I219: 30 | J219: 62.5
A220: Peru Chef | B220: 03/26/2025 | C220: Bill | E220: Peru Chef Pasta Aji Amarillo 16 oz x 12 | F220: Pasta Aji Amarillo 16 Oz X 12 | G220: 1 | H220: 36 | I220: 36 | J220: 98.5
A221: Peru Chef | B221: 03/26/2025 | C221: Bill | E221: Peru Chef Pasta Aji Panca 16 oz x 12 | F221: Pasta Aji Panca 16 Oz X 12 | G221: 1 | H221: 40 | I221: 40 | J221: 138.5
A222: Peru Chef | B222: 03/26/2025 | C222: Bill | E222: Peru Chef Pasta Ajos 16oz x 12 | F222: Pasta Ajos 16 Oz X 12 | G222: 1 | H222: 60 | I222: 60 | J222: 198.5
A223: Peru Chef | B223: 03/26/2025 | C223: Bill | E223: Peru Chef Crema De Aji P/Ceviche 10.5 oz x 12 | F223: Crema De Aji P/Ceviche 10.5 Oz X 12 | G223: 1 | H223: 36 | I223: 36 | J223: 234.5
A224: Peru Chef | B224: 03/26/2025 | C224: Bill | E224: Peru Chef Salsa de Aji Limo con Rocoto 10.5oz x 12 | F224: Peru Chef Salsa de Aji Limo con Rocoto | G224: 1 | H224: 45 | I224: 45 | J224: 279.5
A225: Peru Chef | B225: 03/26/2025 | C225: Bill | E225: Peru Chef Maiz Morado 15 Oz X 22 | F225: Maiz Morado 15 Oz X 22 | G225: 1 | H225: 48 | I225: 48 | J225: 327.5
A226: Peru Chef | B226: 03/26/2025 | C226: Bill | E226: PERU CHEF Maiz Chulpe 15oz x 12 | F226: Maiz Chulpe 15 Oz X 12 | G226: 1 | H226: 28 | I226: 28 | J226: 355.5
A227: Peru Chef | B227: 03/26/2025 | C227: Bill | E227: Peru Chef Maiz Cancha Montaña15 Oz X 10 | F227: Maiz Cancha Montaña 15 Oz X 10 | G227: 1 | H227: 28 | I227: 28 | J227: 383.5
A228: Peru Chef | B228: 03/26/2025 | C228: Bill | E228: Peru Chef Maiz Mote Pelado 15 Oz X 12 | F228: Maiz Mote Pelado 15 Oz X 12 | G228: 1 | H228: 30 | I228: 30 | J228: 413.5
A229: Peru Chef | B229: 03/26/2025 | C229: Bill | E229: Peru Chef Papa Seca Serrana 15 Oz X 10 | F229: Papa Seca Serrana 15 Oz X 10 | G229: 1 | H229: 19 | I229: 19 | J229: 432.5
... A283: Peru Chef | B283: 03/26/2025 | C283: Bill | E283: Peru Chef Yuca Amarilla 1.5Lb x 18 bolsas | F283: Yuca Amarilla 1.5Lb X 18 | G283: 1 | H283: 72 | I283: 72 | J283: 2308.7
A284: Peru Chef | B284: 04/10/2025 | C284: Bill | D284: 55130 | E284: Peru Chef Pasta Aji Amarillo 16 oz x 12 | F284: Pasta Aji Amarillo 16 Oz X 12 | G284: 1 | H284: 36 | I284: 36 | J284: 2344.7
...

Sheet Hoja1
D3: Valores
A4: Vendor | B4: Transaction date | C4: Product/Service full name | D4: Mín. de Rate | E4: Máx. de Rate | F4: Dif | G4: List Price | H4: Version
A5: Amazon | B5: 06/02/2025 | C5: Display Strip | D5: 5.41 | E5: 5.41 | F5: =D5=E5 -> TRUE | G5: =+A5 -> Amazon
A6: Amazon | B6: 06/04/2025 | C6: Display Strip | D6: 5.41 | E6: 5.41 | F6: =D6=E6 -> TRUE | G6: =+A6 -> Amazon
A7: Arjo Vision Trading Company LLC | B7: 03/19/2025 | C7: Volt yellow Guarana 16fl oz /15 | D7: 16.0226 | E7: 16.0226 | F7: =D7=E7 -> TRUE | G7: =+A7 -> Arjo Vision Trading Company LLC
A8: Belmont International Trading Corp | B8: 04/28/2025 | C8: AjiNomoto Bolsa 1Kg x 18 | D8: 109 | E8: 109 | F8: =D8=E8 -> TRUE | G8: =+A8 -> Belmont International Trading Corp
A9: Belmont International Trading Corp | B9: 04/28/2025 | C9: Ajinomoto Bolsa 250gr x 60 | D9: 90 | E9: 90 | F9: =D9=E9 -> TRUE | G9: =+A9 -> Belmont International Trading Corp
A10: Belmont International Trading Corp | B10: 04/28/2025 | C10: AJINOSIYAO 500ml x 24 | D10: 50.4 | E10: 50.4 | F10: =D10=E10 -> TRUE | G10: =+A10 -> Belmont International Trading Corp
A11: Belmont International Trading Corp | B11: 04/28/2025 | C11: Belmont Aceituna Bidon 104oz x 6 | D11: 106 | E11: 106 | F11: =D11=E11 -> TRUE | G11: =+A11 -> Belmont International Trading Corp
A12: Belmont International Trading Corp | B12: 04/28/2025 | C12: Belmont Aceituna Botija 20oz x 12 | D12: 39 | E12: 39 | F12: =D12=E12 -> TRUE | G12: =+A12 -> Belmont International Trading Corp
A13: Belmont International Trading Corp | B13: 04/28/2025 | C13: Belmont Aderezo de Anticucho 16oz x 12 | D13: 41 | E13: 41 | F13: =D13=E13 -> TRUE | G13: =+A13 -> Belmont International Trading Corp
A14: Belmont International Trading Corp | B14: 04/28/2025 | C14: Belmont Aji Amarillo en Salmuera 20oz x 12 | D14: 36.75 | E14: 36.75 | F14: =D14=E14 -> TRUE | G14: =+A14 -> Belmont International Trading Corp
A15: Belmont International Trading Corp | B15: 04/28/2025 | C15: Belmont Aji Amarillo entero 1Lb x 18 FROZEN | D15: 45 | E15: 45 | F15: =D15=E15 -> TRUE | G15: =+A15 -> Belmont International Trading Corp
A16: Belmont International Trading Corp | B16: 04/28/2025 | C16: Belmont Aji Amarillo pasta 8oz x 12 | D16: 23.5 | E16: 23.5 | F16: =D16=E16 -> TRUE | G16: =+A16 -> Belmont International Trading Corp
... A1452: Tradiciones Andinas | B1452: 12/03/2025 | C1452: VITAPLUSS - Maiz expandido con miel 140gr x 24 | D1452: 26.4 | E1452: 26.4 | F1452: =D1452=E1452 -> TRUE | G1452: =+A1452 -> Tradiciones Andinas
A1453: Total general | D1453: -21.5 | E1453: 204.88

Sheet Productos
A1: Product/Service full name
A2: Display Strip
A3: Volt yellow Guarana 16fl oz /15
A4: Belmont Yuyo Marino FROZEN 2.2lb x 8
A5: Belmont Chirimoya pulpa 14oz x 20
A6: Belmont Aji Amarillo entero 1Lb x 18 FROZEN
A7: Belmont Choclo desgranado 1Lb x 30 FROZEN
A8: Belmont Aji Limo 14oz x 9 FROZEN
A9: Belmont Aji Amarillo pasta 8oz x 12
A10: Belmont Aji Panca pasta 8oz x 12
A11: AJINOSIYAO 500ml x 24
A12: Ajinomoto Bolsa 250gr x 60
... A455: SOL DEL CUZCO Tableta sabor a chocolate con canela y clavo para taza 12 x 90gr

Sheet Proveedores
A1: Vendor | B1: BP
A2: Amazon | B2: =_xlfn.CONCAT(A2," ", "BP") -> Amazon BP
A3: Arjo Vision Trading Company LLC | B3: =_xlfn.CONCAT(A3," ", "BP") -> Arjo Vision Trading Company LLC BP
A4: Belmont International Trading Corp | B4: =_xlfn.CONCAT(A4," ", "BP") -> Belmont International Trading Corp BP
A5: Continental Food and Beverage, inc | B5: =_xlfn.CONCAT(A5," ", "BP") -> Continental Food and Beverage, inc BP
A6: Fiesta Mart #60 | B6: =_xlfn.CONCAT(A6," ", "BP") -> Fiesta Mart #60 BP
A7: GUIXENS FOOD GROUP, INC. | B7: =_xlfn.CONCAT(A7," ", "BP") -> GUIXENS FOOD GROUP, INC. BP
A8: Lam's Foods Inc. | B8: =_xlfn.CONCAT(A8," ", "BP") -> Lam's Foods Inc. BP
A9: La Sorpresa Store | B9: =_xlfn.CONCAT(A9," ", "BP") -> La Sorpresa Store BP
A10: Peru Chef | B10: =_xlfn.CONCAT(A10," ", "BP") -> Peru Chef BP
A11: Sam's Club | B11: =_xlfn.CONCAT(A11," ", "BP") -> Sam's Club BP
A12: SAVERS SUPERMERCADO COST + PLUS | B12: =_xlfn.CONCAT(A12," ", "BP") -> SAVERS SUPERMERCADO COST + PLUS BP
A13: Tradiciones Andinas | B13: =_xlfn.CONCAT(A13," ", "BP") -> Tradiciones Andinas BP

Sheet Base Limpia
A1: Vendor | B1: Transaction date | C1: Transaction type | D1: Num | E1: Product/Service full name | F1: Memo/Description | G1: Quantity | H1: Rate | I1: Amount | J1: Balance | K1: Se repite | L1: x | M1: y
A2: Amazon | B2: 06/02/2025 | C2: Bill | E2: Display Strip | F2: Used for product displays at retail stores | G2: 8 | H2: 5.41 | I2: 43.28 | J2: 43.28 | K2: =COUNTIF($E$2:$E$1466,E2) -> 2 | L2: =IF(G2>0,1,0) -> 1 | M2: =IF(H2>0,1,0) -> 1
A3: Amazon | B3: 06/04/2025 | C3: Expense | E3: Display Strip | F3: AMAZON MKTPL*N647V 06-03 Amzn.com/bill WA 6953 DEBIT CARD PURCHASE | G3: 8 | H3: 5.41 | I3: 43.28 | J3: 86.56 | K3: =COUNTIF($E$2:$E$1466,E3) -> 2 | L3: =IF(G3>0,1,0) -> 1 | M3: =IF(H3>0,1,0) -> 1
A4: Arjo Vision Trading Company LLC | B4: 03/19/2025 | C4: Bill | D4: 295 | E4: Volt yellow Guarana 16fl oz /15 | F4: Volt yellow Guarana lata 16fl oz /15 | G4: 15 | H4: 16.0226 | I4: 240.34 | J4: 240.34 | K4: =COUNTIF($E$2:$E$1466,E4) -> 1 | L4: =IF(G4>0,1,0) -> 1 | M4: =IF(H4>0,1,0) -> 1
A5: Belmont International Trading Corp | B5: 04/28/2025 | C5: Bill | D5: 64308 | E5: Belmont Yuyo Marino FROZEN 2.2lb x 8 | F5: Belmont Yuyo Marino FROZEN 2.2lb x 8 / 1FP-36 | G5: 1 | H5: 54 | I5: 54 | J5: 54 | K5: =COUNTIF($E$2:$E$1466,E5) -> 5 | L5: =IF(G5>0,1,0) -> 1 | M5: =IF(H5>0,1,0) -> 1
A6: Belmont International Trading Corp | B6: 04/28/2025 | C6: Bill | D6: 64308 | E6: Belmont Chirimoya pulpa 14oz x 20 | F6: Belmont Chirimoya pulpa 14oz x 20 / 859174003153 | G6: 1 | H6: 48 | I6: 48 | J6: 102 | K6: =COUNTIF($E$2:$E$1466,E6) -> 2 | L6: =IF(G6>0,1,0) -> 1 | M6: =IF(H6>0,1,0) -> 1
A7: Belmont International Trading Corp | B7: 04/28/2025 | C7: Bill | D7: 64308 | E7: Belmont Aji Amarillo entero 1Lb x 18 FROZEN | F7: BELMONT - Belmont Aji Amarillo entero 1Lb x 18 bolsas FROZEN | G7: 6 | H7: 45 | I7: 270 | J7: 372 | K7: =COUNTIF($E$2:$E$1466,E7) -> 2 | L7: =IF(G7>0,1,0) -> 1 | M7: =IF(H7>0,1,0) -> 1
A8: Belmont International Trading Corp | B8: 04/28/2025 | C8: Bill | D8: 64308 | E8: Belmont Choclo desgranado 1Lb x 30 FROZEN | F8: BELMONT - Belmont Choclo desgranado 1Lb x 30 bolsas FROZEN / 1FP-08 | G8: 6 | H8: 72.5 | I8: 435 | J8: 807 | K8: =COUNTIF($E$2:$E$1466,E8) -> 3 | L8: =IF(G8>0,1,0) -> 1 | M8: =IF(H8>0,1,0) -> 1
A9: Belmont International Trading Corp | B9: 04/28/2025 | C9: Bill | D9: 64308 | E9: Belmont Aji Limo 14oz x 9 FROZEN | F9: BELMONT - Belmont Aji Limo 14oz x 9 bolsas FROZEN | G9: 1 | H9: 20.9 | I9: 20.9 | J9: 827.9 | K9: =COUNTIF($E$2:$E$1466,E9) -> 2 | L9: =IF(G9>0,1,0) -> 1 | M9: =IF(H9>0,1,0) -> 1
A10: Belmont International Trading Corp | B10: 04/28/2025 | C10: Bill | D10: 64308 | E10: Belmont Aji Amarillo pasta 8oz x 12 | F10: BELMONT - Belmont Aji Amarillo pasta 8oz x 12 frascos de vidrio / PA-02 | G10: 3 | H10: 23.5 | I10: 70.5 | J10: 898.4 | K10: =COUNTIF($E$2:$E$1466,E10) -> 1 | L10: =IF(G10>0,1,0) -> 1 | M10: =IF(H10>0,1,0) -> 1
A11: Belmont International Trading Corp | B11: 04/28/2025 | C11: Bill | D11: 64308 | E11: Belmont Aji Panca pasta 8oz x 12 | F11: BELMONT - Belmont Aji Panca pasta 8oz x 12 frascos de vidrio / PA-08 | G11: 2 | H11: 23.5 | I11: 47 | J11: 945.4 | K11: =COUNTIF($E$2:$E$1466,E11) -> 1 | L11: =IF(G11>0,1,0) -> 1 | M11: =IF(H11>0,1,0) -> 1
A12: Belmont International Trading Corp | B12: 04/28/2025 | C12: Bill | D12: 64308 | E12: AJINOSIYAO 500ml x 24 | F12: TA- PERU - CONDIMENT PRODUCTS - AJI NO Siyau- 24 / 500 ml - 00999 | G12: 1 | H12: 50.4 | I12: 50.4 | J12: 995.8 | K12: =COUNTIF($E$2:$E$1466,E12) -> 5 | L12: =IF(G12>0,1,0) -> 1 | M12: =IF(H12>0,1,0) -> 1
A13: Belmont International Trading Corp | B13: 04/28/2025 | C13: Bill | D13: 64308 | E13: Ajinomoto Bolsa 250gr x 60 | F13: TA- PERU - CONDIMENT PRODUCTS - MSG -AJINOMOTO- 60 / 250gr - 00995 | G13: 1 | H13: 90 | I13: 90 | J13: 1085.8 | K13: =COUNTIF($E$2:$E$1466,E13) -> 7 | L13: =IF(G13>0,1,0) -> 1 | M13: =IF(H13>0,1,0) -> 1
A14: Belmont International Trading Corp | B14: 04/28/2025 | C14: Bill | D14: 64308 | E14: Chocolate Cuzco con canela y clavo 4 x 12 | F14: Chocolate Cuzco con canela y clavo 4 x 12 | G14: 1 | H14: 30 | I14: 30 | J14: 1115.8 | K14: =COUNTIF($E$2:$E$1466,E14) -> 1 | L14: =IF(G14>0,1,0) -> 1 | M14: =IF(H14>0,1,0) -> 1
A15: Belmont International Trading Corp | B15: 04/28/2025 | C15: Bill | D15: 64308 | E15: Chocolate Cuzco regular 4 x 12 | F15: Chocolate Cuzco regular 4 x 12 / 859174003672 / AB-07 | G15: 1 | H15: 30 | I15: 30 | J15: 1145.8 | K15: =COUNTIF($E$2:$E$1466,E15) -> 4 | L15: =IF(G15>0,1,0) -> 1 | M15: =IF(H15>0,1,0) -> 1
... A146: Belmont International Trading Corp | B146: 12/11/2025 | C146: Bill | D146: 75131 | E146: Galletas Morochas 30gr 6x 30 | F146: PCH- Galletas Morochas 30gr 6x 30 / 7613035803121 / DD-05 | G146: 4 | H146: 63.9 | I146: 255.6 | J146: 24582.44 | K146: =COUNTIF($E$2:$E$1466,E146) -> 6 | L146: =IF(G146>0,1,0) -> 1 | M146: =IF(H146>0,1,0) -> 1
A147: Continental Food and Beverage, inc | B147: 03/03/2025 | C147: Bill | E147: Inca Kola Plastico 2Lt x 8 | F147: Plastico 2Lt | G147: 840 | H147: 12.73 | I147: 10693.2 | J147: 10693.2 | K147: =COUNTIF($E$2:$E$1466,E147) -> 6 | L147: =IF(G147>0,1,0) -> 1 | M147: =IF(H147>0,1,0) -> 1
A148: Continental Food and Beverage, inc | B148: 03/03/2025 | C148: Bill | E148: Inca Kola Regular x 24 Latas | F148: Regular | G148: 104 | H148: 10.06 | I148: 1046.24 | J148: 11739.44 | K148: =COUNTIF($E$2:$E$1466,E148) -> 5 | L148: =IF(G148>0,1,0) -> 1 | M148: =IF(H148>0,1,0) -> 1
A149: Continental Food and Beverage, inc | B149: 03/03/2025 | C149: Bill | E149: Inca Kola Vidrio x 24 | F149: Vidrio | G149: 70 | H149: 22.5 | I149: 1575 | J149: 13314.44 | K149: =COUNTIF($E$2:$E$1466,E149) -> 3 | L149: =IF(G149>0,1,0) -> 1 | M149: =IF(H149>0,1,0) -> 1
A150: Continental Food and Beverage, inc | B150: 03/03/2025 | C150: Bill | E150: Inca Kola Regular x 12 latas | F150: Regular lata x 12 | G150: 416 | H150: 4.985 | I150: 2073.76 | J150: 15388.2 | K150: =COUNTIF($E$2:$E$1466,E150) -> 10 | L150: =IF(G150>0,1,0) -> 1 | M150: =IF(H150>0,1,0) -> 1
A151: Continental Food and Beverage, inc | B151: 03/03/2025 | C151: Bill | E151: Inca Kola Diet Lata 12oz x 24 | F151: Diet | G151: 104 | H151: 11.94 | I151: 1241.76 | J151: 16629.96 | K151: =COUNTIF($E$2:$E$1466,E151) -> 4 | L151: =IF(G151>0,1,0) -> 1 | M151: =IF(H151>0,1,0) -> 1
A152: Continental Food and Beverage, inc | B152: 03/13/2025 | C152: Vendor Credit | E152: Inca Kola Plastico 2Lt x 8 | F152: Plastico 2Lt | G152: -80 | H152: 12.73 | I152: -1018.4 | J152: 15611.56 | K152: =COUNTIF($E$2:$E$1466,E152) -> 6 | L152: =IF(G152>0,1,0) -> 0 | M152: =IF(H152>0,1,0) -> 1
A153: Continental Food and Beverage, inc | B153: 03/13/2025 | C153: Vendor Credit | E153: Product Adjustment | F153: Used for credit memos related to price differences or missing/ damaged inventory | G153: -1 | H153: 204.88 | I153: -204.88 | J153: 15406.68 | K153: =COUNTIF($E$2:$E$1466,E153) -> 1 | L153: =IF(G153>0,1,0) -> 0 | M153: =IF(H153>0,1,0) -> 1
A154: Continental Food and Beverage, inc | B154: 04/09/2025 | C154: Bill | E154: Inca Kola Regular x 12 latas | F154: - BEBIDAS - INCA KOLA - REGULAR LATA 12 OZ / 12 | G154: 1664 | H154: 5.235 | I154: 8711.04 | J154: 24117.72 | K154: =COUNTIF($E$2:$E$1466,E154) -> 10 | L154: =IF(G154>0,1,0) -> 1 | M154: =IF(H154>0,1,0) -> 1
A155: Continental Food and Beverage, inc | B155: 04/09/2025 | C155: Bill | E155: Inca Kola Regular x 24 Latas | F155: - BEBIDAS - INCA KOLA - REGULAR- LATA 12 OZ / 24 | G155: 104 | H155: 12.44 | I155: 1293.76 | J155: 25411.48 | K155: =COUNTIF($E$2:$E$1466,E155) -> 5 | L155: =IF(G155>0,1,0) -> 1 | M155: =IF(H155>0,1,0) -> 1
A156: Continental Food and Beverage, inc | B156: 04/28/2025 | C156: Bill | E156: Inca Kola Regular x 12 latas | F156: - BEBIDAS - INCA KOLA - REGULAR LATA 12 OZ / 12 | G156: 416 | H156: 5.235 | I156: 2177.76 | J156: 27589.24 | K156: =COUNTIF($E$2:$E$1466,E156) -> 10 | L156: =IF(G156>0,1,0) -> 1 | M156: =IF(H156>0,1,0) -> 1
A157: Continental Food and Beverage, inc | B157: 04/28/2025 | C157: Bill | E157: Inca Kola Diet Lata 12oz x 24 | F157: INCA KOLA - BEBIDAS - INCA KOLA - DIET- LATA 12 OZ / 24 | G157: 208 | H157: 12.44 | I157: 2587.52 | J157: 30176.76 | K157: =COUNTIF($E$2:$E$1466,E157) -> 4 | L157: =IF(G157>0,1,0) -> 1 | M157: =IF(H157>0,1,0) -> 1
A158: Continental Food and Beverage, inc | B158: 04/28/2025 | C158: Bill | E158: Kola Inglesa 12oz x 24 | F158: - BEBIDAS - KOLA INGLESA - VIDRIO- VIDRIO / 24 | G158: 50 | H158: 16 | I158: 800 | J158: 30976.76 | K158: =COUNTIF($E$2:$E$1466,E158) -> 2 | L158: =IF(G158>0,1,0) -> 1 | M158: =IF(H158>0,1,0) -> 1
A159: Continental Food and Beverage, inc | B159: 05/14/2025 | C159: Vendor Credit | E159: Inca Kola Diet Lata 12oz x 24 | F159: INCA KOLA - BEBIDAS - INCA KOLA - DIET- LATA 12 OZ / 24 | G159: -8 | H159: 12.44 | I159: -99.52 | J159: 30877.24 | K159: =COUNTIF($E$2:$E$1466,E159) -> 4 | L159: =IF(G159>0,1,0) -> 0 | M159: =IF(H159>0,1,0) -> 1
A160: Continental Food and Beverage, inc | B160: 07/08/2025 | C160: Bill | D160: 70933 | E160: Inca Kola Plastico 2Lt x 8 | F160: - BEBIDAS - INCA KOLA - PLASTICO 2LT- / 8 | G160: 240 | H160: 13.28 | I160: 3187.2 | J160: 34064.44 | K160: =COUNTIF($E$2:$E$1466,E160) -> 6 | L160: =IF(G160>0,1,0) -> 1 | M160: =IF(H160>0,1,0) -> 1
A161: Continental Food and Beverage, inc | B161: 07/08/2025 | C161: Bill | D161: 70933 | E161: Inca Kola Regular x 12 latas | F161: - BEBIDAS - INCA KOLA - REGULAR LATA 12 OZ / 12 | G161: 824 | H161: 5.235 | I161: 4313.64 | J161: 38378.08 | K161: =COUNTIF($E$2:$E$1466,E161) -> 10 | L161: =IF(G161>0,1,0) -> 1 | M161: =IF(H161>0,1,0) -> 1
A162: Continental Food and Beverage, inc | B162: 07/08/2025 | C162: Bill | D162: 70933 | E162: Inca Kola Regular x 24 Latas | F162: - BEBIDAS - INCA KOLA - REGULAR- LATA 12 OZ / 24 | G162: 312 | H162: 10.56 | I162: 3294.72 | J162: 41672.8 | K162: =COUNTIF($E$2:$E$1466,E162) -> 5 | L162: =IF(G162>0,1,0) -> 1 | M162: =IF(H162>0,1,0) -> 1
A163: Continental Food and Beverage, inc | B163: 08/21/2025 | C163: Bill | D163: 71340 | E163: Inca Kola Plastico 2Lt x 8 | F163: - BEBIDAS - INCA KOLA - PLASTICO 2LT- / 8 | G163: 240 | H163: 13.28 | I163: 3187.2 | J163: 44860 | K163: =COUNTIF($E$2:$E$1466,E163) -> 6 | L163: =IF(G163>0,1,0) -> 1 | M163: =IF(H163>0,1,0) -> 1
A164: Continental Food and Beverage, inc | B164: 08/21/2025 | C164: Bill | D164: 71340 | E164: Inca Kola Regular x 12 latas | F164: - BEBIDAS - INCA KOLA - REGULAR LATA 12 OZ / 12 | G164: 832 | H164: 5.235 | I164: 4355.52 | J164: 49215.52 | K164: =COUNTIF($E$2:$E$1466,E164) -> 10 | L164: =IF(G164>0,1,0) -> 1 | M164: =IF(H164>0,1,0) -> 1
A165: Continental Food and Beverage, inc | B165: 08/21/2025 | C165: Bill | D165: 71340 | E165: Inca Kola Diet Lata 12oz x 24 | F165: INCA KOLA - BEBIDAS - INCA KOLA - DIET- LATA 12 OZ / 24 | G165: 100 | H165: 12.44 | I165: 1244 | J165: 50459.52 | K165: =COUNTIF($E$2:$E$1466,E165) -> 4 | L165: =IF(G165>0,1,0) -> 1 | M165: =IF(H165>0,1,0) -> 1
A166: Continental Food and Beverage, inc | B166: 08/21/2025 | C166: Bill | D166: 71340 | E166: Inca Kola Vidrio x 24 | F166: - BEBIDAS - INCA KOLA - VIDRIO- 10 OZ / 24 | G166: 70 | H166: 24.25 | I166: 1697.5 | J166: 52157.02 | K166: =COUNTIF($E$2:$E$1466,E166) -> 3 | L166: =IF(G166>0,1,0) -> 1 | M166: =IF(H166>0,1,0) -> 1
A167: Continental Food and Beverage, inc | B167: 08/21/2025 | C167: Bill | D167: 71340 | E167: Kola Inglesa 12oz x 24 | F167: - BEBIDAS - KOLA INGLESA - VIDRIO- VIDRIO / 24 | G167: 50 | H167: 16 | I167: 800 | J167: 52957.02 | K167: =COUNTIF($E$2:$E$1466,E167) -> 2 | L167: =IF(G167>0,1,0) -> 1 | M167: =IF(H167>0,1,0) -> 1
A168: Continental Food and Beverage, inc | B168: 09/30/2025 | C168: Vendor Credit | D168: 10823 | E168: Inca Kola Regular x 24 Latas | F168: - BEBIDAS - INCA KOLA - REGULAR- LATA 12 OZ / 24 | G168: -100 | H168: 10.56 | I168: -1056 | J168: 51901.02 | K168: =COUNTIF($E$2:$E$1466,E168) -> 5 | L168: =IF(G168>0,1,0) -> 0 | M168: =IF(H168>0,1,0) -> 1
A169: Continental Food and Beverage, inc | B169: 09/30/2025 | C169: Vendor Credit | D169: 10823 | E169: Inca Kola Regular x 12 latas | F169: - BEBIDAS - INCA KOLA - REGULAR LATA 12 OZ / 12 | G169: -824 | H169: 5.235 | I169: -4313.64 | J169: 47587.38 | K169: =COUNTIF($E$2:$E$1466,E169) -> 10 | L169: =IF(G169>0,1,0) -> 0 | M169: =IF(H169>0,1,0) -> 1
A170: Continental Food and Beverage, inc | B170: 09/30/2025 | C170: Vendor Credit | D170: 10823 | E170: Inca Kola Regular x 12 latas | F170: - BEBIDAS - INCA KOLA - REGULAR LATA 12 OZ / 12 | G170: -832 | H170: 5.235 | I170: -4355.52 | J170: 43231.86 | K170: =COUNTIF($E$2:$E$1466,E170) -> 10 | L170: =IF(G170>0,1,0) -> 0 | M170: =IF(H170>0,1,0) -> 1
A171: Continental Food and Beverage, inc | B171: 10/01/2025 | C171: Bill | D171: 0071667 | E171: Inca Kola Plastico 2Lt x 8 | F171: - BEBIDAS - INCA KOLA - PLASTICO 2LT- / 8 | G171: 160 | H171: 13.28 | I171: 2124.8 | J171: 45356.66 | K171: =COUNTIF($E$2:$E$1466,E171) -> 6 | L171: =IF(G171>0,1,0) -> 1 | M171: =IF(H171>0,1,0) -> 1
... A173: Continental Food and Beverage, inc | B173: 10/01/2025 | C173: Bill | D173: 0071667 | E173: Paneton TODINNO 900gr x 6 | F173: CF&B Paneton TODINNO 900gr x 6 | G173: 100 | H173: 38 | I173: 3800 | J173: 53512.18 | K173: =COUNTIF($E$2:$E$1466,E173) -> 2 | L173: =IF(G173>0,1,0) -> 1 | M173: =IF(H173>0,1,0) -> 1
A174: Continental Food and Beverage, inc | B174: 11/01/2025 | C174: Vendor Credit | E174: Inca Kola Regular x 12 latas | F174: - BEBIDAS - INCA KOLA - REGULAR LATA 12 OZ / 12 | G174: -208 | H174: 5.235 | I174: -1088.88 | J174: 52423.3 | K174: =COUNTIF($E$2:$E$1466,E174) -> 10 | L174: =IF(G174>0,1,0) -> 0 | M174: =IF(H174>0,1,0) -> 1
A175: Continental Food and Beverage, inc | B175: 11/04/2025 | C175: Bill | D175: 0071969 | E175: Inca Kola Plastico 2Lt x 8 | F175: - BEBIDAS - INCA KOLA - PLASTICO 2LT- / 8 | G175: 240 | H175: 13.28 | I175: 3187.2 | J175: 55610.5 | K175: =COUNTIF($E$2:$E$1466,E175) -> 6 | L175: =IF(G175>0,1,0) -> 1 | M175: =IF(H175>0,1,0) -> 1
A176: Continental Food and Beverage, inc | B176: 11/04/2025 | C176: Bill | D176: 0071969 | E176: Paneton TODINNO 900gr x 6 | F176: CF&B Paneton TODINNO 900gr x 6 | G176: 50 | H176: 38 | I176: 1900 | J176: 57510.5 | K176: =COUNTIF($E$2:$E$1466,E176) -> 2 | L176: =IF(G176>0,1,0) -> 1 | M176: =IF(H176>0,1,0) -> 1
A177: Continental Food and Beverage, inc | B177: 11/04/2025 | C177: Bill | D177: 0071969 | E177: Inca Kola Regular x 24 Latas | F177: - BEBIDAS - INCA KOLA - REGULAR- LATA 12 OZ / 24 | G177: 104 | H177: 10.56 | I177: 1098.24 | J177: 58608.74 | K177: =COUNTIF($E$2:$E$1466,E177) -> 5 | L177: =IF(G177>0,1,0) -> 1 | M177: =IF(H177>0,1,0) -> 1
A178: Continental Food and Beverage, inc | B178: 11/04/2025 | C178: Bill | D178: 0071969 | E178: Inca Kola Vidrio x 24 | F178: - BEBIDAS - INCA KOLA - VIDRIO- 10 OZ / 24 | G178: 70 | H178: 24.25 | I178: 1697.5 | J178: 60306.24 | K178: =COUNTIF($E$2:$E$1466,E178) -> 3 | L178: =IF(G178>0,1,0) -> 1 | M178: =IF(H178>0,1,0) -> 1
A179: Continental Food and Beverage, inc | B179: 11/04/2025 | C179: Bill | D179: 0071969 | E179: Inca Kola Regular x 12 latas | F179: - BEBIDAS - INCA KOLA - REGULAR LATA 12 OZ / 12 | G179: 208 | H179: 5.235 | I179: 1088.88 | J179: 61395.12 | K179: =COUNTIF($E$2:$E$1466,E179) -> 10 | L179: =IF(G179>0,1,0) -> 1 | M179: =IF(H179>0,1,0) -> 1
A180: Continental Food and Beverage, inc | B180: 11/04/2025 | C180: Bill | D180: 0071969 | E180: Galleta Costa Chocolate Cookies x 24 | F180: Galleta Costa Chocolate Cookies x 24 | G180: 1 | H180: 0 | I180: 0 | J180: 61395.12 | K180: =COUNTIF($E$2:$E$1466,E180) -> 1 | L180: =IF(G180>0,1,0) -> 1 | M180: =IF(H180>0,1,0) -> 0
A181: Continental Food and Beverage, inc | B181: 11/04/2025 | C181: Bill | D181: 0071969 | E181: Galleta Costa Lemon Cookies 140gr x 24 | F181: Galleta Costa Lemon Cookies 140gr x 24 | G181: 1 | H181: 0 | I181: 0 | J181: 61395.12 | K181: =COUNTIF($E$2:$E$1466,E181) -> 1 | L181: =IF(G181>0,1,0) -> 1 | M181: =IF(H181>0,1,0) -> 0
A182: Continental Food and Beverage, inc | B182: 11/04/2025 | C182: Bill | D182: 0071969 | E182: Galleta Costa Butter Cookies 140gr x 24 | F182: Galleta Costa Butter Cookies 140gr x 24 | G182: 1 | H182: 0 | I182: 0 | J182: 61395.12 | K182: =COUNTIF($E$2:$E$1466,E182) -> 1 | L182: =IF(G182>0,1,0) -> 1 | M182: =IF(H182>0,1,0) -> 0
A183: Continental Food and Beverage, inc | B183: 11/04/2025 | C183: Bill | D183: 0071969 | E183: Galleta Costa Coconut Cookies 125gr x 28 | F183: Galleta Costa Coconut Cookies 125gr x 28 | G183: 1 | H183: 0 | I183: 0 | J183: 61395.12 | K183: =COUNTIF($E$2:$E$1466,E183) -> 1 | L183: =IF(G183>0,1,0) -> 1 | M183: =IF(H183>0,1,0) -> 0
A184: Continental Food and Beverage, inc | B184: 11/04/2025 | C184: Bill | D184: 0071969 | E184: Vivo Mifrut Pear 100% frut pouch | F184: Vivo Mifrut Pear 100% frut pouch | G184: 1 | H184: 0 | I184: 0 | J184: 61395.12 | K184: =COUNTIF($E$2:$E$1466,E184) -> 1 | L184: =IF(G184>0,1,0) -> 1 | M184: =IF(H184>0,1,0) -> 0
A185: Continental Food and Beverage, inc | B185: 11/04/2025 | C185: Bill | D185: 0071969 | E185: Vivo Mifrut Apple 100% frut pouch | F185: Vivo Mifrut Apple 100% frut pouch | G185: 1 | H185: 0 | I185: 0 | J185: 61395.12 | K185: =COUNTIF($E$2:$E$1466,E185) -> 1 | L185: =IF(G185>0,1,0) -> 1 | M185: =IF(H185>0,1,0) -> 0
A186: Continental Food and Beverage, inc | B186: 11/04/2025 | C186: Bill | D186: 0071969 | E186: Vivo Mifrut Banana 100% frut pouch | F186: Vivo Mifrut Banana 100% frut pouch | G186: 1 | H186: 0 | I186: 0 | J186: 61395.12 | K186: =COUNTIF($E$2:$E$1466,E186) -> 1 | L186: =IF(G186>0,1,0) -> 1 | M186: =IF(H186>0,1,0) -> 0
A187: Fiesta Mart #60 | B187: 11/13/2025 | C187: Bill | D187: 824277 | E187: Paneton Donofrio 6/31.04 oz | F187: Paneton Donofrio 6/31.04 oz | G187: 15 | H187: 65.94 | I187: 989.1 | J187: 989.1 | K187: =COUNTIF($E$2:$E$1466,E187) -> 3 | L187: =IF(G187>0,1,0) -> 1 | M187: =IF(H187>0,1,0) -> 1
A188: Fiesta Mart #60 | B188: 12/18/2025 | C188: Bill | E188: Paneton Donofrio 6/31.04 oz | F188: Paneton Donofrio 6/31.04 oz | G188: 12 | H188: 47.94 | I188: 575.28 | J188: 1564.38 | K188: =COUNTIF($E$2:$E$1466,E188) -> 3 | L188: =IF(G188>0,1,0) -> 1 | M188: =IF(H188>0,1,0) -> 1
A189: GUIXENS FOOD GROUP, INC. | B189: 10/29/2025 | C189: Bill | D189: 407638 | E189: Paneton Donofrio 6/31.04 oz | F189: Paneton Donofrio 6/31.04 oz | G189: 40 | H189: 50.1535 | I189: 2006.14 | J189: 2006.14 | K189: =COUNTIF($E$2:$E$1466,E189) -> 3 | L189: =IF(G189>0,1,0) -> 1 | M189: =IF(H189>0,1,0) -> 1
A190: Lam's Foods Inc. | B190: 10/03/2025 | C190: Bill | D190: 32400 | E190: Lam's Chifles salado en tiras 2.5oz x 24 | F190: Lam's Chifles salado en tiras 2.5oz x 24 | G190: 48 | H190: 30 | I190: 1440 | J190: 1440 | K190: =COUNTIF($E$2:$E$1466,E190) -> 1 | L190: =IF(G190>0,1,0) -> 1 | M190: =IF(H190>0,1,0) -> 1
A191: Lam's Foods Inc. | B191: 10/03/2025 | C191: Bill | D191: 32400 | E191: Lam's Chifles dulce en tiras 2.1oz x 24 | F191: Lam's Chifles dulce en tiras 2.1oz x 24 | G191: 12 | H191: 30 | I191: 360 | J191: 1800 | K191: =COUNTIF($E$2:$E$1466,E191) -> 1 | L191: =IF(G191>0,1,0) -> 1 | M191: =IF(H191>0,1,0) -> 1
A192: Lam's Foods Inc. | B192: 10/03/2025 | C192: Bill | D192: 32400 | E192: Lam's Patacones / Tostones picante 4oz x 24 | F192: Lam's Patacones / Tostones picante 4oz x 24 | G192: 4 | H192: 36 | I192: 144 | J192: 1944 | K192: =COUNTIF($E$2:$E$1466,E192) -> 1 | L192: =IF(G192>0,1,0) -> 1 | M192: =IF(H192>0,1,0) -> 1
A193: Lam's Foods Inc. | B193: 10/03/2025 | C193: Bill | D193: 32400 | E193: Lam's Patacones / Tostones Regular 4oz x 24 | F193: Lam's Patacones / Tostones Regular 4oz x 24 | G193: 4 | H193: 36 | I193: 144 | J193: 2088 | K193: =COUNTIF($E$2:$E$1466,E193) -> 1 | L193: =IF(G193>0,1,0) -> 1 | M193: =IF(H193>0,1,0) -> 1
A194: Lam's Foods Inc. | B194: 10/03/2025 | C194: Bill | D194: 32400 | E194: Lam's Patacones / Tostones Dulce 4oz x 24 | F194: Lam's Patacones / Tostones Dulce 4oz x 24 | G194: 4 | H194: 36 | I194: 144 | J194: 2232 | K194: =COUNTIF($E$2:$E$1466,E194) -> 1 | L194: =IF(G194>0,1,0) -> 1 | M194: =IF(H194>0,1,0) -> 1
A195: La Sorpresa Store | B195: 08/26/2025 | C195: Bill | E195: Los Nietitos - Dulce de Leche | F195: dulce de leche | G195: 1 | H195: 75 | I195: 75 | J195: 75 | K195: =COUNTIF($E$2:$E$1466,E195) -> 1 | L195: =IF(G195>0,1,0) -> 1 | M195: =IF(H195>0,1,0) -> 1
A196: La Sorpresa Store | B196: 08/26/2025 | C196: Bill | E196: Conaprole - Dulce de Leche - Milk Caramel Spread | F196: Conaprole - Dulce de Leche - Milk Caramel Spread | G196: 1 | H196: 148 | I196: 148 | J196: 223 | K196: =COUNTIF($E$2:$E$1466,E196) -> 1 | L196: =IF(G196>0,1,0) -> 1 | M196: =IF(H196>0,1,0) -> 1
A197: Peru Chef | B197: 03/26/2025 | C197: Bill | E197: Peru Chef Maracuya jugo / Passion friut juice 1Lt x 12 | F197: Peru Chef Passion friut juice 1Lt x 12 | G197: 1 | H197: 32.5 | I197: 32.5 | J197: 32.5 | K197: =COUNTIF($E$2:$E$1466,E197) -> 1 | L197: =IF(G197>0,1,0) -> 1 | M197: =IF(H197>0,1,0) -> 1
A198: Peru Chef | B198: 03/26/2025 | C198: Bill | E198: Peru Chef Emoliente bebida 1Lt x 12 | F198: Peru Chef Emoliente 1Lt x 12 | G198: 1 | H198: 30 | I198: 30 | J198: 62.5 | K198: =COUNTIF($E$2:$E$1466,E198) -> 3 | L198: =IF(G198>0,1,0) -> 1 | M198: =IF(H198>0,1,0) -> 1
A199: Peru Chef | B199: 03/26/2025 | C199: Bill | E199: Peru Chef Pasta Aji Amarillo 16 oz x 12 | F199: Pasta Aji Amarillo 16 Oz X 12 | G199: 1 | H199: 36 | I199: 36 | J199: 98.5 | K199: =COUNTIF($E$2:$E$1466,E199) -> 6 | L199: =IF(G199>0,1,0) -> 1 | M199: =IF(H199>0,1,0) -> 1
A200: Peru Chef | B200: 03/26/2025 | C200: Bill | E200: Peru Chef Pasta Aji Panca 16 oz x 12 | F200: Pasta Aji Panca 16 Oz X 12 | G200: 1 | H200: 40 | I200: 40 | J200: 138.5 | K200: =COUNTIF($E$2:$E$1466,E200) -> 5 | L200: =IF(G200>0,1,0) -> 1 | M200: =IF(H200>0,1,0) -> 1
A201: Peru Chef | B201: 03/26/2025 | C201: Bill | E201: Peru Chef Pasta Ajos 16oz x 12 | F201: Pasta Ajos 16 Oz X 12 | G201: 1 | H201: 60 | I201: 60 | J201: 198.5 | K201: =COUNTIF($E$2:$E$1466,E201) -> 5 | L201: =IF(G201>0,1,0) -> 1 | M201: =IF(H201>0,1,0) -> 1
A202: Peru Chef | B202: 03/26/2025 | C202: Bill | E202: Peru Chef Crema De Aji P/Ceviche 10.5 oz x 12 | F202: Crema De Aji P/Ceviche 10.5 Oz X 12 | G202: 1 | H202: 36 | I202: 36 | J202: 234.5 | K202: =COUNTIF($E$2:$E$1466,E202) -> 4 | L202: =IF(G202>0,1,0) -> 1 | M202: =IF(H202>0,1,0) -> 1
A203: Peru Chef | B203: 03/26/2025 | C203: Bill | E203: Peru Chef Salsa de Aji Limo con Rocoto 10.5oz x 12 | F203: Peru Chef Salsa de Aji Limo con Rocoto | G203: 1 | H203: 45 | I203: 45 | J203: 279.5 | K203: =COUNTIF($E$2:$E$1466,E203) -> 4 | L203: =IF(G203>0,1,0) -> 1 | M203: =IF(H203>0,1,0) -> 1
A204: Peru Chef | B204: 03/26/2025 | C204: Bill | E204: Peru Chef Maiz Morado 15 Oz X 22 | F204: Maiz Morado 15 Oz X 22 | G204: 1 | H204: 48 | I204: 48 | J204: 327.5 | K204: =COUNTIF($E$2:$E$1466,E204) -> 3 | L204: =IF(G204>0,1,0) -> 1 | M204: =IF(H204>0,1,0) -> 1
A205: Peru Chef | B205: 03/26/2025 | C205: Bill | E205: PERU CHEF Maiz Chulpe 15oz x 12 | F205: Maiz Chulpe 15 Oz X 12 | G205: 1 | H205: 28 | I205: 28 | J205: 355.5 | K205: =COUNTIF($E$2:$E$1466,E205) -> 5 | L205: =IF(G205>0,1,0) -> 1 | M205: =IF(H205>0,1,0) -> 1
A206: Peru Chef | B206: 03/26/2025 | C206: Bill | E206: Peru Chef Maiz Cancha Montaña15 Oz X 10 | F206: Maiz Cancha Montaña 15 Oz X 10 | G206: 1 | H206: 28 | I206: 28 | J206: 383.5 | K206: =COUNTIF($E$2:$E$1466,E206) -> 5 | L206: =IF(G206>0,1,0) -> 1 | M206: =IF(H206>0,1,0) -> 1
... A262: Peru Chef | B262: 03/26/2025 | C262: Bill | E262: Peru Chef Yuca Amarilla 1.5Lb x 18 bolsas | F262: Yuca Amarilla 1.5Lb X 18 | G262: 1 | H262: 72 | I262: 72 | J262: 2308.7 | K262: =COUNTIF($E$2:$E$1466,E262) -> 2 | L262: =IF(G262>0,1,0) -> 1 | M262: =IF(H262>0,1,0) -> 1
A263: Peru Chef | B263: 04/10/2025 | C263: Bill | D263: 55130 | E263: Peru Chef Pasta Aji Amarillo 16 oz x 12 | F263: Pasta Aji Amarillo 16 Oz X 12 | G263: 1 | H263: 36 | I263: 36 | J263: 2344.7 | K263: =COUNTIF($E$2:$E$1466,E263) -> 6 | L263: =IF(G263>0,1,0) -> 1 | M263: =IF(H263>0,1,0) -> 1
A264: Peru Chef | B264: 04/10/2025 | C264: Bill | D264: 55130 | E264: Peru Chef Pasta Aji Panca 16 oz x 12 | F264: Pasta Aji Panca 16 Oz X 12 | G264: 1 | H264: 40 | I264: 40 | J264: 2384.7 | K264: =COUNTIF($E$2:$E$1466,E264) -> 5 | L264: =IF(G264>0,1,0) -> 1 | M264: =IF(H264>0,1,0) -> 1
A265: Peru Chef | B265: 04/10/2025 | C265: Bill | D265: 55130 | E265: Peru Chef Pasta Ajos 16oz x 12 | F265: Pasta Ajos 16 Oz X 12 | G265: 1 | H265: 60 | I265: 60 | J265: 2444.7 | K265: =COUNTIF($E$2:$E$1466,E265) -> 5 | L265: =IF(G265>0,1,0) -> 1 | M265: =IF(H265>0,1,0) -> 1
A266: Peru Chef | B266: 04/10/2025 | C266: Bill | D266: 55130 | E266: Peru Chef Crema De Aji P/Ceviche 10.5 oz x 12 | F266: Crema De Aji P/Ceviche 10.5 Oz X 12 | G266: 1 | H266: 36 | I266: 36 | J266: 2480.7 | K266: =COUNTIF($E$2:$E$1466,E266) -> 4 | L266: =IF(G266>0,1,0) -> 1 | M266: =IF(H266>0,1,0) -> 1
A267: Peru Chef | B267: 04/10/2025 | C267: Bill | D267: 55130 | E267: Peru Chef Salsa de Aji Limo con Rocoto 10.5oz x 12 | F267: Peru Chef Salsa de Aji Limo con Rocoto | G267: 1 | H267: 45 | I267: 45 | J267: 2525.7 | K267: =COUNTIF($E$2:$E$1466,E267) -> 4 | L267: =IF(G267>0,1,0) -> 1 | M267: =IF(H267>0,1,0) -> 1
A268: Peru Chef | B268: 04/10/2025 | C268: Bill | D268: 55130 | E268: Peru Chef Maiz Morado 15 Oz X 22 | F268: Maiz Morado 15 Oz X 22 | G268: 1 | H268: 48 | I268: 48 | J268: 2573.7 | K268: =COUNTIF($E$2:$E$1466,E268) -> 3 | L268: =IF(G268>0,1,0) -> 1 | M268: =IF(H268>0,1,0) -> 1
A269: Peru Chef | B269: 04/10/2025 | C269: Bill | D269: 55130 | E269: PERU CHEF Maiz Chulpe 15oz x 12 | F269: Maiz Chulpe 15 Oz X 12 | G269: 1 | H269: 28 | I269: 28 | J269: 2601.7 | K269: =COUNTIF($E$2:$E$1466,E269) -> 5 | L269: =IF(G269>0,1,0) -> 1 | M269: =IF(H269>0,1,0) -> 1
A270: Peru Chef | B270: 04/10/2025 | C270: Bill | D270: 55130 | E270: Peru Chef Maiz Cancha Montaña15 Oz X 10 | F270: Maiz Cancha Montaña 15 Oz X 10 | G270: 1 | H270: 28 | I270: 28 | J270: 2629.7 | K270: =COUNTIF($E$2:$E$1466,E270) -> 5 | L270: =IF(G270>0,1,0) -> 1 | M270: =IF(H270>0,1,0) -> 1
A271: Peru Chef | B271: 04/10/2025 | C271: Bill | D271: 55130 | E271: Peru Chef Maiz Mote Pelado 15 Oz X 12 | F271: Maiz Mote Pelado 15 Oz X 12 | G271: 1 | H271: 30 | I271: 30 | J271: 2659.7 | K271: =COUNTIF($E$2:$E$1466,E271) -> 4 | L271: =IF(G271>0,1,0) -> 1 | M271: =IF(H271>0,1,0) -> 1
A272: Peru Chef | B272: 04/10/2025 | C272: Bill | D272: 55130 | E272: Peru Chef Papa Seca Serrana 15 Oz X 10 | F272: Papa Seca Serrana 15 Oz X 10 | G272: 1 | H272: 19 | I272: 19 | J272: 2678.7 | K272: =COUNTIF($E$2:$E$1466,E272) -> 6 | L272: =IF(G272>0,1,0) -> 1 | M272: =IF(H272>0,1,0) -> 1
A273: Peru Chef | B273: 04/10/2025 | C273: Bill | D273: 55130 | E273: Peru Chef Papa Seca Amarilla 12oz x 8 | F273: Papa Seca Amarilla 12 Oz X 8 | G273: 1 | H273: 17 | I273: 17 | J273: 2695.7 | K273: =COUNTIF($E$2:$E$1466,E273) -> 8 | L273: =IF(G273>0,1,0) -> 1 | M273: =IF(H273>0,1,0) -> 1
A274: Peru Chef | B274: 04/10/2025 | C274: Bill | D274: 55130 | E274: Peru Chef Trigo Pelado 15 Oz X 12 | F274: Trigo Pelado 15 Oz X 12 | G274: 1 | H274: 19.8 | I274: 19.8 | J274: 2715.5 | K274: =COUNTIF($E$2:$E$1466,E274) -> 5 | L274: =IF(G274>0,1,0) -> 1 | M274: =IF(H274>0,1,0) -> 1
... A438: Peru Chef | B438: 08/11/2025 | C438: Bill | D438: 56352 | E438: Peru Chef Emoliente bebida 1Lt x 12 | F438: Peru Chef Emoliente 1Lt x 12 | G438: 2 | H438: 33 | I438: 66 | J438: 14709.5 | K438: =COUNTIF($E$2:$E$1466,E438) -> 3 | L438: =IF(G438>0,1,0) -> 1 | M438: =IF(H438>0,1,0) -> 1
A439: Peru Chef | B439: 08/27/2025 | C439: Vendor Credit | E439: Peru Chef Tuco 70gr x 12 | F439: PERU CHEF- CONDIMENTO EN POLVO - - TUCO 70 G X 12 | G439: -1 | H439: 24 | I439: -24 | J439: 14685.5 | K439: =COUNTIF($E$2:$E$1466,E439) -> 3 | L439: =IF(G439>0,1,0) -> 0 | M439: =IF(H439>0,1,0) -> 1
A440: Peru Chef | B440: 08/27/2025 | C440: Vendor Credit | E440: EL TRIUNFO Fideo Chino - Chinese Noodles 250gr x 30 | F440: T.A - PERU - MISCELANEUS PRODUCTS - EL TRIUNFO - Fideo Chino - Chinese Noodles - 30 / 250gr - FIDEO | G440: -1 | H440: 39 | I440: -39 | J440: 14646.5 | K440: =COUNTIF($E$2:$E$1466,E440) -> 9 | L440: =IF(G440>0,1,0) -> 0 | M440: =IF(H440>0,1,0) -> 1
A441: Peru Chef | B441: 08/27/2025 | C441: Vendor Credit | E441: Peru Chef Harina de Chuño 15 Oz X 12 | F441: PERU CHEF- GRANOS - BOLSA - HARINA DE CHUNO 15 OZ X 12 | G441: -4 | H441: 3.5 | I441: -14 | J441: 14632.5 | K441: =COUNTIF($E$2:$E$1466,E441) -> 7 | L441: =IF(G441>0,1,0) -> 0 | M441: =IF(H441>0,1,0) -> 1
A442: Peru Chef | B442: 08/27/2025 | C442: Vendor Credit | E442: EL TRIUNFO Fideo Chino - Chinese Noodles 250gr x 30 | F442: T.A - PERU - MISCELANEUS PRODUCTS - EL TRIUNFO - Fideo Chino - Chinese Noodles - 30 / 250gr - FIDEO | G442: 1 | H442: 9 | I442: 9 | J442: 14641.5 | K442: =COUNTIF($E$2:$E$1466,E442) -> 9 | L442: =IF(G442>0,1,0) -> 1 | M442: =IF(H442>0,1,0) -> 1
A443: Peru Chef | B443: 08/27/2025 | C443: Vendor Credit | E443: Peru Chef Harina de Chuño 15 Oz X 12 | F443: PERU CHEF- GRANOS - BOLSA - HARINA DE CHUNO 15 OZ X 12 | G443: 4 | H443: -21.5 | I443: -86 | J443: 14555.5 | K443: =COUNTIF($E$2:$E$1466,E443) -> 7 | L443: =IF(G443>0,1,0) -> 1 | M443: =IF(H443>0,1,0) -> 0
A444: Peru Chef | B444: 08/27/2025 | C444: Vendor Credit | E444: EL TRIUNFO Fideo Chino - Chinese Noodles 250gr x 30 | F444: T.A - PERU - MISCELANEUS PRODUCTS - EL TRIUNFO - Fideo Chino - Chinese Noodles - 30 / 250gr - FIDEO | G444: -1 | H444: 9 | I444: -9 | J444: 14546.5 | K444: =COUNTIF($E$2:$E$1466,E444) -> 9 | L444: =IF(G444>0,1,0) -> 0 | M444: =IF(H444>0,1,0) -> 1
A445: Peru Chef | B445: 08/27/2025 | C445: Vendor Credit | E445: Peru Chef Harina de Chuño 15 Oz X 12 | F445: PERU CHEF- GRANOS - BOLSA - HARINA DE CHUNO 15 OZ X 12 | G445: -4 | H445: -21.5 | I445: 86 | J445: 14632.5 | K445: =COUNTIF($E$2:$E$1466,E445) -> 7 | L445: =IF(G445>0,1,0) -> 0 | M445: =IF(H445>0,1,0) -> 0
A446: Peru Chef | B446: 08/28/2025 | C446: Bill | D446: 2025001209 | E446: Sayon Galletas Tejanas 480gr x 8 | F446: PERU CHEF- GOLOSINAS Y DULCES - - SAYON GALLETAS TEJANAS 480 G X 8- / 8 | G446: 5 | H446: 37 | I446: 185 | J446: 14817.5 | K446: =COUNTIF($E$2:$E$1466,E446) -> 8 | L446: =IF(G446>0,1,0) -> 1 | M446: =IF(H446>0,1,0) -> 1
A447: Peru Chef | B447: 08/28/2025 | C447: Bill | D447: 2025001209 | E447: CASINO Galleta Menta 51gr x 6 x 8 | F447: BELMONT - PERU - GOLOSINAS - DULCES - CASINO - Galleta Menta- 8 / 6x51g - CH117 | G447: 9 | H447: 17 | I447: 153 | J447: 14970.5 | K447: =COUNTIF($E$2:$E$1466,E447) -> 7 | L447: =IF(G447>0,1,0) -> 1 | M447: =IF(H447>0,1,0) -> 1
A448: Peru Chef | B448: 08/28/2025 | C448: Bill | D448: 2025001209 | E448: CASINO Galleta Fresa 51gr x 6 x 8 | F448: BELMONT - PERU - GOLOSINAS - DULCES - CASINO - Galleta Fresa- 8 / 6x51g - CH116 | G448: 4 | H448: 17 | I448: 68 | J448: 15038.5 | K448: =COUNTIF($E$2:$E$1466,E448) -> 5 | L448: =IF(G448>0,1,0) -> 1 | M448: =IF(H448>0,1,0) -> 1
A449: Peru Chef | B449: 08/28/2025 | C449: Bill | D449: 2025001209 | E449: CASINO Galleta Chocolate 51gr x 6 x 8 | F449: BELMONT - PERU - GOLOSINAS - DULCES - CASINO - Galleta Chocolate- 8 / 6x51g - CH118 | G449: 6 | H449: 17 | I449: 102 | J449: 15140.5 | K449: =COUNTIF($E$2:$E$1466,E449) -> 5 | L449: =IF(G449>0,1,0) -> 1 | M449: =IF(H449>0,1,0) -> 1
...

Sheet Base Sin Negativos
A1: Vendor | B1: Transaction date | C1: Transaction type | D1: Num | E1: Product/Service full name | F1: Memo/Description | G1: Quantity | H1: Rate | I1: Amount | J1: Balance | K1: # | L1: Repite producto? | M1: # | N1: # | O1: Repite producto en proveedor? | P1: # | Q1: # | R1: Repite precio en producto en proveedor? | S1: Final | W1: Version | X1: Detalle error | Z1: x
A2: Sam's Club | B2: 12/14/2025 | C2: Bill | E2: Agua Ozarka Texas 8 fl oz Paquete de 48 Botellas de Plástico | F2: Agua de Manantial Ozarka Texas, 8 fl oz, Paquete de 48 Botellas de Plástico | G2: 5 | H2: 7.98 | I2: 39.9 | J2: 39.9 | K2: =COUNTIF($E$2:$E$1438,E2) -> 1 | L2: =IF(K2>1,_xlfn.CONCAT("Se repite ",K2," veces"),"No se repite") -> No se repite | M2: =_xlfn.CONCAT(A2,"-",E2) -> Sam's Club-Agua Ozarka Texas 8 fl oz Paquete de 48 Botellas de Plástico | N2: =COUNTIF($M$2:$M$1438,M2) -> 1 | O2: =IF(N2>1,_xlfn.CONCAT("Se repite ",N2," veces en ",A2),"No se repite en proveedor") -> No se repite en proveedor | P2: =_xlfn.CONCAT(A2,"-",E2,"-",H2) -> Sam's Club-Agua Ozarka Texas 8 fl oz Paquete de 48 Botellas de Plástico-7.98 | Q2: =COUNTIF($P$2:$P$1438,P2) -> 1 | R2: =IF(Q2>1,_xlfn.CONCAT("Se repite ",Q2," veces el precio de ",H2),"No se repite") -> No se repite | S2: =_xlfn.CONCAT("El producto ",E2," ",O2,IF(R2="No se repite",_xlfn.CONCAT(" Una vez con el precio ",H2),_xlfn.CONCAT(", ",R2))) -> El producto Agua Ozarka Texas 8 fl oz Paquete de 48 Botellas de Plástico No se repite en proveedor Una vez con el precio 7.98 | T2: =+A2 -> Sam's Club | U2: =+E2 -> Agua Ozarka Texas 8 fl oz Paquete de 48 Botellas de Plástico | V2: =+H2 -> 7.98 | W2: =_xlfn.CONCAT(A2," ",B2) -> Sam's Club 12/14/2025 | Z2: =G2*H2 -> 39.9
A3: Peru Chef | B3: 09/11/2025 | C3: Bill | D3: 2025001378 | E3: Aji Panca Seco sin pepa 2.04kg | F3: Aji Panca Seco | G3: 1 | H3: 180 | I3: 180 | J3: 25252 | K3: =COUNTIF($E$2:$E$1438,E3) -> 2 | L3: =IF(K3>1,_xlfn.CONCAT("Se repite ",K3," veces"),"No se repite") -> Se repite 2 veces | M3: =_xlfn.CONCAT(A3,"-",E3) -> Peru Chef-Aji Panca Seco sin pepa 2.04kg | N3: =COUNTIF($M$2:$M$1438,M3) -> 2 | O3: =IF(N3>1,_xlfn.CONCAT("Se repite ",N3," veces en ",A3),"No se repite en proveedor") -> Se repite 2 veces en Peru Chef | P3: =_xlfn.CONCAT(A3,"-",E3,"-",H3) -> Peru Chef-Aji Panca Seco sin pepa 2.04kg-180 | Q3: =COUNTIF($P$2:$P$1438,P3) -> 1 | R3: =IF(Q3>1,_xlfn.CONCAT("Se repite ",Q3," veces el precio de ",H3),"No se repite") -> No se repite | S3: =_xlfn.CONCAT("El producto ",E3," ",O3,IF(R3="No se repite",_xlfn.CONCAT(" Una vez con el precio ",H3),_xlfn.CONCAT(", ",R3))) -> El producto Aji Panca Seco sin pepa 2.04kg Se repite 2 veces en Peru Chef Una vez con el precio 180 | T3: =+A3 -> Peru Chef | U3: =+E3 -> Aji Panca Seco sin pepa 2.04kg | V3: =+H3 -> 180 | W3: =_xlfn.CONCAT(A3," ",B3) -> Peru Chef 09/11/2025 | Z3: =G3*H3 -> 180
A4: Peru Chef | B4: 10/09/2025 | C4: Bill | D4: 2025001691 | E4: Aji Panca Seco sin pepa 2.04kg | F4: Aji Panca Seco | G4: 5 | H4: 40 | I4: 200 | J4: 28751.5 | K4: =COUNTIF($E$2:$E$1438,E4) -> 2 | L4: =IF(K4>1,_xlfn.CONCAT("Se repite ",K4," veces"),"No se repite") -> Se repite 2 veces | M4: =_xlfn.CONCAT(A4,"-",E4) -> Peru Chef-Aji Panca Seco sin pepa 2.04kg | N4: =COUNTIF($M$2:$M$1438,M4) -> 2 | O4: =IF(N4>1,_xlfn.CONCAT("Se repite ",N4," veces en ",A4),"No se repite en proveedor") -> Se repite 2 veces en Peru Chef | P4: =_xlfn.CONCAT(A4,"-",E4,"-",H4) -> Peru Chef-Aji Panca Seco sin pepa 2.04kg-40 | Q4: =COUNTIF($P$2:$P$1438,P4) -> 1 | R4: =IF(Q4>1,_xlfn.CONCAT("Se repite ",Q4," veces el precio de ",H4),"No se repite") -> No se repite | S4: =_xlfn.CONCAT("El producto ",E4," ",O4,IF(R4="No se repite",_xlfn.CONCAT(" Una vez con el precio ",H4),_xlfn.CONCAT(", ",R4))) -> El producto Aji Panca Seco sin pepa 2.04kg Se repite 2 veces en Peru Chef Una vez con el precio 40 | T4: =+A4 -> Peru Chef | U4: =+E4 -> Aji Panca Seco sin pepa 2.04kg | V4: =+H4 -> 40 | W4: =_xlfn.CONCAT(A4," ",B4) -> Peru Chef 10/09/2025 | Z4: =G4*H4 -> 200
A5: Belmont International Trading Corp | B5: 04/28/2025 | C5: Bill | D5: 64308 | E5: AjiNomoto Bolsa 1Kg x 18 | F5: AjiNomoto Bolsa 1Kg x 18 / 7754487118804 / 00803 / AB-11 | G5: 1 | H5: 109 | I5: 109 | J5: 1254.8 | K5: =COUNTIF($E$2:$E$1438,E5) -> 5 | L5: =IF(K5>1,_xlfn.CONCAT("Se repite ",K5," veces"),"No se repite") -> Se repite 5 veces | M5: =_xlfn.CONCAT(A5,"-",E5) -> Belmont International Trading Corp-AjiNomoto Bolsa 1Kg x 18 | N5: =COUNTIF($M$2:$M$1438,M5) -> 1 | O5: =IF(N5>1,_xlfn.CONCAT("Se repite ",N5," veces en ",A5),"No se repite en proveedor") -> No se repite en proveedor | P5: =_xlfn.CONCAT(A5,"-",E5,"-",H5) -> Belmont International Trading Corp-AjiNomoto Bolsa 1Kg x 18-109 | Q5: =COUNTIF($P$2:$P$1438,P5) -> 1 | R5: =IF(Q5>1,_xlfn.CONCAT("Se repite ",Q5," veces el precio de ",H5),"No se repite") -> No se repite | S5: =_xlfn.CONCAT("El producto ",E5," ",O5,IF(R5="No se repite",_xlfn.CONCAT(" Una vez con el precio ",H5),_xlfn.CONCAT(", ",R5))) -> El producto AjiNomoto Bolsa 1Kg x 18 No se repite en proveedor Una vez con el precio 109 | T5: =+A5 -> Belmont International Trading Corp | U5: =+E5 -> AjiNomoto Bolsa 1Kg x 18 | V5: =+H5 -> 109 | W5: =_xlfn.CONCAT(A5," ",B5) -> Belmont International Trading Corp 04/28/2025 | Z5: =G5*H5 -> 109
A6: Tradiciones Andinas | B6: 06/12/2025 | C6: Bill | D6: 480295 | E6: AjiNomoto Bolsa 1Kg x 18 | F6: AjiNomoto Bolsa 1Kg x 18 / 7754487118804 / 00803 / AB-11 | G6: 1 | H6: 85 | I6: 85 | J6: 38616.68 | K6: =COUNTIF($E$2:$E$1438,E6) -> 5 | L6: =IF(K6>1,_xlfn.CONCAT("Se repite ",K6," veces"),"No se repite") -> Se repite 5 veces | M6: =_xlfn.CONCAT(A6,"-",E6) -> Tradiciones Andinas-AjiNomoto Bolsa 1Kg x 18 | N6: =COUNTIF($M$2:$M$1438,M6) -> 4 | O6: =IF(N6>1,_xlfn.CONCAT("Se repite ",N6," veces en ",A6),"No se repite en proveedor") -> Se repite 4 veces en Tradiciones Andinas | P6: =_xlfn.CONCAT(A6,"-",E6,"-",H6) -> Tradiciones Andinas-AjiNomoto Bolsa 1Kg x 18-85 | Q6: =COUNTIF($P$2:$P$1438,P6) -> 4 | R6: =IF(Q6>1,_xlfn.CONCAT("Se repite ",Q6," veces el precio de ",H6),"No se repite") -> Se repite 4 veces el precio de 85 | S6: =_xlfn.CONCAT("El producto ",E6," ",O6,IF(R6="No se repite",_xlfn.CONCAT(" Una vez con el precio ",H6),_xlfn.CONCAT(", ",R6))) -> El producto AjiNomoto Bolsa 1Kg x 18 Se repite 4 veces en Tradiciones Andinas, Se repite 4 veces el precio de 85 | T6: =+A6 -> Tradiciones Andinas | U6: =+E6 -> AjiNomoto Bolsa 1Kg x 18 | V6: =+H6 -> 85 | W6: 1 | Z6: =G6*H6 -> 85
A7: Tradiciones Andinas | B7: 07/03/2025 | C7: Bill | D7: 482005 | E7: AjiNomoto Bolsa 1Kg x 18 | F7: AjiNomoto Bolsa 1Kg x 18 / 7754487118804 / 00803 / AB-11 | G7: 2 | H7: 85 | I7: 170 | J7: 50395.63 | K7: =COUNTIF($E$2:$E$1438,E7) -> 5 | L7: =IF(K7>1,_xlfn.CONCAT("Se repite ",K7," veces"),"No se repite") -> Se repite 5 veces | M7: =_xlfn.CONCAT(A7,"-",E7) -> Tradiciones Andinas-AjiNomoto Bolsa 1Kg x 18 | N7: =COUNTIF($M$2:$M$1438,M7) -> 4 | O7: =IF(N7>1,_xlfn.CONCAT("Se repite ",N7," veces en ",A7),"No se repite en proveedor") -> Se repite 4 veces en Tradiciones Andinas | P7: =_xlfn.CONCAT(A7,"-",E7,"-",H7) -> Tradiciones Andinas-AjiNomoto Bolsa 1Kg x 18-85 | Q7: =COUNTIF($P$2:$P$1438,P7) -> 4 | R7: =IF(Q7>1,_xlfn.CONCAT("Se repite ",Q7," veces el precio de ",H7),"No se repite") -> Se repite 4 veces el precio de 85 | S7: =_xlfn.CONCAT("El producto ",E7," ",O7,IF(R7="No se repite",_xlfn.CONCAT(" Una vez con el precio ",H7),_xlfn.CONCAT(", ",R7))) -> El producto AjiNomoto Bolsa 1Kg x 18 Se repite 4 veces en Tradiciones Andinas, Se repite 4 veces el precio de 85 | T7: =+A7 -> Tradiciones Andinas | U7: =+E7 -> AjiNomoto Bolsa 1Kg x 18 | V7: =+H7 -> 85 | W7: =_xlfn.CONCAT(A7," ",B7) -> Tradiciones Andinas 07/03/2025 | Z7: =G7*H7 -> 170
A8: Tradiciones Andinas | B8: 09/24/2025 | C8: Bill | D8: 487860 | E8: AjiNomoto Bolsa 1Kg x 18 | F8: AjiNomoto Bolsa 1Kg x 18 / 7754487118804 / 00803 / AB-11 | G8: 1 | H8: 85 | I8: 85 | J8: 80699.94 | K8: =COUNTIF($E$2:$E$1438,E8) -> 5 | L8: =IF(K8>1,_xlfn.CONCAT("Se repite ",K8," veces"),"No se repite") -> Se repite 5 veces | M8: =_xlfn.CONCAT(A8,"-",E8) -> Tradiciones Andinas-AjiNomoto Bolsa 1Kg x 18 | N8: =COUNTIF($M$2:$M$1438,M8) -> 4 | O8: =IF(N8>1,_xlfn.CONCAT("Se repite ",N8," veces en ",A8),"No se repite en proveedor") -> Se repite 4 veces en Tradiciones Andinas | P8: =_xlfn.CONCAT(A8,"-",E8,"-",H8) -> Tradiciones Andinas-AjiNomoto Bolsa 1Kg x 18-85 | Q8: =COUNTIF($P$2:$P$1438,P8) -> 4 | R8: =IF(Q8>1,_xlfn.CONCAT("Se repite ",Q8," veces el precio de ",H8),"No se repite") -> Se repite 4 veces el precio de 85 | S8: =_xlfn.CONCAT("El producto ",E8," ",O8,IF(R8="No se repite",_xlfn.CONCAT(" Una vez con el precio ",H8),_xlfn.CONCAT(", ",R8))) -> El producto AjiNomoto Bolsa 1Kg x 18 Se repite 4 veces en Tradiciones Andinas, Se repite 4 veces el precio de 85 | T8: =+A8 -> Tradiciones Andinas | U8: =+E8 -> AjiNomoto Bolsa 1Kg x 18 | V8: =+H8 -> 85 | W8: =_xlfn.CONCAT(A8," ",B8) -> Tradiciones Andinas 09/24/2025 | Z8: =G8*H8 -> 85
A9: Tradiciones Andinas | B9: 11/28/2025 | C9: Bill | D9: 492743 | E9: AjiNomoto Bolsa 1Kg x 18 | F9: AjiNomoto Bolsa 1Kg x 18 / 7754487118804 / 00803 / AB-11 | G9: 2 | H9: 85 | I9: 170 | J9: 107432.13 | K9: =COUNTIF($E$2:$E$1438,E9) -> 5 | L9: =IF(K9>1,_xlfn.CONCAT("Se repite ",K9," veces"),"No se repite") -> Se repite 5 veces | M9: =_xlfn.CONCAT(A9,"-",E9) -> Tradiciones Andinas-AjiNomoto Bolsa 1Kg x 18 | N9: =COUNTIF($M$2:$M$1438,M9) -> 4 | O9: =IF(N9>1,_xlfn.CONCAT("Se repite ",N9," veces en ",A9),"No se repite en proveedor") -> Se repite 4 veces en Tradiciones Andinas | P9: =_xlfn.CONCAT(A9,"-",E9,"-",H9) -> Tradiciones Andinas-AjiNomoto Bolsa 1Kg x 18-85 | Q9: =COUNTIF($P$2:$P$1438,P9) -> 4 | R9: =IF(Q9>1,_xlfn.CONCAT("Se repite ",Q9," veces el precio de ",H9),"No se repite") -> Se repite 4 veces el precio de 85 | S9: =_xlfn.CONCAT("El producto ",E9," ",O9,IF(R9="No se repite",_xlfn.CONCAT(" Una vez con el precio ",H9),_xlfn.CONCAT(", ",R9))) -> El producto AjiNomoto Bolsa 1Kg x 18 Se repite 4 veces en Tradiciones Andinas, Se repite 4 veces el precio de 85 | T9: =+A9 -> Tradiciones Andinas | U9: =+E9 -> AjiNomoto Bolsa 1Kg x 18 | V9: =+H9 -> 85 | W9: =_xlfn.CONCAT(A9," ",B9) -> Tradiciones Andinas 11/28/2025 | Z9: =G9*H9 -> 170
A10: Belmont International Trading Corp | B10: 04/28/2025 | C10: Bill | D10: 64308 | E10: Ajinomoto Bolsa 250gr x 60 | F10: TA- PERU - CONDIMENT PRODUCTS - MSG -AJINOMOTO- 60 / 250gr - 00995 | G10: 1 | H10: 90 | I10: 90 | J10: 1085.8 | K10: =COUNTIF($E$2:$E$1438,E10) -> 7 | L10: =IF(K10>1,_xlfn.CONCAT("Se repite ",K10," veces"),"No se repite") -> Se repite 7 veces | M10: =_xlfn.CONCAT(A10,"-",E10) -> Belmont International Trading Corp-Ajinomoto Bolsa 250gr x 60 | N10: =COUNTIF($M$2:$M$1438,M10) -> 1 | O10: =IF(N10>1,_xlfn.CONCAT("Se repite ",N10," veces en ",A10),"No se repite en proveedor") -> No se repite en proveedor | P10: =_xlfn.CONCAT(A10,"-",E10,"-",H10) -> Belmont International Trading Corp-Ajinomoto Bolsa 250gr x 60-90 | Q10: =COUNTIF($P$2:$P$1438,P10) -> 1 | R10: =IF(Q10>1,_xlfn.CONCAT("Se repite ",Q10," veces el precio de ",H10),"No se repite") -> No se repite | S10: =_xlfn.CONCAT("El producto ",E10," ",O10,IF(R10="No se repite",_xlfn.CONCAT(" Una vez con el precio ",H10),_xlfn.CONCAT(", ",R10))) -> El producto Ajinomoto Bolsa 250gr x 60 No se repite en proveedor Una vez con el precio 90 | T10: =+A10 -> Belmont International Trading Corp | U10: =+E10 -> Ajinomoto Bolsa 250gr x 60 | V10: =+H10 -> 90 | W10: =_xlfn.CONCAT(A10," ",B10) -> Belmont International Trading Corp 04/28/2025 | Z10: =G10*H10 -> 90
A11: Peru Chef | B11: 03/26/2025 | C11: Bill | E11: Ajinomoto Bolsa 250gr x 60 | F11: MSG -AJINOMOTO | G11: 1 | H11: 99 | I11: 99 | J11: 984.8 | K11: =COUNTIF($E$2:$E$1438,E11) -> 7 | L11: =IF(K11>1,_xlfn.CONCAT("Se repite ",K11," veces"),"No se repite") -> Se repite 7 veces | M11: =_xlfn.CONCAT(A11,"-",E11) -> Peru Chef-Ajinomoto Bolsa 250gr x 60 | N11: =COUNTIF($M$2:$M$1438,M11) -> 2 | O11: =IF(N11>1,_xlfn.CONCAT("Se repite ",N11," veces en ",A11),"No se repite en proveedor") -> Se repite 2 veces en Peru Chef | P11: =_xlfn.CONCAT(A11,"-",E11,"-",H11) -> Peru Chef-Ajinomoto Bolsa 250gr x 60-99 | Q11: =COUNTIF($P$2:$P$1438,P11) -> 2 | R11: =IF(Q11>1,_xlfn.CONCAT("Se repite ",Q11," veces el precio de ",H11),"No se repite") -> Se repite 2 veces el precio de 99 | S11: =_xlfn.CONCAT("El producto ",E11," ",O11,IF(R11="No se repite",_xlfn.CONCAT(" Una vez con el precio ",H11),_xlfn.CONCAT(", ",R11))) -> El producto Ajinomoto Bolsa 250gr x 60 Se repite 2 veces en Peru Chef, Se repite 2 veces el precio de 99 | T11: =+A11 -> Peru Chef | U11: =+E11 -> Ajinomoto Bolsa 250gr x 60 | V11: =+H11 -> 99 | W11: =_xlfn.CONCAT(A11," ",B11) -> Peru Chef 03/26/2025 | Z11: =G11*H11 -> 99
A12: Peru Chef | B12: 04/10/2025 | C12: Bill | D12: 55130 | E12: Ajinomoto Bolsa 250gr x 60 | F12: MSG -AJINOMOTO | G12: 1 | H12: 99 | I12: 99 | J12: 3231 | K12: =COUNTIF($E$2:$E$1438,E12) -> 7 | L12: =IF(K12>1,_xlfn.CONCAT("Se repite ",K12," veces"),"No se repite") -> Se repite 7 veces | M12: =_xlfn.CONCAT(A12,"-",E12) -> Peru Chef-Ajinomoto Bolsa 250gr x 60 | N12: =COUNTIF($M$2:$M$1438,M12) -> 2 | O12: =IF(N12>1,_xlfn.CONCAT("Se repite ",N12," veces en ",A12),"No se repite en proveedor") -> Se repite 2 veces en Peru Chef | P12: =_xlfn.CONCAT(A12,"-",E12,"-",H12) -> Peru Chef-Ajinomoto Bolsa 250gr x 60-99 | Q12: =COUNTIF($P$2:$P$1438,P12) -> 2 | R12: =IF(Q12>1,_xlfn.CONCAT("Se repite ",Q12," veces el precio de ",H12),"No se repite") -> Se repite 2 veces el precio de 99 | S12: =_xlfn.CONCAT("El producto ",E12," ",O12,IF(R12="No se repite",_xlfn.CONCAT(" Una vez con el precio ",H12),_xlfn.CONCAT(", ",R12))) -> El producto Ajinomoto Bolsa 250gr x 60 Se repite 2 veces en Peru Chef, Se repite 2 veces el precio de 99 | T12: =+A12 -> Peru Chef | U12: =+E12 -> Ajinomoto Bolsa 250gr x 60 | V12: =+H12 -> 99 | W12: =_xlfn.CONCAT(A12," ",B12) -> Peru Chef 04/10/2025 | Z12: =G12*H12 -> 99
A13: Tradiciones Andinas | B13: 04/25/2025 | C13: Bill | D13: 476974 | E13: Ajinomoto Bolsa 250gr x 60 | F13: MSG -AJINOMOTO | G13: 3 | H13: 69 | I13: 207 | J13: 14449.28 | K13: =COUNTIF($E$2:$E$1438,E13) -> 7 | L13: =IF(K13>1,_xlfn.CONCAT("Se repite ",K13," veces"),"No se repite") -> Se repite 7 veces | M13: =_xlfn.CONCAT(A13,"-",E13) -> Tradiciones Andinas-Ajinomoto Bolsa 250gr x 60 | N13: =COUNTIF($M$2:$M$1438,M13) -> 4 | O13: =IF(N13>1,_xlfn.CONCAT("Se repite ",N13," veces en ",A13),"No se repite en proveedor") -> Se repite 4 veces en Tradiciones Andinas | P13: =_xlfn.CONCAT(A13,"-",E13,"-",H13) -> Tradiciones Andinas-Ajinomoto Bolsa 250gr x 60-69 | Q13: =COUNTIF($P$2:$P$1438,P13) -> 1 | R13: =IF(Q13>1,_xlfn.CONCAT("Se repite ",Q13," veces el precio de ",H13),"No se repite") -> No se repite | S13: =_xlfn.CONCAT("El producto ",E13," ",O13,IF(R13="No se repite",_xlfn.CONCAT(" Una vez con el precio ",H13),_xlfn.CONCAT(", ",R13))) -> El producto Ajinomoto Bolsa 250gr x 60 Se repite 4 veces en Tradiciones Andinas Una vez con el precio 69 | T13: =+A13 -> Tradiciones Andinas | U13: =+E13 -> Ajinomoto Bolsa 250gr x 60 | V13: =+H13 -> 69 | W13: =_xlfn.CONCAT(A13," ",B13) -> Tradiciones Andinas 04/25/2025 | Z13: =G13*H13 -> 207
A14: Tradiciones Andinas | B14: 06/12/2025 | C14: Bill | D14: 480295 | E14: Ajinomoto Bolsa 250gr x 60 | F14: TA- PERU - CONDIMENT PRODUCTS - MSG -AJINOMOTO- 60 / 250gr - 00995 | G14: 5 | H14: 73.8 | I14: 369 | J14: 38531.68 | K14: =COUNTIF($E$2:$E$1438,E14) -> 7 | L14: =IF(K14>1,_xlfn.CONCAT("Se repite ",K14," veces"),"No se repite") -> Se repite 7 veces | M14: =_xlfn.CONCAT(A14,"-",E14) -> Tradiciones Andinas-Ajinomoto Bolsa 250gr x 60 | N14: =COUNTIF($M$2:$M$1438,M14) -> 4 | O14: =IF(N14>1,_xlfn.CONCAT("Se repite ",N14," veces en ",A14),"No se repite en proveedor") -> Se repite 4 veces en Tradiciones Andinas | P14: =_xlfn.CONCAT(A14,"-",E14,"-",H14) -> Tradiciones Andinas-Ajinomoto Bolsa 250gr x 60-73.8 | Q14: =COUNTIF($P$2:$P$1438,P14) -> 3 | R14: =IF(Q14>1,_xlfn.CONCAT("Se repite ",Q14," veces el precio de ",H14),"No se repite") -> Se repite 3 veces el precio de 73.8 | S14: =_xlfn.CONCAT("El producto ",E14," ",O14,IF(R14="No se repite",_xlfn.CONCAT(" Una vez con el precio ",H14),_xlfn.CONCAT(", ",R14))) -> El producto Ajinomoto Bolsa 250gr x 60 Se repite 4 veces en Tradiciones Andinas, Se repite 3 veces el precio de 73.8 | T14: =+A14 -> Tradiciones Andinas | U14: =+E14 -> Ajinomoto Bolsa 250gr x 60 | V14: =+H14 -> 73.8 | W14: =_xlfn.CONCAT(A14," ",B14) -> Tradiciones Andinas 06/12/2025 | Z14: =G14*H14 -> 369
A15: Tradiciones Andinas | B15: 09/24/2025 | C15: Bill | D15: 487860 | E15: Ajinomoto Bolsa 250gr x 60 | F15: TA- PERU - CONDIMENT PRODUCTS - MSG -AJINOMOTO- 60 / 250gr - 00995 | G15: 3 | H15: 73.8 | I15: 221.4 | J15: 80614.94 | K15: =COUNTIF($E$2:$E$1438,E15) -> 7 | L15: =IF(K15>1,_xlfn.CONCAT("Se repite ",K15," veces"),"No se repite") -> Se repite 7 veces | M15: =_xlfn.CONCAT(A15,"-",E15) -> Tradiciones Andinas-Ajinomoto Bolsa 250gr x 60 | N15: =COUNTIF($M$2:$M$1438,M15) -> 4 | O15: =IF(N15>1,_xlfn.CONCAT("Se repite ",N15," veces en ",A15),"No se repite en proveedor") -> Se repite 4 veces en Tradiciones Andinas | P15: =_xlfn.CONCAT(A15,"-",E15,"-",H15) -> Tradiciones Andinas-Ajinomoto Bolsa 250gr x 60-73.8 | Q15: =COUNTIF($P$2:$P$1438,P15) -> 3 | R15: =IF(Q15>1,_xlfn.CONCAT("Se repite ",Q15," veces el precio de ",H15),"No se repite") -> Se repite 3 veces el precio de 73.8 | S15: =_xlfn.CONCAT("El producto ",E15," ",O15,IF(R15="No se repite",_xlfn.CONCAT(" Una vez con el precio ",H15),_xlfn.CONCAT(", ",R15))) -> El producto Ajinomoto Bolsa 250gr x 60 Se repite 4 veces en Tradiciones Andinas, Se repite 3 veces el precio de 73.8 | T15: =+A15 -> Tradiciones Andinas | U15: =+E15 -> Ajinomoto Bolsa 250gr x 60 | V15: =+H15 -> 73.8 | W15: =_xlfn.CONCAT(A15," ",B15) -> Tradiciones Andinas 09/24/2025 | Z15: =G15*H15 -> 221.4
A16: Tradiciones Andinas | B16: 11/28/2025 | C16: Bill | D16: 492743 | E16: Ajinomoto Bolsa 250gr x 60 | F16: TA- PERU - CONDIMENT PRODUCTS - MSG -AJINOMOTO- 60 / 250gr - 00995 | G16: 4 | H16: 73.8 | I16: 295.2 | J16: 107262.13 | K16: =COUNTIF($E$2:$E$1438,E16) -> 7 | L16: =IF(K16>1,_xlfn.CONCAT("Se repite ",K16," veces"),"No se repite") -> Se repite 7 veces | M16: =_xlfn.CONCAT(A16,"-",E16) -> Tradiciones Andinas-Ajinomoto Bolsa 250gr x 60 | N16: =COUNTIF($M$2:$M$1438,M16) -> 4 | O16: =IF(N16>1,_xlfn.CONCAT("Se repite ",N16," veces en ",A16),"No se repite en proveedor") -> Se repite 4 veces en Tradiciones Andinas | P16: =_xlfn.CONCAT(A16,"-",E16,"-",H16) -> Tradiciones Andinas-Ajinomoto Bolsa 250gr x 60-73.8 | Q16: =COUNTIF($P$2:$P$1438,P16) -> 3 | R16: =IF(Q16>1,_xlfn.CONCAT("Se repite ",Q16," veces el precio de ",H16),"No se repite") -> Se repite 3 veces el precio de 73.8 | S16: =_xlfn.CONCAT("El producto ",E16," ",O16,IF(R16="No se repite",_xlfn.CONCAT(" Una vez con el precio ",H16),_xlfn.CONCAT(", ",R16))) -> El producto Ajinomoto Bolsa 250gr x 60 Se repite 4 veces en Tradiciones Andinas, Se repite 3 veces el precio de 73.8 | T16: =+A16 -> Tradiciones Andinas | U16: =+E16 -> Ajinomoto Bolsa 250gr x 60 | V16: =+H16 -> 73.8 | W16: =_xlfn.CONCAT(A16," ",B16) -> Tradiciones Andinas 11/28/2025 | Z16: =G16*H16 -> 295.2
A17: Tradiciones Andinas | B17: 04/25/2025 | C17: Bill | D17: 476974 | E17: AjiNomoto Bolsa 500g x 30 | F17: AjiNomoto Bolsa 500g x 30 - TA | G17: 6 | H17: 71 | I17: 426 | J17: 14875.28 | K17: =COUNTIF($E$2:$E$1438,E17) -> 5 | L17: =IF(K17>1,_xlfn.CONCAT("Se repite ",K17," veces"),"No se repite") -> Se repite 5 veces | M17: =_xlfn.CONCAT(A17,"-",E17) -> Tradiciones Andinas-AjiNomoto Bolsa 500g x 30 | N17: =COUNTIF($M$2:$M$1438,M17) -> 5 | O17: =IF(N17>1,_xlfn.CONCAT("Se repite ",N17," veces en ",A17),"No se repite en proveedor") -> Se repite 5 veces en Tradiciones Andinas | P17: =_xlfn.CONCAT(A17,"-",E17,"-",H17) -> Tradiciones Andinas-AjiNomoto Bolsa 500g x 30-71 | Q17: =COUNTIF($P$2:$P$1438,P17) -> 1 | R17: =IF(Q17>1,_xlfn.CONCAT("Se repite ",Q17," veces el precio de ",H17),"No se repite") -> No se repite | S17: =_xlfn.CONCAT("El producto ",E17," ",O17,IF(R17="No se repite",_xlfn.CONCAT(" Una vez con el precio ",H17),_xlfn.CONCAT(", ",R17))) -> El producto AjiNomoto Bolsa 500g x 30 Se repite 5 veces en Tradiciones Andinas Una vez con el precio 71 | T17: =+A17 -> Tradiciones Andinas | U17: =+E17 -> AjiNomoto Bolsa 500g x 30 | V17: =+H17 -> 71 | W17: =_xlfn.CONCAT(A17," ",B17) -> Tradiciones Andinas 04/25/2025 | Z17: =G17*H17 -> 426
A18: Tradiciones Andinas | B18: 05/19/2025 | C18: Bill | D18: 478734 | E18: AjiNomoto Bolsa 500g x 30 | F18: T.A AjiNomoto Bolsa 500g x 30 / 00804 | G18: 2 | H18: 75.97 | I18: 151.94 | J18: 25794.28 | K18: =COUNTIF($E$2:$E$1438,E18) -> 5 | L18: =IF(K18>1,_xlfn.CONCAT("Se repite ",K18," veces"),"No se repite") -> Se repite 5 veces | M18: =_xlfn.CONCAT(A18,"-",E18) -> Tradiciones Andinas-AjiNomoto Bolsa 500g x 30 | N18: =COUNTIF($M$2:$M$1438,M18) -> 5 | O18: =IF(N18>1,_xlfn.CONCAT("Se repite ",N18," veces en ",A18),"No se repite en proveedor") -> Se repite 5 veces en Tradiciones Andinas | P18: =_xlfn.CONCAT(A18,"-",E18,"-",H18) -> Tradiciones Andinas-AjiNomoto Bolsa 500g x 30-75.97 | Q18: =COUNTIF($P$2:$P$1438,P18) -> 4 | R18: =IF(Q18>1,_xlfn.CONCAT("Se repite ",Q18," veces el precio de ",H18),"No se repite") -> Se repite 4 veces el precio de 75.97 | S18: =_xlfn.CONCAT("El producto ",E18," ",O18,IF(R18="No se repite",_xlfn.CONCAT(" Una vez con el precio ",H18),_xlfn.CONCAT(", ",R18))) -> El producto AjiNomoto Bolsa 500g x 30 Se repite 5 veces en Tradiciones Andinas, Se repite 4 veces el precio de 75.97 | T18: =+A18 -> Tradiciones Andinas | U18: =+E18 -> AjiNomoto Bolsa 500g x 30 | V18: =+H18 -> 75.97 | W18: =_xlfn.CONCAT(A18," ",B18) -> Tradiciones Andinas 05/19/2025 | Z18: =G18*H18 -> 151.94
A19: Tradiciones Andinas | B19: 06/12/2025 | C19: Bill | D19: 480295 | E19: AjiNomoto Bolsa 500g x 30 | F19: T.A AjiNomoto Bolsa 500g x 30 / 00804 | G19: 1 | H19: 75.97 | I19: 75.97 | J19: 38692.65 | K19: =COUNTIF($E$2:$E$1438,E19) -> 5 | L19: =IF(K19>1,_xlfn.CONCAT("Se repite ",K19," veces"),"No se repite") -> Se repite 5 veces | M19: =_xlfn.CONCAT(A19,"-",E19) -> Tradiciones Andinas-AjiNomoto Bolsa 500g x 30 | N19: =COUNTIF($M$2:$M$1438,M19) -> 5 | O19: =IF(N19>1,_xlfn.CONCAT("Se repite ",N19," veces en ",A19),"No se repite en proveedor") -> Se repite 5 veces en Tradiciones Andinas | P19: =_xlfn.CONCAT(A19,"-",E19,"-",H19) -> Tradiciones Andinas-AjiNomoto Bolsa 500g x 30-75.97 | Q19: =COUNTIF($P$2:$P$1438,P19) -> 4 | R19: =IF(Q19>1,_xlfn.CONCAT("Se repite ",Q19," veces el precio de ",H19),"No se repite") -> Se repite 4 veces el precio de 75.97 | S19: =_xlfn.CONCAT("El producto ",E19," ",O19,IF(R19="No se repite",_xlfn.CONCAT(" Una vez con el precio ",H19),_xlfn.CONCAT(", ",R19))) -> El producto AjiNomoto Bolsa 500g x 30 Se repite 5 veces en Tradiciones Andinas, Se repite 4 veces el precio de 75.97 | T19: =+A19 -> Tradiciones Andinas | U19: =+E19 -> AjiNomoto Bolsa 500g x 30 | V19: =+H19 -> 75.97 | W19: =_xlfn.CONCAT(A19," ",B19) -> Tradiciones Andinas 06/12/2025 | Z19: =G19*H19 -> 75.97
A20: Tradiciones Andinas | B20: 07/03/2025 | C20: Bill | D20: 482005 | E20: AjiNomoto Bolsa 500g x 30 | F20: T.A AjiNomoto Bolsa 500g x 30 / 00804 | G20: 4 | H20: 75.97 | I20: 303.88 | J20: 50699.51 | K20: =COUNTIF($E$2:$E$1438,E20) -> 5 | L20: =IF(K20>1,_xlfn.CONCAT("Se repite ",K20," veces"),"No se repite") -> Se repite 5 veces | M20: =_xlfn.CONCAT(A20,"-",E20) -> Tradiciones Andinas-AjiNomoto Bolsa 500g x 30 | N20: =COUNTIF($M$2:$M$1438,M20) -> 5 | O20: =IF(N20>1,_xlfn.CONCAT("Se repite ",N20," veces en ",A20),"No se repite en proveedor") -> Se repite 5 veces en Tradiciones Andinas | P20: =_xlfn.CONCAT(A20,"-",E20,"-",H20) -> Tradiciones Andinas-AjiNomoto Bolsa 500g x 30-75.97 | Q20: =COUNTIF($P$2:$P$1438,P20) -> 4 | R20: =IF(Q20>1,_xlfn.CONCAT("Se repite ",Q20," veces el precio de ",H20),"No se repite") -> Se repite 4 veces el precio de 75.97 | S20: =_xlfn.CONCAT("El producto ",E20," ",O20,IF(R20="No se repite",_xlfn.CONCAT(" Una vez con el precio ",H20),_xlfn.CONCAT(", ",R20))) -> El producto AjiNomoto Bolsa 500g x 30 Se repite 5 veces en Tradiciones Andinas, Se repite 4 veces el precio de 75.97 | T20: =+A20 -> Tradiciones Andinas | U20: =+E20 -> AjiNomoto Bolsa 500g x 30 | V20: =+H20 -> 75.97 | W20: =_xlfn.CONCAT(A20," ",B20) -> Tradiciones Andinas 07/03/2025 | Z20: =G20*H20 -> 303.88
A21: Tradiciones Andinas | B21: 09/24/2025 | C21: Bill | D21: 487860 | E21: AjiNomoto Bolsa 500g x 30 | F21: T.A AjiNomoto Bolsa 500g x 30 / 00804 | G21: 3 | H21: 75.97 | I21: 227.91 | J21: 80927.85 | K21: =COUNTIF($E$2:$E$1438,E21) -> 5 | L21: =IF(K21>1,_xlfn.CONCAT("Se repite ",K21," veces"),"No se repite") -> Se repite 5 veces | M21: =_xlfn.CONCAT(A21,"-",E21) -> Tradiciones Andinas-AjiNomoto Bolsa 500g x 30 | N21: =COUNTIF($M$2:$M$1438,M21) -> 5 | O21: =IF(N21>1,_xlfn.CONCAT("Se repite ",N21," veces en ",A21),"No se repite en proveedor") -> Se repite 5 veces en Tradiciones Andinas | P21: =_xlfn.CONCAT(A21,"-",E21,"-",H21) -> Tradiciones Andinas-AjiNomoto Bolsa 500g x 30-75.97 | Q21: =COUNTIF($P$2:$P$1438,P21) -> 4 | R21: =IF(Q21>1,_xlfn.CONCAT("Se repite ",Q21," veces el precio de ",H21),"No se repite") -> Se repite 4 veces el precio de 75.97 | S21: =_xlfn.CONCAT("El producto ",E21," ",O21,IF(R21="No se repite",_xlfn.CONCAT(" Una vez con el precio ",H21),_xlfn.CONCAT(", ",R21))) -> El producto AjiNomoto Bolsa 500g x 30 Se repite 5 veces en Tradiciones Andinas, Se repite 4 veces el precio de 75.97 | T21: =+A21 -> Tradiciones Andinas | U21: =+E21 -> AjiNomoto Bolsa 500g x 30 | V21: =+H21 -> 75.97 | W21: =_xlfn.CONCAT(A21," ",B21) -> Tradiciones Andinas 09/24/2025 | Z21: =G21*H21 -> 227.91
A22: Belmont International Trading Corp | B22: 04/28/2025 | C22: Bill | D22: 64308 | E22: AJINOSIYAO 500ml x 24 | F22: TA- PERU - CONDIMENT PRODUCTS - AJI NO Siyau- 24 / 500 ml - 00999 | G22: 1 | H22: 50.4 | I22: 50.4 | J22: 995.8 | K22: =COUNTIF($E$2:$E$1438,E22) -> 5 | L22: =IF(K22>1,_xlfn.CONCAT("Se repite ",K22," veces"),"No se repite") -> Se repite 5 veces | M22: =_xlfn.CONCAT(A22,"-",E22) -> Belmont International Trading Corp-AJINOSIYAO 500ml x 24 | N22: =COUNTIF($M$2:$M$1438,M22) -> 1 | O22: =IF(N22>1,_xlfn.CONCAT("Se repite ",N22," veces en ",A22),"No se repite en proveedor") -> No se repite en proveedor | P22: =_xlfn.CONCAT(A22,"-",E22,"-",H22) -> Belmont International Trading Corp-AJINOSIYAO 500ml x 24-50.4 | Q22: =COUNTIF($P$2:$P$1438,P22) -> 1 | R22: =IF(Q22>1,_xlfn.CONCAT("Se repite ",Q22," veces el precio de ",H22),"No se repite") -> No se repite | S22: =_xlfn.CONCAT("El producto ",E22," ",O22,IF(R22="No se repite",_xlfn.CONCAT(" Una vez con el precio ",H22),_xlfn.CONCAT(", ",R22))) -> El producto AJINOSIYAO 500ml x 24 No se repite en proveedor Una vez con el precio 50.4 | T22: =+A22 -> Belmont International Trading Corp | U22: =+E22 -> AJINOSIYAO 500ml x 24 | V22: =+H22 -> 50.4 | W22: =_xlfn.CONCAT(A22," ",B22) -> Belmont International Trading Corp 04/28/2025 | Z22: =G22*H22 -> 50.4
A23: Peru Chef | B23: 08/11/2025 | C23: Bill | D23: 56352 | E23: AJINOSIYAO 500ml x 24 | F23: TA- PERU - CONDIMENT PRODUCTS - AJI NO Siyau- 24 / 500 ml - 00999 | G23: 1 | H23: 45 | I23: 45 | J23: 14643.5 | K23: =COUNTIF($E$2:$E$1438,E23) -> 5 | L23: =IF(K23>1,_xlfn.CONCAT("Se repite ",K23," veces"),"No se repite") -> Se repite 5 veces | M23: =_xlfn.CONCAT(A23,"-",E23) -> Peru Chef-AJINOSIYAO 500ml x 24 | N23: =COUNTIF($M$2:$M$1438,M23) -> 1 | O23: =IF(N23>1,_xlfn.CONCAT("Se repite ",N23," veces en ",A23),"No se repite en proveedor") -> No se repite en proveedor | P23: =_xlfn.CONCAT(A23,"-",E23,"-",H23) -> Peru Chef-AJINOSIYAO 500ml x 24-45 | Q23: =COUNTIF($P$2:$P$1438,P23) -> 1 | R23: =IF(Q23>1,_xlfn.CONCAT("Se repite ",Q23," veces el precio de ",H23),"No se repite") -> No se repite | S23: =_xlfn.CONCAT("El producto ",E23," ",O23,IF(R23="No se repite",_xlfn.CONCAT(" Una vez con el precio ",H23),_xlfn.CONCAT(", ",R23))) -> El producto AJINOSIYAO 500ml x 24 No se repite en proveedor Una vez con el precio 45 | T23: =+A23 -> Peru Chef | U23: =+E23 -> AJINOSIYAO 500ml x 24 | V23: =+H23 -> 45 | W23: =_xlfn.CONCAT(A23," ",B23) -> Peru Chef 08/11/2025 | Z23: =G23*H23 -> 45
... A26: Tradiciones Andinas | B26: 11/28/2025 | C26: Bill | D26: 492743 | E26: AJINOSIYAO 500ml x 24 | F26: TA- PERU - CONDIMENT PRODUCTS - AJI NO Siyau- 24 / 500 ml - 00999 | G26: 3 | H26: 28.8 | I26: 86.4 | J26: 107518.53 | K26: =COUNTIF($E$2:$E$1438,E26) -> 5 | L26: =IF(K26>1,_xlfn.CONCAT("Se repite ",K26," veces"),"No se repite") -> Se repite 5 veces | M26: =_xlfn.CONCAT(A26,"-",E26) -> Tradiciones Andinas-AJINOSIYAO 500ml x 24 | N26: =COUNTIF($M$2:$M$1438,M26) -> 3 | O26: =IF(N26>1,_xlfn.CONCAT("Se repite ",N26," veces en ",A26),"No se repite en proveedor") -> Se repite 3 veces en Tradiciones Andinas | P26: =_xlfn.CONCAT(A26,"-",E26,"-",H26) -> Tradiciones Andinas-AJINOSIYAO 500ml x 24-28.8 | Q26: =COUNTIF($P$2:$P$1438,P26) -> 3 | R26: =IF(Q26>1,_xlfn.CONCAT("Se repite ",Q26," veces el precio de ",H26),"No se repite") -> Se repite 3 veces el precio de 28.8 | S26: =_xlfn.CONCAT("El producto ",E26," ",O26,IF(R26="No se repite",_xlfn.CONCAT(" Una vez con el precio ",H26),_xlfn.CONCAT(", ",R26))) -> El producto AJINOSIYAO 500ml x 24 Se repite 3 veces en Tradiciones Andinas, Se repite 3 veces el precio de 28.8 | T26: =+A26 -> Tradiciones Andinas | U26: =+E26 -> AJINOSIYAO 500ml x 24 | V26: =+H26 -> 28.8 | W26: =_xlfn.CONCAT(A26," ",B26) -> Tradiciones Andinas 11/28/2025 | Z26: =G26*H26 -> 86.4
A27: Tradiciones Andinas | B27: 04/10/2025 | C27: Bill | E27: Arrocito Atomico 150gr x 20 (5.3oz) x 20 | F27: Arrocito Atomico | G27: 2 | H27: 20 | I27: 40 | J27: 6965.64 | K27: =COUNTIF($E$2:$E$1438,E27) -> 2 | L27: =IF(K27>1,_xlfn.CONCAT("Se repite ",K27," veces"),"No se repite") -> Se repite 2 veces | M27: =_xlfn.CONCAT(A27,"-",E27) -> Tradiciones Andinas-Arrocito Atomico 150gr x 20 (5.3oz) x 20 | N27: =COUNTIF($M$2:$M$1438,M27) -> 2 | O27: =IF(N27>1,_xlfn.CONCAT("Se repite ",N27," veces en ",A27),"No se repite en proveedor") -> Se repite 2 veces en Tradiciones Andinas | P27: =_xlfn.CONCAT(A27,"-",E27,"-",H27) -> Tradiciones Andinas-Arrocito Atomico 150gr x 20 (5.3oz) x 20-20 | Q27: =COUNTIF($P$2:$P$1438,P27) -> 1 | R27: =IF(Q27>1,_xlfn.CONCAT("Se repite ",Q27," veces el precio de ",H27),"No se repite") -> No se repite | S27: =_xlfn.CONCAT("El producto ",E27," ",O27,IF(R27="No se repite",_xlfn.CONCAT(" Una vez con el precio ",H27),_xlfn.CONCAT(", ",R27))) -> El producto Arrocito Atomico 150gr x 20 (5.3oz) x 20 Se repite 2 veces en Tradiciones Andinas Una vez con el precio 20 | T27: =+A27 -> Tradiciones Andinas | U27: =+E27 -> Arrocito Atomico 150gr x 20 (5.3oz) x 20 | V27: =+H27 -> 20 | W27: =_xlfn.CONCAT(A27," ",B27) -> Tradiciones Andinas 04/10/2025 | Z27: =G27*H27 -> 40
A28: Tradiciones Andinas | B28: 12/03/2025 | C28: Bill | D28: 493132 | E28: Arrocito Atomico 150gr x 20 (5.3oz) x 20 | F28: TA- PERU - GOLOSINAS - DULCES - Arrocito Atomico- 20 / 150g - CH146 | G28: 2 | H28: 21.4 | I28: 42.8 | J28: 118453.32 | K28: =COUNTIF($E$2:$E$1438,E28) -> 2 | L28: =IF(K28>1,_xlfn.CONCAT("Se repite ",K28," veces"),"No se repite") -> Se repite 2 veces | M28: =_xlfn.CONCAT(A28,"-",E28) -> Tradiciones Andinas-Arrocito Atomico 150gr x 20 (5.3oz) x 20 | N28: =COUNTIF($M$2:$M$1438,M28) -> 2 | O28: =IF(N28>1,_xlfn.CONCAT("Se repite ",N28," veces en ",A28),"No se repite en proveedor") -> Se repite 2 veces en Tradiciones Andinas | P28: =_xlfn.CONCAT(A28,"-",E28,"-",H28) -> Tradiciones Andinas-Arrocito Atomico 150gr x 20 (5.3oz) x 20-21.4 | Q28: =COUNTIF($P$2:$P$1438,P28) -> 1 | R28: =IF(Q28>1,_xlfn.CONCAT("Se repite ",Q28," veces el precio de ",H28),"No se repite") -> No se repite | S28: =_xlfn.CONCAT("El producto ",E28," ",O28,IF(R28="No se repite",_xlfn.CONCAT(" Una vez con el precio ",H28),_xlfn.CONCAT(", ",R28))) -> El producto Arrocito Atomico 150gr x 20 (5.3oz) x 20 Se repite 2 veces en Tradiciones Andinas Una vez con el precio 21.4 | T28: =+A28 -> Tradiciones Andinas | U28: =+E28 -> Arrocito Atomico 150gr x 20 (5.3oz) x 20 | V28: =+H28 -> 21.4 | W28: =_xlfn.CONCAT(A28," ",B28) -> Tradiciones Andinas 12/03/2025 | Z28: =G28*H28 -> 42.8
A29: Peru Chef | B29: 03/26/2025 | C29: Bill | E29: Atun Florida Solido en aceite 6 oz X 48 | F29: Atun Florida 6 Oz X 48 | G29: 1 | H29: 82.5 | I29: 82.5 | J29: 885.8 | K29: =COUNTIF($E$2:$E$1438,E29) -> 6 | L29: =IF(K29>1,_xlfn.CONCAT("Se repite ",K29," veces"),"No se repite") -> Se repite 6 veces | M29: =_xlfn.CONCAT(A29,"-",E29) -> Peru Chef-Atun Florida Solido en aceite 6 oz X 48 | N29: =COUNTIF($M$2:$M$1438,M29) -> 6 | O29: =IF(N29>1,_xlfn.CONCAT("Se repite ",N29," veces en ",A29),"No se repite en proveedor") -> Se repite 6 veces en Peru Chef | P29: =_xlfn.CONCAT(A29,"-",E29,"-",H29) -> Peru Chef-Atun Florida Solido en aceite 6 oz X 48-82.5 | Q29: =COUNTIF($P$2:$P$1438,P29) -> 2 | R29: =IF(Q29>1,_xlfn.CONCAT("Se repite ",Q29," veces el precio de ",H29),"No se repite") -> Se repite 2 veces el precio de 82.5 | S29: =_xlfn.CONCAT("El producto ",E29," ",O29,IF(R29="No se repite",_xlfn.CONCAT(" Una vez con el precio ",H29),_xlfn.CONCAT(", ",R29))) -> El producto Atun Florida Solido en aceite 6 oz X 48 Se repite 6 veces en Peru Chef, Se repite 2 veces el precio de 82.5 | T29: =+A29 -> Peru Chef | U29: =+E29 -> Atun Florida Solido en aceite 6 oz X 48 | V29: =+H29 -> 82.5 | W29: =_xlfn.CONCAT(A29," ",B29) -> Peru Chef 03/26/2025 | Z29: =G29*H29 -> 82.5
A30: Peru Chef | B30: 04/10/2025 | C30: Bill | D30: 55130 | E30: Atun Florida Solido en aceite 6 oz X 48 | F30: Atun Florida Solido en aceite 6 Oz X 48 | G30: 1 | H30: 82.5 | I30: 82.5 | J30: 3132 | K30: =COUNTIF($E$2:$E$1438,E30) -> 6 | L30: =IF(K30>1,_xlfn.CONCAT("Se repite ",K30," veces"),"No se repite") -> Se repite 6 veces | M30: =_xlfn.CONCAT(A30,"-",E30) -> Peru Chef-Atun Florida Solido en aceite 6 oz X 48 | N30: =COUNTIF($M$2:$M$1438,M30) -> 6 | O30: =IF(N30>1,_xlfn.CONCAT("Se repite ",N30," veces en ",A30),"No se repite en proveedor") -> Se repite 6 veces en Peru Chef | P30: =_xlfn.CONCAT(A30,"-",E30,"-",H30) -> Peru Chef-Atun Florida Solido en aceite 6 oz X 48-82.5 | Q30: =COUNTIF($P$2:$P$1438,P30) -> 2 | R30: =IF(Q30>1,_xlfn.CONCAT("Se repite ",Q30," veces el precio de ",H30),"No se repite") -> Se repite 2 veces el precio de 82.5 | S30: =_xlfn.CONCAT("El producto ",E30," ",O30,IF(R30="No se repite",_xlfn.CONCAT(" Una vez con el precio ",H30),_xlfn.CONCAT(", ",R30))) -> El producto Atun Florida Solido en aceite 6 oz X 48 Se repite 6 veces en Peru Chef, Se repite 2 veces el precio de 82.5 | T30: =+A30 -> Peru Chef | U30: =+E30 -> Atun Florida Solido en aceite 6 oz X 48 | V30: =+H30 -> 82.5 | W30: =_xlfn.CONCAT(A30," ",B30) -> Peru Chef 04/10/2025 | Z30: =G30*H30 -> 82.5
A31: Peru Chef | B31: 04/24/2025 | C31: Bill | D31: 55372 | E31: Atun Florida Solido en aceite 6 oz X 48 | F31: CONSERVAS - - ATUN FLORIDA SOLIDO EN ACEITE 6 OZ X 48- LATA / 48 | G31: 2 | H31: 82 | I31: 164 | J31: 9496.7 | K31: =COUNTIF($E$2:$E$1438,E31) -> 6 | L31: =IF(K31>1,_xlfn.CONCAT("Se repite ",K31," veces"),"No se repite") -> Se repite 6 veces | M31: =_xlfn.CONCAT(A31,"-",E31) -> Peru Chef-Atun Florida Solido en aceite 6 oz X 48 | N31: =COUNTIF($M$2:$M$1438,M31) -> 6 | O31: =IF(N31>1,_xlfn.CONCAT("Se repite ",N31," veces en ",A31),"No se repite en proveedor") -> Se repite 6 veces en Peru Chef | P31: =_xlfn.CONCAT(A31,"-",E31,"-",H31) -> Peru Chef-Atun Florida Solido en aceite 6 oz X 48-82 | Q31: =COUNTIF($P$2:$P$1438,P31) -> 1 | R31: =IF(Q31>1,_xlfn.CONCAT("Se repite ",Q31," veces el precio de ",H31),"No se repite") -> No se repite | S31: =_xlfn.CONCAT("El producto ",E31," ",O31,IF(R31="No se repite",_xlfn.CONCAT(" Una vez con el precio ",H31),_xlfn.CONCAT(", ",R31))) -> El producto Atun Florida Solido en aceite 6 oz X 48 Se repite 6 veces en Peru Chef Una vez con el precio 82 | T31: =+A31 -> Peru Chef | U31: =+E31 -> Atun Florida Solido en aceite 6 oz X 48 | V31: =+H31 -> 82 | W31: =_xlfn.CONCAT(A31," ",B31) -> Peru Chef 04/24/2025 | Z31: =G31*H31 -> 164
A32: Peru Chef | B32: 10/28/2025 | C32: Bill | D32: 2025001895 | E32: Atun Florida Solido en aceite 6 oz X 48 | F32: CONSERVAS - - ATUN FLORIDA SOLIDO EN ACEITE 6 OZ X 48- LATA / 48 | G32: 2 | H32: 81 | I32: 162 | J32: 29879.5 | K32: =COUNTIF($E$2:$E$1438,E32) -> 6 | L32: =IF(K32>1,_xlfn.CONCAT("Se repite ",K32," veces"),"No se repite") -> Se repite 6 veces | M32: =_xlfn.CONCAT(A32,"-",E32) -> Peru Chef-Atun Florida Solido en aceite 6 oz X 48 | N32: =COUNTIF($M$2:$M$1438,M32) -> 6 | O32: =IF(N32>1,_xlfn.CONCAT("Se repite ",N32," veces en ",A32),"No se repite en proveedor") -> Se repite 6 veces en Peru Chef | P32: =_xlfn.CONCAT(A32,"-",E32,"-",H32) -> Peru Chef-Atun Florida Solido en aceite 6 oz X 48-81 | Q32: =COUNTIF($P$2:$P$1438,P32) -> 3 | R32: =IF(Q32>1,_xlfn.CONCAT("Se repite ",Q32," veces el precio de ",H32),"No se repite") -> Se repite 3 veces el precio de 81 | S32: =_xlfn.CONCAT("El producto ",E32," ",O32,IF(R32="No se repite",_xlfn.CONCAT(" Una vez con el precio ",H32),_xlfn.CONCAT(", ",R32))) -> El producto Atun Florida Solido en aceite 6 oz X 48 Se repite 6 veces en Peru Chef, Se repite 3 veces el precio de 81 | T32: =+A32 -> Peru Chef | U32: =+E32 -> Atun Florida Solido en aceite 6 oz X 48 | V32: =+H32 -> 81 | W32: =_xlfn.CONCAT(A32," ",B32) -> Peru Chef 10/28/2025 | Z32: =G32*H32 -> 162
A33: Peru Chef | B33: 11/14/2025 | C33: Bill | D33: 57055 | E33: Atun Florida Solido en aceite 6 oz X 48 | F33: CONSERVAS - - ATUN FLORIDA SOLIDO EN ACEITE 6 OZ X 48- LATA / 48 | G33: 2 | H33: 81 | I33: 162 | J33: 35454.55 | K33: =COUNTIF($E$2:$E$1438,E33) -> 6 | L33: =IF(K33>1,_xlfn.CONCAT("Se repite ",K33," veces"),"No se repite") -> Se repite 6 veces | M33: =_xlfn.CONCAT(A33,"-",E33) -> Peru Chef-Atun Florida Solido en aceite 6 oz X 48 | N33: =COUNTIF($M$2:$M$1438,M33) -> 6 | O33: =IF(N33>1,_xlfn.CONCAT("Se repite ",N33," veces en ",A33),"No se repite en proveedor") -> Se repite 6 veces en Peru Chef | P33: =_xlfn.CONCAT(A33,"-",E33,"-",H33) -> Peru Chef-Atun Florida Solido en aceite 6 oz X 48-81 | Q33: =COUNTIF($P$2:$P$1438,P33) -> 3 | R33: =IF(Q33>1,_xlfn.CONCAT("Se repite ",Q33," veces el precio de ",H33),"No se repite") -> Se repite 3 veces el precio de 81 | S33: =_xlfn.CONCAT("El producto ",E33," ",O33,IF(R33="No se repite",_xlfn.CONCAT(" Una vez con el precio ",H33),_xlfn.CONCAT(", ",R33))) -> El producto Atun Florida Solido en aceite 6 oz X 48 Se repite 6 veces en Peru Chef, Se repite 3 veces el precio de 81 | T33: =+A33 -> Peru Chef | U33: =+E33 -> Atun Florida Solido en aceite 6 oz X 48 | V33: =+H33 -> 81 | W33: =_xlfn.CONCAT(A33," ",B33) -> Peru Chef 11/14/2025 | Z33: =G33*H33 -> 162
A34: Peru Chef | B34: 12/09/2025 | C34: Bill | D34: 2025002373 | E34: Atun Florida Solido en aceite 6 oz X 48 | F34: CONSERVAS - - ATUN FLORIDA SOLIDO EN ACEITE 6 OZ X 48- LATA / 48 | G34: 2 | H34: 81 | I34: 162 | J34: 38934.85 | K34: =COUNTIF($E$2:$E$1438,E34) -> 6 | L34: =IF(K34>1,_xlfn.CONCAT("Se repite ",K34," veces"),"No se repite") -> Se repite 6 veces | M34: =_xlfn.CONCAT(A34,"-",E34) -> Peru Chef-Atun Florida Solido en aceite 6 oz X 48 | N34: =COUNTIF($M$2:$M$1438,M34) -> 6 | O34: =IF(N34>1,_xlfn.CONCAT("Se repite ",N34," veces en ",A34),"No se repite en proveedor") -> Se repite 6 veces en Peru Chef | P34: =_xlfn.CONCAT(A34,"-",E34,"-",H34) -> Peru Chef-Atun Florida Solido en aceite 6 oz X 48-81 | Q34: =COUNTIF($P$2:$P$1438,P34) -> 3 | R34: =IF(Q34>1,_xlfn.CONCAT("Se repite ",Q34," veces el precio de ",H34),"No se repite") -> Se repite 3 veces el precio de 81 | S34: =_xlfn.CONCAT("El producto ",E34," ",O34,IF(R34="No se repite",_xlfn.CONCAT(" Una vez con el precio ",H34),_xlfn.CONCAT(", ",R34))) -> El producto Atun Florida Solido en aceite 6 oz X 48 Se repite 6 veces en Peru Chef, Se repite 3 veces el precio de 81 | T34: =+A34 -> Peru Chef | U34: =+E34 -> Atun Florida Solido en aceite 6 oz X 48 | V34: =+H34 -> 81 | W34: =_xlfn.CONCAT(A34," ",B34) -> Peru Chef 12/09/2025 | Z34: =G34*H34 -> 162
A35: Belmont International Trading Corp | B35: 04/28/2025 | C35: Bill | D35: 64308 | E35: Belmont Aceituna Bidon 104oz x 6 | F35: BELMONT - Belmont Aceituna Bidon 104oz x 6 / OL-02 | G35: 1 | H35: 106 | I35: 106 | J35: 5468.44 | K35: =COUNTIF($E$2:$E$1438,E35) -> 2 | L35: =IF(K35>1,_xlfn.CONCAT("Se repite ",K35," veces"),"No se repite") -> Se repite 2 veces | M35: =_xlfn.CONCAT(A35,"-",E35) -> Belmont International Trading Corp-Belmont Aceituna Bidon 104oz x 6 | N35: =COUNTIF($M$2:$M$1438,M35) -> 2 | O35: =IF(N35>1,_xlfn.CONCAT("Se repite ",N35," veces en ",A35),"No se repite en proveedor") -> Se repite 2 veces en Belmont International Trading Corp | P35: =_xlfn.CONCAT(A35,"-",E35,"-",H35) -> Belmont International Trading Corp-Belmont Aceituna Bidon 104oz x 6-106 | Q35: =COUNTIF($P$2:$P$1438,P35) -> 2 | R35: =IF(Q35>1,_xlfn.CONCAT("Se repite ",Q35," veces el precio de ",H35),"No se repite") -> Se repite 2 veces el precio de 106 | S35: =_xlfn.CONCAT("El producto ",E35," ",O35,IF(R35="No se repite",_xlfn.CONCAT(" Una vez con el precio ",H35),_xlfn.CONCAT(", ",R35))) -> El producto Belmont Aceituna Bidon 104oz x 6 Se repite 2 veces en Belmont International Trading Corp, Se repite 2 veces el precio de 106 | T35: =+A35 -> Belmont International Trading Corp | U35: =+E35 -> Belmont Aceituna Bidon 104oz x 6 | V35: =+H35 -> 106 | W35: =_xlfn.CONCAT(A35," ",B35) -> Belmont International Trading Corp 04/28/2025 | Z35: =G35*H35 -> 106
A36: Belmont International Trading Corp | B36: 05/16/2025 | C36: Bill | D36: 65207 | E36: Belmont Aceituna Bidon 104oz x 6 | F36: BELMONT - Belmont Aceituna Bidon 104oz x 6 / OL-02 | G36: 4 | H36: 106 | I36: 424 | J36: 6973.74 | K36: =COUNTIF($E$2:$E$1438,E36) -> 2 | L36: =IF(K36>1,_xlfn.CONCAT("Se repite ",K36," veces"),"No se repite") -> Se repite 2 veces | M36: =_xlfn.CONCAT(A36,"-",E36) -> Belmont International Trading Corp-Belmont Aceituna Bidon 104oz x 6 | N36: =COUNTIF($M$2:$M$1438,M36) -> 2 | O36: =IF(N36>1,_xlfn.CONCAT("Se repite ",N36," veces en ",A36),"No se repite en proveedor") -> Se repite 2 veces en Belmont International Trading Corp | P36: =_xlfn.CONCAT(A36,"-",E36,"-",H36) -> Belmont International Trading Corp-Belmont Aceituna Bidon 104oz x 6-106 | Q36: =COUNTIF($P$2:$P$1438,P36) -> 2 | R36: =IF(Q36>1,_xlfn.CONCAT("Se repite ",Q36," veces el precio de ",H36),"No se repite") -> Se repite 2 veces el precio de 106 | S36: =_xlfn.CONCAT("El producto ",E36," ",O36,IF(R36="No se repite",_xlfn.CONCAT(" Una vez con el precio ",H36),_xlfn.CONCAT(", ",R36))) -> El producto Belmont Aceituna Bidon 104oz x 6 Se repite 2 veces en Belmont International Trading Corp, Se repite 2 veces el precio de 106 | T36: =+A36 -> Belmont International Trading Corp | U36: =+E36 -> Belmont Aceituna Bidon 104oz x 6 | V36: =+H36 -> 106 | W36: =_xlfn.CONCAT(A36," ",B36) -> Belmont International Trading Corp 05/16/2025 | Z36: =G36*H36 -> 424
A37: Belmont International Trading Corp | B37: 04/28/2025 | C37: Bill | D37: 64308 | E37: Belmont Aceituna Botija 20oz x 12 | F37: BELMONT - Belmont Aceituna Botija 20oz x 12 | G37: 2 | H37: 39 | I37: 78 | J37: 4746.8 | K37: =COUNTIF($E$2:$E$1438,E37) -> 2 | L37: =IF(K37>1,_xlfn.CONCAT("Se repite ",K37," veces"),"No se repite") -> Se repite 2 veces | M37: =_xlfn.CONCAT(A37,"-",E37) -> Belmont International Trading Corp-Belmont Aceituna Botija 20oz x 12 | N37: =COUNTIF($M$2:$M$1438,M37) -> 2 | O37: =IF(N37>1,_xlfn.CONCAT("Se repite ",N37," veces en ",A37),"No se repite en proveedor") -> Se repite 2 veces en Belmont International Trading Corp | P37: =_xlfn.CONCAT(A37,"-",E37,"-",H37) -> Belmont International Trading Corp-Belmont Aceituna Botija 20oz x 12-39 | Q37: =COUNTIF($P$2:$P$1438,P37) -> 2 | R37: =IF(Q37>1,_xlfn.CONCAT("Se repite ",Q37," veces el precio de ",H37),"No se repite") -> Se repite 2 veces el precio de 39 | S37: =_xlfn.CONCAT("El producto ",E37," ",O37,IF(R37="No se repite",_xlfn.CONCAT(" Una vez con el precio ",H37),_xlfn.CONCAT(", ",R37))) -> El producto Belmont Aceituna Botija 20oz x 12 Se repite 2 veces en Belmont International Trading Corp, Se repite 2 veces el precio de 39 | T37: =+A37 -> Belmont International Trading Corp | U37: =+E37 -> Belmont Aceituna Botija 20oz x 12 | V37: =+H37 -> 39 | W37: =_xlfn.CONCAT(A37," ",B37) -> Belmont International Trading Corp 04/28/2025 | Z37: =G37*H37 -> 78
A38: Belmont International Trading Corp | B38: 10/20/2025 | C38: Bill | D38: 72533 | E38: Belmont Aceituna Botija 20oz x 12 | F38: BELMONT - Belmont Aceituna Botija 20oz x 12 / OL-01 / 859174003863 | G38: 2 | H38: 39 | I38: 78 | J38: 20440.04 | K38: =COUNTIF($E$2:$E$1438,E38) -> 2 | L38: =IF(K38>1,_xlfn.CONCAT("Se repite ",K38," veces"),"No se repite") -> Se repite 2 veces | M38: =_xlfn.CONCAT(A38,"-",E38) -> Belmont International Trading Corp-Belmont Aceituna Botija 20oz x 12 | N38: =COUNTIF($M$2:$M$1438,M38) -> 2 | O38: =IF(N38>1,_xlfn.CONCAT("Se repite ",N38," veces en ",A38),"No se repite en proveedor") -> Se repite 2 veces en Belmont International Trading Corp | P38: =_xlfn.CONCAT(A38,"-",E38,"-",H38) -> Belmont International Trading Corp-Belmont Aceituna Botija 20oz x 12-39 | Q38: =COUNTIF($P$2:$P$1438,P38) -> 2 | R38: =IF(Q38>1,_xlfn.CONCAT("Se repite ",Q38," veces el precio de ",H38),"No se repite") -> Se repite 2 veces el precio de 39 | S38: =_xlfn.CONCAT("El producto ",E38," ",O38,IF(R38="No se repite",_xlfn.CONCAT(" Una vez con el precio ",H38),_xlfn.CONCAT(", ",R38))) -> El producto Belmont Aceituna Botija 20oz x 12 Se repite 2 veces en Belmont International Trading Corp, Se repite 2 veces el precio de 39 | T38: =+A38 -> Belmont International Trading Corp | U38: =+E38 -> Belmont Aceituna Botija 20oz x 12 | V38: =+H38 -> 39 | W38: =_xlfn.CONCAT(A38," ",B38) -> Belmont International Trading Corp 10/20/2025 | Z38: =G38*H38 -> 78
A39: Belmont International Trading Corp | B39: 04/28/2025 | C39: Bill | D39: 64308 | E39: Belmont Aderezo de Anticucho 16oz x 12 | F39: BELMONT -Belmont Aderezo de Anticucho 16oz x 12 / 859174003993 / PA-33 | G39: 1 | H39: 41 | I39: 41 | J39: 4811.3 | K39: =COUNTIF($E$2:$E$1438,E39) -> 2 | L39: =IF(K39>1,_xlfn.CONCAT("Se repite ",K39," veces"),"No se repite") -> Se repite 2 veces | M39: =_xlfn.CONCAT(A39,"-",E39) -> Belmont International Trading Corp-Belmont Aderezo de Anticucho 16oz x 12 | N39: =COUNTIF($M$2:$M$1438,M39) -> 2 | O39: =IF(N39>1,_xlfn.CONCAT("Se repite ",N39," veces en ",A39),"No se repite en proveedor") -> Se repite 2 veces en Belmont International Trading Corp | P39: =_xlfn.CONCAT(A39,"-",E39,"-",H39) -> Belmont International Trading Corp-Belmont Aderezo de Anticucho 16oz x 12-41 | Q39: =COUNTIF($P$2:$P$1438,P39) -> 1 | R39: =IF(Q39>1,_xlfn.CONCAT("Se repite ",Q39," veces el precio de ",H39),"No se repite") -> No se repite | S39: =_xlfn.CONCAT("El producto ",E39," ",O39,IF(R39="No se repite",_xlfn.CONCAT(" Una vez con el precio ",H39),_xlfn.CONCAT(", ",R39))) -> El producto Belmont Aderezo de Anticucho 16oz x 12 Se repite 2 veces en Belmont International Trading Corp Una vez con el precio 41 | T39: =+A39 -> Belmont International Trading Corp | U39: =+E39 -> Belmont Aderezo de Anticucho 16oz x 12 | V39: =+H39 -> 41 | W39: =_xlfn.CONCAT(A39," ",B39) -> Belmont International Trading Corp 04/28/2025 | Z39: =G39*H39 -> 41
A40: Belmont International Trading Corp | B40: 10/20/2025 | C40: Bill | D40: 72533 | E40: Belmont Aderezo de Anticucho 16oz x 12 | F40: BELMONT -Belmont Aderezo de Anticucho 16oz x 12 / 859174003993 / PA-33 | G40: 2 | H40: 45 | I40: 90 | J40: 20362.04 | K40: =COUNTIF($E$2:$E$1438,E40) -> 2 | L40: =IF(K40>1,_xlfn.CONCAT("Se repite ",K40," veces"),"No se repite") -> Se repite 2 veces | M40: =_xlfn.CONCAT(A40,"-",E40) -> Belmont International Trading Corp-Belmont Aderezo de Anticucho 16oz x 12 | N40: =COUNTIF($M$2:$M$1438,M40) -> 2 | O40: =IF(N40>1,_xlfn.CONCAT("Se repite ",N40," veces en ",A40),"No se repite en proveedor") -> Se repite 2 veces en Belmont International Trading Corp | P40: =_xlfn.CONCAT(A40,"-",E40,"-",H40) -> Belmont International Trading Corp-Belmont Aderezo de Anticucho 16oz x 12-45 | Q40: =COUNTIF($P$2:$P$1438,P40) -> 1 | R40: =IF(Q40>1,_xlfn.CONCAT("Se repite ",Q40," veces el precio de ",H40),"No se repite") -> No se repite | S40: =_xlfn.CONCAT("El producto ",E40," ",O40,IF(R40="No se repite",_xlfn.CONCAT(" Una vez con el precio ",H40),_xlfn.CONCAT(", ",R40))) -> El producto Belmont Aderezo de Anticucho 16oz x 12 Se repite 2 veces en Belmont International Trading Corp Una vez con el precio 45 | T40: =+A40 -> Belmont International Trading Corp | U40: =+E40 -> Belmont Aderezo de Anticucho 16oz x 12 | V40: =+H40 -> 45 | W40: =_xlfn.CONCAT(A40," ",B40) -> Belmont International Trading Corp 10/20/2025 | Z40: =G40*H40 -> 90
A41: Belmont International Trading Corp | B41: 10/20/2025 | C41: Bill | D41: 72533 | E41: Belmont Aji Amarillo desvenado FROZEN 12oz x 10 | F41: Belmont Aji Amarillo desvenado FROZEN 12oz x 10 / 1FP-44 | G41: 3 | H41: 30.9 | I41: 92.7 | J41: 18168.14 | K41: =COUNTIF($E$2:$E$1438,E41) -> 1 | L41: =IF(K41>1,_xlfn.CONCAT("Se repite ",K41," veces"),"No se repite") -> No se repite | M41: =_xlfn.CONCAT(A41,"-",E41) -> Belmont International Trading Corp-Belmont Aji Amarillo desvenado FROZEN 12oz x 10 | N41: =COUNTIF($M$2:$M$1438,M41) -> 1 | O41: =IF(N41>1,_xlfn.CONCAT("Se repite ",N41," veces en ",A41),"No se repite en proveedor") -> No se repite en proveedor | P41: =_xlfn.CONCAT(A41,"-",E41,"-",H41) -> Belmont International Trading Corp-Belmont Aji Amarillo desvenado FROZEN 12oz x 10-30.9 | Q41: =COUNTIF($P$2:$P$1438,P41) -> 1 | R41: =IF(Q41>1,_xlfn.CONCAT("Se repite ",Q41," veces el precio de ",H41),"No se repite") -> No se repite | S41: =_xlfn.CONCAT("El producto ",E41," ",O41,IF(R41="No se repite",_xlfn.CONCAT(" Una vez con el precio ",H41),_xlfn.CONCAT(", ",R41))) -> El producto Belmont Aji Amarillo desvenado FROZEN 12oz x 10 No se repite en proveedor Una vez con el precio 30.9 | T41: =+A41 -> Belmont International Trading Corp | U41: =+E41 -> Belmont Aji Amarillo desvenado FROZEN 12oz x 10 | V41: =+H41 -> 30.9 | W41: =_xlfn.CONCAT(A41," ",B41) -> Belmont International Trading Corp 10/20/2025 | Z41: =G41*H41 -> 92.7
... A87: Belmont International Trading Corp | B87: 04/28/2025 | C87: Bill | D87: 64308 | E87: Belmont Mango nectar 1Lt x 6 | F87: BELMONT - Belmont Mango nectar 1Lt x 6 / 859174003092 / JB-06 | G87: 1 | H87: 12 | I87: 12 | J87: 4633.3 | K87: =COUNTIF($E$2:$E$1438,E87) -> 2 | L87: =IF(K87>1,_xlfn.CONCAT("Se repite ",K87," veces"),"No se repite") -> Se repite 2 veces | M87: =_xlfn.CONCAT(A87,"-",E87) -> Belmont International Trading Corp-Belmont Mango nectar 1Lt x 6 | N87: =COUNTIF($M$2:$M$1438,M87) -> 2 | O87: =IF(N87>1,_xlfn.CONCAT("Se repite ",N87," veces en ",A87),"No se repite en proveedor") -> Se repite 2 veces en Belmont International Trading Corp | P87: =_xlfn.CONCAT(A87,"-",E87,"-",H87) -> Belmont International Trading Corp-Belmont Mango nectar 1Lt x 6-12 | Q87: =COUNTIF($P$2:$P$1438,P87) -> 2 | R87: =IF(Q87>1,_xlfn.CONCAT("Se repite ",Q87," veces el precio de ",H87),"No se repite") -> Se repite 2 veces el precio de 12 | S87: =_xlfn.CONCAT("El producto ",E87," ",O87,IF(R87="No se repite",_xlfn.CONCAT(" Una vez con el precio ",H87),_xlfn.CONCAT(", ",R87))) -> El producto Belmont Mango nectar 1Lt x 6 Se repite 2 veces en Belmont International Trading Corp, Se repite 2 veces el precio de 12 | T87: =+A87 -> Belmont International Trading Corp | U87: =+E87 -> Belmont Mango nectar 1Lt x 6 | V87: =+H87 -> 12 | W87: =_xlfn.CONCAT(A87," ",B87) -> Belmont International Trading Corp 04/28/2025 | Z87: =G87*H87 -> 12
A88: Belmont International Trading Corp | B88: 07/31/2025 | C88: Bill | D88: 68755 | E88: Belmont Mango nectar 1Lt x 6 | F88: BELMONT - Belmont Mango nectar 1Lt x 6 / 859174003092 / JB-06 | G88: 10 | H88: 12 | I88: 120 | J88: 17712.34 | K88: =COUNTIF($E$2:$E$1438,E88) -> 2 | L88: =IF(K88>1,_xlfn.CONCAT("Se repite ",K88," veces"),"No se repite") -> Se repite 2 veces | M88: =_xlfn.CONCAT(A88,"-",E88) -> Belmont International Trading Corp-Belmont Mango nectar 1Lt x 6 | N88: =COUNTIF($M$2:$M$1438,M88) -> 2 | O88: =IF(N88>1,_xlfn.CONCAT("Se repite ",N88," veces en ",A88),"No se repite en proveedor") -> Se repite 2 veces en Belmont International Trading Corp | P88: =_xlfn.CONCAT(A88,"-",E88,"-",H88) -> Belmont International Trading Corp-Belmont Mango nectar 1Lt x 6-12 | Q88: =COUNTIF($P$2:$P$1438,P88) -> 2 | R88: =IF(Q88>1,_xlfn.CONCAT("Se repite ",Q88," veces el precio de ",H88),"No se repite") -> Se repite 2 veces el precio de 12 | S88: =_xlfn.CONCAT("El producto ",E88," ",O88,IF(R88="No se repite",_xlfn.CONCAT(" Una vez con el precio ",H88),_xlfn.CONCAT(", ",R88))) -> El producto Belmont Mango nectar 1Lt x 6 Se repite 2 veces en Belmont International Trading Corp, Se repite 2 veces el precio de 12 | T88: =+A88 -> Belmont International Trading Corp | U88: =+E88 -> Belmont Mango nectar 1Lt x 6 | V88: =+H88 -> 12 | W88: =_xlfn.CONCAT(A88," ",B88) -> Belmont International Trading Corp 07/31/2025 | X88: Producto repetido con el mismo precio | Z88: =G88*H88 -> 120
A89: Belmont International Trading Corp | B89: 10/20/2025 | C89: Bill | D89: 72533 | E89: Belmont Maracuya con pepas FROZEN 1Kg x 16 | F89: Belmont Maracuya con pepas FROZEN 1Kg x 16 / 1FP-38 | G89: 3 | H89: 79.5 | I89: 238.5 | J89: 19036.64 | K89: =COUNTIF($E$2:$E$1438,E89) -> 1 | L89: =IF(K89>1,_xlfn.CONCAT("Se repite ",K89," veces"),"No se repite") -> No se repite | M89: =_xlfn.CONCAT(A89,"-",E89) -> Belmont International Trading Corp-Belmont Maracuya con pepas FROZEN 1Kg x 16 | N89: =COUNTIF($M$2:$M$1438,M89) -> 1 | O89: =IF(N89>1,_xlfn.CONCAT("Se repite ",N89," veces en ",A89),"No se repite en proveedor") -> No se repite en proveedor | P89: =_xlfn.CONCAT(A89,"-",E89,"-",H89) -> Belmont International Trading Corp-Belmont Maracuya con pepas FROZEN 1Kg x 16-79.5 | Q89: =COUNTIF($P$2:$P$1438,P89) -> 1 | R89: =IF(Q89>1,_xlfn.CONCAT("Se repite ",Q89," veces el precio de ",H89),"No se repite") -> No se repite | S89: =_xlfn.CONCAT("El producto ",E89," ",O89,IF(R89="No se repite",_xlfn.CONCAT(" Una vez con el precio ",H89),_xlfn.CONCAT(", ",R89))) -> El producto Belmont Maracuya con pepas FROZEN 1Kg x 16 No se repite en proveedor Una vez con el precio 79.5 | T89: =+A89 -> Belmont International Trading Corp | U89: =+E89 -> Belmont Maracuya con pepas FROZEN 1Kg x 16 | V89: =+H89 -> 79.5 | W89: =_xlfn.CONCAT(A89," ",B89) -> Belmont International Trading Corp 10/20/2025 | Z89: =G89*H89 -> 238.5
A90: Belmont International Trading Corp | B90: 10/20/2025 | C90: Bill | D90: 72533 | E90: Belmont Pallares 15oz x 14 | F90: Belmont Pallares 15oz x 14 / SE-15 / 859174003535 | G90: 1 | H90: 29.9 | I90: 29.9 | J90: 20574.74 | K90: =COUNTIF($E$2:$E$1438,E90) -> 1 | L90: =IF(K90>1,_xlfn.CONCAT("Se repite ",K90," veces"),"No se repite") -> No se repite | M90: =_xlfn.CONCAT(A90,"-",E90) -> Belmont International Trading Corp-Belmont Pallares 15oz x 14 | N90: =COUNTIF($M$2:$M$1438,M90) -> 1 | O90: =IF(N90>1,_xlfn.CONCAT("Se repite ",N90," veces en ",A90),"No se repite en proveedor") -> No se repite en proveedor | P90: =_xlfn.CONCAT(A90,"-",E90,"-",H90) -> Belmont International Trading Corp-Belmont Pallares 15oz x 14-29.9 | Q90: =COUNTIF($P$2:$P$1438,P90) -> 1 | R90: =IF(Q90>1,_xlfn.CONCAT("Se repite ",Q90," veces el precio de ",H90),"No se repite") -> No se repite | S90: =_xlfn.CONCAT("El producto ",E90," ",O90,IF(R90="No se repite",_xlfn.CONCAT(" Una vez con el precio ",H90),_xlfn.CONCAT(", ",R90))) -> El producto Belmont Pallares 15oz x 14 No se repite en proveedor Una vez con el precio 29.9 | T90: =+A90 -> Belmont International Trading Corp | U90: =+E90 -> Belmont Pallares 15oz x 14 | V90: =+H90 -> 29.9 | W90: =_xlfn.CONCAT(A90," ",B90) -> Belmont International Trading Corp 10/20/2025 | Z90: =G90*H90 -> 29.9
A91: Belmont International Trading Corp | B91: 05/16/2025 | C91: Bill | D91: 65207 | E91: Belmont Pulpa de Lucuma | F91: Belmont Pulpa de Lucuma 14oz x 20 bolsas | G91: 4 | H91: 62.9 | I91: 251.6 | J91: 5959.64 | K91: =COUNTIF($E$2:$E$1438,E91) -> 1 | L91: =IF(K91>1,_xlfn.CONCAT("Se repite ",K91," veces"),"No se repite") -> No se repite | M91: =_xlfn.CONCAT(A91,"-",E91) -> Belmont International Trading Corp-Belmont Pulpa de Lucuma | N91: =COUNTIF($M$2:$M$1438,M91) -> 1 | O91: =IF(N91>1,_xlfn.CONCAT("Se repite ",N91," veces en ",A91),"No se repite en proveedor") -> No se repite en proveedor | P91: =_xlfn.CONCAT(A91,"-",E91,"-",H91) -> Belmont International Trading Corp-Belmont Pulpa de Lucuma-62.9 | Q91: =COUNTIF($P$2:$P$1438,P91) -> 1 | R91: =IF(Q91>1,_xlfn.CONCAT("Se repite ",Q91," veces el precio de ",H91),"No se repite") -> No se repite | S91: =_xlfn.CONCAT("El producto ",E91," ",O91,IF(R91="No se repite",_xlfn.CONCAT(" Una vez con el precio ",H91),_xlfn.CONCAT(", ",R91))) -> El producto Belmont Pulpa de Lucuma No se repite en proveedor Una vez con el precio 62.9 | T91: =+A91 -> Belmont International Trading Corp | U91: =+E91 -> Belmont Pulpa de Lucuma | V91: =+H91 -> 62.9 | W91: =_xlfn.CONCAT(A91," ",B91) -> Belmont International Trading Corp 05/16/2025 | Z91: =G91*H91 -> 251.6
A92: Belmont International Trading Corp | B92: 06/12/2025 | C92: Bill | D92: 66496 | E92: Belmont Pulpa de Maracuya 14oz x 20 | F92: Belmont Pulpa de Maracuya 14oz x 20 bolsas / 1FP-43 | G92: 5 | H92: 48.5 | I92: 242.5 | J92: 12432.14 | K92: =COUNTIF($E$2:$E$1438,E92) -> 3 | L92: =IF(K92>1,_xlfn.CONCAT("Se repite ",K92," veces"),"No se repite") -> Se repite 3 veces | M92: =_xlfn.CONCAT(A92,"-",E92) -> Belmont International Trading Corp-Belmont Pulpa de Maracuya 14oz x 20 | N92: =COUNTIF($M$2:$M$1438,M92) -> 3 | O92: =IF(N92>1,_xlfn.CONCAT("Se repite ",N92," veces en ",A92),"No se repite en proveedor") -> Se repite 3 veces en Belmont International Trading Corp | P92: =_xlfn.CONCAT(A92,"-",E92,"-",H92) -> Belmont International Trading Corp-Belmont Pulpa de Maracuya 14oz x 20-48.5 | Q92: =COUNTIF($P$2:$P$1438,P92) -> 3 | R92: =IF(Q92>1,_xlfn.CONCAT("Se repite ",Q92," veces el precio de ",H92),"No se repite") -> Se repite 3 veces el precio de 48.5 | S92: =_xlfn.CONCAT("El producto ",E92," ",O92,IF(R92="No se repite",_xlfn.CONCAT(" Una vez con el precio ",H92),_xlfn.CONCAT(", ",R92))) -> El producto Belmont Pulpa de Maracuya 14oz x 20 Se repite 3 veces en Belmont International Trading Corp, Se repite 3 veces el precio de 48.5 | T92: =+A92 -> Belmont International Trading Corp | U92: =+E92 -> Belmont Pulpa de Maracuya 14oz x 20 | V92: =+H92 -> 48.5 | W92: =_xlfn.CONCAT(A92," ",B92) -> Belmont International Trading Corp 06/12/2025 | Z92: =G92*H92 -> 242.5
A93: Belmont International Trading Corp | B93: 07/31/2025 | C93: Bill | D93: 68755 | E93: Belmont Pulpa de Maracuya 14oz x 20 | F93: Belmont Pulpa de Maracuya 14oz x 20 bolsas / 1FP-43 | G93: 12 | H93: 48.5 | I93: 582 | J93: 15124.64 | K93: =COUNTIF($E$2:$E$1438,E93) -> 3 | L93: =IF(K93>1,_xlfn.CONCAT("Se repite ",K93," veces"),"No se repite") -> Se repite 3 veces | M93: =_xlfn.CONCAT(A93,"-",E93) -> Belmont International Trading Corp-Belmont Pulpa de Maracuya 14oz x 20 | N93: =COUNTIF($M$2:$M$1438,M93) -> 3 | O93: =IF(N93>1,_xlfn.CONCAT("Se repite ",N93," veces en ",A93),"No se repite en proveedor") -> Se repite 3 veces en Belmont International Trading Corp | P93: =_xlfn.CONCAT(A93,"-",E93,"-",H93) -> Belmont International Trading Corp-Belmont Pulpa de Maracuya 14oz x 20-48.5 | Q93: =COUNTIF($P$2:$P$1438,P93) -> 3 | R93: =IF(Q93>1,_xlfn.CONCAT("Se repite ",Q93," veces el precio de ",H93),"No se repite") -> Se repite 3 veces el precio de 48.5 | S93: =_xlfn.CONCAT("El producto ",E93," ",O93,IF(R93="No se repite",_xlfn.CONCAT(" Una vez con el precio ",H93),_xlfn.CONCAT(", ",R93))) -> El producto Belmont Pulpa de Maracuya 14oz x 20 Se repite 3 veces en Belmont International Trading Corp, Se repite 3 veces el precio de 48.5 | T93: =+A93 -> Belmont International Trading Corp | U93: =+E93 -> Belmont Pulpa de Maracuya 14oz x 20 | V93: =+H93 -> 48.5 | W93: =_xlfn.CONCAT(A93," ",B93) -> Belmont International Trading Corp 07/31/2025 | Z93: =G93*H93 -> 582
A94: Belmont International Trading Corp | B94: 10/20/2025 | C94: Bill | D94: 72533 | E94: Belmont Pulpa de Maracuya 14oz x 20 | F94: Belmont Pulpa de Maracuya 14oz x 20 bolsas / 1FP-43 | G94: 10 | H94: 48.5 | I94: 485 | J94: 18798.14 | K94: =COUNTIF($E$2:$E$1438,E94) -> 3 | L94: =IF(K94>1,_xlfn.CONCAT("Se repite ",K94," veces"),"No se repite") -> Se repite 3 veces | M94: =_xlfn.CONCAT(A94,"-",E94) -> Belmont International Trading Corp-Belmont Pulpa de Maracuya 14oz x 20 | N94: =COUNTIF($M$2:$M$1438,M94) -> 3 | O94: =IF(N94>1,_xlfn.CONCAT("Se repite ",N94," veces en ",A94),"No se repite en proveedor") -> Se repite 3 veces en Belmont International Trading Corp | P94: =_xlfn.CONCAT(A94,"-",E94,"-",H94) -> Belmont International Trading Corp-Belmont Pulpa de Maracuya 14oz x 20-48.5 | Q94: =COUNTIF($P$2:$P$1438,P94) -> 3 | R94: =IF(Q94>1,_xlfn.CONCAT("Se repite ",Q94," veces el precio de ",H94),"No se repite") -> Se repite 3 veces el precio de 48.5 | S94: =_xlfn.CONCAT("El producto ",E94," ",O94,IF(R94="No se repite",_xlfn.CONCAT(" Una vez con el precio ",H94),_xlfn.CONCAT(", ",R94))) -> El producto Belmont Pulpa de Maracuya 14oz x 20 Se repite 3 veces en Belmont International Trading Corp, Se repite 3 veces el precio de 48.5 | T94: =+A94 -> Belmont International Trading Corp | U94: =+E94 -> Belmont Pulpa de Maracuya 14oz x 20 | V94: =+H94 -> 48.5 | W94: =_xlfn.CONCAT(A94," ",B94) -> Belmont International Trading Corp 10/20/2025 | Z94: =G94*H94 -> 485
A95: Belmont International Trading Corp | B95: 06/12/2025 | C95: Bill | D95: 66496 | E95: Belmont Rocoto Desvenado limpio FROZEN 2lb x 10 | F95: Belmont Rocoto Desvenado limpio FROZEN 2lb x 10 bolsas / 1FP-14 | G95: 2 | H95: 66.5 | I95: 133 | J95: 12565.14 | K95: =COUNTIF($E$2:$E$1438,E95) -> 1 | L95: =IF(K95>1,_xlfn.CONCAT("Se repite ",K95," veces"),"No se repite") -> No se repite | M95: =_xlfn.CONCAT(A95,"-",E95) -> Belmont International Trading Corp-Belmont Rocoto Desvenado limpio FROZEN 2lb x 10 | N95: =COUNTIF($M$2:$M$1438,M95) -> 1 | O95: =IF(N95>1,_xlfn.CONCAT("Se repite ",N95," veces en ",A95),"No se repite en proveedor") -> No se repite en proveedor | P95: =_xlfn.CONCAT(A95,"-",E95,"-",H95) -> Belmont International Trading Corp-Belmont Rocoto Desvenado limpio FROZEN 2lb x 10-66.5 | Q95: =COUNTIF($P$2:$P$1438,P95) -> 1 | R95: =IF(Q95>1,_xlfn.CONCAT("Se repite ",Q95," veces el precio de ",H95),"No se repite") -> No se repite | S95: =_xlfn.CONCAT("El producto ",E95," ",O95,IF(R95="No se repite",_xlfn.CONCAT(" Una vez con el precio ",H95),_xlfn.CONCAT(", ",R95))) -> El producto Belmont Rocoto Desvenado limpio FROZEN 2lb x 10 No se repite en proveedor Una vez con el precio 66.5 | T95: =+A95 -> Belmont International Trading Corp | U95: =+E95 -> Belmont Rocoto Desvenado limpio FROZEN 2lb x 10 | V95: =+H95 -> 66.5 | W95: =_xlfn.CONCAT(A95," ",B95) -> Belmont International Trading Corp 06/12/2025 | Z95: =G95*H95 -> 133
A96: Belmont International Trading Corp | B96: 10/20/2025 | C96: Bill | D96: 72533 | E96: Belmont Rocoto en salmuera 20oz x 12 | F96: Belmont Rocoto en salmuera frasco de vidrio 20oz x 12 / PA-30 / 859174003955 | G96: 2 | H96: 39.9 | I96: 79.8 | J96: 20519.84 | K96: =COUNTIF($E$2:$E$1438,E96) -> 1 | L96: =IF(K96>1,_xlfn.CONCAT("Se repite ",K96," veces"),"No se repite") -> No se repite | M96: =_xlfn.CONCAT(A96,"-",E96) -> Belmont International Trading Corp-Belmont Rocoto en salmuera 20oz x 12 | N96: =COUNTIF($M$2:$M$1438,M96) -> 1 | O96: =IF(N96>1,_xlfn.CONCAT("Se repite ",N96," veces en ",A96),"No se repite en proveedor") -> No se repite en proveedor | P96: =_xlfn.CONCAT(A96,"-",E96,"-",H96) -> Belmont International Trading Corp-Belmont Rocoto en salmuera 20oz x 12-39.9 | Q96: =COUNTIF($P$2:$P$1438,P96) -> 1 | R96: =IF(Q96>1,_xlfn.CONCAT("Se repite ",Q96," veces el precio de ",H96),"No se repite") -> No se repite | S96: =_xlfn.CONCAT("El producto ",E96," ",O96,IF(R96="No se repite",_xlfn.CONCAT(" Una vez con el precio ",H96),_xlfn.CONCAT(", ",R96))) -> El producto Belmont Rocoto en salmuera 20oz x 12 No se repite en proveedor Una vez con el precio 39.9 | T96: =+A96 -> Belmont International Trading Corp | U96: =+E96 -> Belmont Rocoto en salmuera 20oz x 12 | V96: =+H96 -> 39.9 | W96: =_xlfn.CONCAT(A96," ",B96) -> Belmont International Trading Corp 10/20/2025 | Z96: =G96*H96 -> 79.8
A97: Belmont International Trading Corp | B97: 05/16/2025 | C97: Bill | D97: 65207 | E97: Belmont Rocoto entero FROZEN | F97: Belmont Rocoto entero FROZEN 1Lb x 18 bolsas | G97: 6 | H97: 51 | I97: 306 | J97: 6549.74 | K97: =COUNTIF($E$2:$E$1438,E97) -> 1 | L97: =IF(K97>1,_xlfn.CONCAT("Se repite ",K97," veces"),"No se repite") -> No se repite | M97: =_xlfn.CONCAT(A97,"-",E97) -> Belmont International Trading Corp-Belmont Rocoto entero FROZEN | N97: =COUNTIF($M$2:$M$1438,M97) -> 1 | O97: =IF(N97>1,_xlfn.CONCAT("Se repite ",N97," veces en ",A97),"No se repite en proveedor") -> No se repite en proveedor | P97: =_xlfn.CONCAT(A97,"-",E97,"-",H97) -> Belmont International Trading Corp-Belmont Rocoto entero FROZEN-51 | Q97: =COUNTIF($P$2:$P$1438,P97) -> 1 | R97: =IF(Q97>1,_xlfn.CONCAT("Se repite ",Q97," veces el precio de ",H97),"No se repite") -> No se repite | S97: =_xlfn.CONCAT("El producto ",E97," ",O97,IF(R97="No se repite",_xlfn.CONCAT(" Una vez con el precio ",H97),_xlfn.CONCAT(", ",R97))) -> El producto Belmont Rocoto entero FROZEN No se repite en proveedor Una vez con el precio 51 | T97: =+A97 -> Belmont International Trading Corp | U97: =+E97 -> Belmont Rocoto entero FROZEN | V97: =+H97 -> 51 | W97: =_xlfn.CONCAT(A97," ",B97) -> Belmont International Trading Corp 05/16/2025 | Z97: =G97*H97 -> 306
A98: Belmont International Trading Corp | B98: 04/28/2025 | C98: Bill | D98: 64308 | E98: Belmont Yuyo Marino FROZEN 2.2lb x 8 | F98: Belmont Yuyo Marino FROZEN 2.2lb x 8 / 1FP-36 | G98: 1 | H98: 54 | I98: 54 | J98: 54 | K98: =COUNTIF($E$2:$E$1438,E98) -> 5 | L98: =IF(K98>1,_xlfn.CONCAT("Se repite ",K98," veces"),"No se repite") -> Se repite 5 veces | M98: =_xlfn.CONCAT(A98,"-",E98) -> Belmont International Trading Corp-Belmont Yuyo Marino FROZEN 2.2lb x 8 | N98: =COUNTIF($M$2:$M$1438,M98) -> 5 | O98: =IF(N98>1,_xlfn.CONCAT("Se repite ",N98," veces en ",A98),"No se repite en proveedor") -> Se repite 5 veces en Belmont International Trading Corp | P98: =_xlfn.CONCAT(A98,"-",E98,"-",H98) -> Belmont International Trading Corp-Belmont Yuyo Marino FROZEN 2.2lb x 8-54 | Q98: =COUNTIF($P$2:$P$1438,P98) -> 1 | R98: =IF(Q98>1,_xlfn.CONCAT("Se repite ",Q98," veces el precio de ",H98),"No se repite") -> No se repite | S98: =_xlfn.CONCAT("El producto ",E98," ",O98,IF(R98="No se repite",_xlfn.CONCAT(" Una vez con el precio ",H98),_xlfn.CONCAT(", ",R98))) -> El producto Belmont Yuyo Marino FROZEN 2.2lb x 8 Se repite 5 veces en Belmont International Trading Corp Una vez con el precio 54 | T98: =+A98 -> Belmont International Trading Corp | U98: =+E98 -> Belmont Yuyo Marino FROZEN 2.2lb x 8 | V98: =+H98 -> 54 | W98: =_xlfn.CONCAT(A98," ",B98) -> Belmont International Trading Corp 04/28/2025 | Z98: =G98*H98 -> 54
A99: Belmont International Trading Corp | B99: 05/16/2025 | C99: Bill | D99: 65207 | E99: Belmont Yuyo Marino FROZEN 2.2lb x 8 | F99: Belmont Yuyo Marino FROZEN 2.2lb x 8 / 1FP-36 | G99: 4 | H99: 59.9 | I99: 239.6 | J99: 5708.04 | K99: =COUNTIF($E$2:$E$1438,E99) -> 5 | L99: =IF(K99>1,_xlfn.CONCAT("Se repite ",K99," veces"),"No se repite") -> Se repite 5 veces | M99: =_xlfn.CONCAT(A99,"-",E99) -> Belmont International Trading Corp-Belmont Yuyo Marino FROZEN 2.2lb x 8 | N99: =COUNTIF($M$2:$M$1438,M99) -> 5 | O99: =IF(N99>1,_xlfn.CONCAT("Se repite ",N99," veces en ",A99),"No se repite en proveedor") -> Se repite 5 veces en Belmont International Trading Corp | P99: =_xlfn.CONCAT(A99,"-",E99,"-",H99) -> Belmont International Trading Corp-Belmont Yuyo Marino FROZEN 2.2lb x 8-59.9 | Q99: =COUNTIF($P$2:$P$1438,P99) -> 4 | R99: =IF(Q99>1,_xlfn.CONCAT("Se repite ",Q99," veces el precio de ",H99),"No se repite") -> Se repite 4 veces el precio de 59.9 | S99: =_xlfn.CONCAT("El producto ",E99," ",O99,IF(R99="No se repite",_xlfn.CONCAT(" Una vez con el precio ",H99),_xlfn.CONCAT(", ",R99))) -> El producto Belmont Yuyo Marino FROZEN 2.2lb x 8 Se repite 5 veces en Belmont International Trading Corp, Se repite 4 veces el precio de 59.9 | T99: =+A99 -> Belmont International Trading Corp | U99: =+E99 -> Belmont Yuyo Marino FROZEN 2.2lb x 8 | V99: =+H99 -> 59.9 | W99: =_xlfn.CONCAT(A99," ",B99) -> Belmont International Trading Corp 05/16/2025 | Z99: =G99*H99 -> 239.6
A100: Belmont International Trading Corp | B100: 06/12/2025 | C100: Bill | D100: 66496 | E100: Belmont Yuyo Marino FROZEN 2.2lb x 8 | F100: Belmont Yuyo Marino FROZEN 2.2lb x 8 / 1FP-36 | G100: 4 | H100: 59.9 | I100: 239.6 | J100: 12804.74 | K100: =COUNTIF($E$2:$E$1438,E100) -> 5 | L100: =IF(K100>1,_xlfn.CONCAT("Se repite ",K100," veces"),"No se repite") -> Se repite 5 veces | M100: =_xlfn.CONCAT(A100,"-",E100) -> Belmont International Trading Corp-Belmont Yuyo Marino FROZEN 2.2lb x 8 | N100: =COUNTIF($M$2:$M$1438,M100) -> 5 | O100: =IF(N100>1,_xlfn.CONCAT("Se repite ",N100," veces en ",A100),"No se repite en proveedor") -> Se repite 5 veces en Belmont International Trading Corp | P100: =_xlfn.CONCAT(A100,"-",E100,"-",H100) -> Belmont International Trading Corp-Belmont Yuyo Marino FROZEN 2.2lb x 8-59.9 | Q100: =COUNTIF($P$2:$P$1438,P100) -> 4 | R100: =IF(Q100>1,_xlfn.CONCAT("Se repite ",Q100," veces el precio de ",H100),"No se repite") -> Se repite 4 veces el precio de 59.9 | S100: =_xlfn.CONCAT("El producto ",E100," ",O100,IF(R100="No se repite",_xlfn.CONCAT(" Una vez con el precio ",H100),_xlfn.CONCAT(", ",R100))) -> El producto Belmont Yuyo Marino FROZEN 2.2lb x 8 Se repite 5 veces en Belmont International Trading Corp, Se repite 4 veces el precio de 59.9 | T100: =+A100 -> Belmont International Trading Corp | U100: =+E100 -> Belmont Yuyo Marino FROZEN 2.2lb x 8 | V100: =+H100 -> 59.9 | W100: =_xlfn.CONCAT(A100," ",B100) -> Belmont International Trading Corp 06/12/2025 | Z100: =G100*H100 -> 239.6
... A104: Belmont International Trading Corp | B104: 05/16/2025 | C104: Bill | D104: 65207 | E104: CASINO Galleta Chocolate 51gr x 6 x 8 | F104: BELMONT - PERU - GOLOSINAS - DULCES - CASINO - Galleta Chocolate- 8 / 6x51g - CH118 | G104: 10 | H104: 17.6 | I104: 176 | J104: 10609.74 | K104: =COUNTIF($E$2:$E$1438,E104) -> 5 | L104: =IF(K104>1,_xlfn.CONCAT("Se repite ",K104," veces"),"No se repite") -> Se repite 5 veces | M104: =_xlfn.CONCAT(A104,"-",E104) -> Belmont International Trading Corp-CASINO Galleta Chocolate 51gr x 6 x 8 | N104: =COUNTIF($M$2:$M$1438,M104) -> 2 | O104: =IF(N104>1,_xlfn.CONCAT("Se repite ",N104," veces en ",A104),"No se repite en proveedor") -> Se repite 2 veces en Belmont International Trading Corp | P104: =_xlfn.CONCAT(A104,"-",E104,"-",H104) -> Belmont International Trading Corp-CASINO Galleta Chocolate 51gr x 6 x 8-17.6 | Q104: =COUNTIF($P$2:$P$1438,P104) -> 1 | R104: =IF(Q104>1,_xlfn.CONCAT("Se repite ",Q104," veces el precio de ",H104),"No se repite") -> No se repite | S104: =_xlfn.CONCAT("El producto ",E104," ",O104,IF(R104="No se repite",_xlfn.CONCAT(" Una vez con el precio ",H104),_xlfn.CONCAT(", ",R104))) -> El producto CASINO Galleta Chocolate 51gr x 6 x 8 Se repite 2 veces en Belmont International Trading Corp Una vez con el precio 17.6 | T104: =+A104 -> Belmont International Trading Corp | U104: =+E104 -> CASINO Galleta Chocolate 51gr x 6 x 8 | V104: =+H104 -> 17.6 | W104: =_xlfn.CONCAT(A104," ",B104) -> Belmont International Trading Corp 05/16/2025 | Z104: =G104*H104 -> 176
A105: Peru Chef | B105: 03/26/2025 | C105: Bill | E105: CASINO Galleta Chocolate 51gr x 6 x 8 | F105: CASINO - Galleta Chocolate | G105: 1 | H105: 15.5 | I105: 15.5 | J105: 1395.2 | K105: =COUNTIF($E$2:$E$1438,E105) -> 5 | L105: =IF(K105>1,_xlfn.CONCAT("Se repite ",K105," veces"),"No se repite") -> Se repite 5 veces | M105: =_xlfn.CONCAT(A105,"-",E105) -> Peru Chef-CASINO Galleta Chocolate 51gr x 6 x 8 | N105: =COUNTIF($M$2:$M$1438,M105) -> 3 | O105: =IF(N105>1,_xlfn.CONCAT("Se repite ",N105," veces en ",A105),"No se repite en proveedor") -> Se repite 3 veces en Peru Chef | P105: =_xlfn.CONCAT(A105,"-",E105,"-",H105) -> Peru Chef-CASINO Galleta Chocolate 51gr x 6 x 8-15.5 | Q105: =COUNTIF($P$2:$P$1438,P105) -> 1 | R105: =IF(Q105>1,_xlfn.CONCAT("Se repite ",Q105," veces el precio de ",H105),"No se repite") -> No se repite | S105: =_xlfn.CONCAT("El producto ",E105," ",O105,IF(R105="No se repite",_xlfn.CONCAT(" Una vez con el precio ",H105),_xlfn.CONCAT(", ",R105))) -> El producto CASINO Galleta Chocolate 51gr x 6 x 8 Se repite 3 veces en Peru Chef Una vez con el precio 15.5 | T105: =+A105 -> Peru Chef | U105: =+E105 -> CASINO Galleta Chocolate 51gr x 6 x 8 | V105: =+H105 -> 15.5 | W105: =_xlfn.CONCAT(A105," ",B105) -> Peru Chef 03/26/2025 | Z105: =G105*H105 -> 15.5
A106: Peru Chef | B106: 08/28/2025 | C106: Bill | D106: 2025001209 | E106: CASINO Galleta Chocolate 51gr x 6 x 8 | F106: BELMONT - PERU - GOLOSINAS - DULCES - CASINO - Galleta Chocolate- 8 / 6x51g - CH118 | G106: 6 | H106: 17 | I106: 102 | J106: 15140.5 | K106: =COUNTIF($E$2:$E$1438,E106) -> 5 | L106: =IF(K106>1,_xlfn.CONCAT("Se repite ",K106," veces"),"No se repite") -> Se repite 5 veces | M106: =_xlfn.CONCAT(A106,"-",E106) -> Peru Chef-CASINO Galleta Chocolate 51gr x 6 x 8 | N106: =COUNTIF($M$2:$M$1438,M106) -> 3 | O106: =IF(N106>1,_xlfn.CONCAT("Se repite ",N106," veces en ",A106),"No se repite en proveedor") -> Se repite 3 veces en Peru Chef | P106: =_xlfn.CONCAT(A106,"-",E106,"-",H106) -> Peru Chef-CASINO Galleta Chocolate 51gr x 6 x 8-17 | Q106: =COUNTIF($P$2:$P$1438,P106) -> 1 | R106: =IF(Q106>1,_xlfn.CONCAT("Se repite ",Q106," veces el precio de ",H106),"No se repite") -> No se repite | S106: =_xlfn.CONCAT("El producto ",E106," ",O106,IF(R106="No se repite",_xlfn.CONCAT(" Una vez con el precio ",H106),_xlfn.CONCAT(", ",R106))) -> El producto CASINO Galleta Chocolate 51gr x 6 x 8 Se repite 3 veces en Peru Chef Una vez con el precio 17 | T106: =+A106 -> Peru Chef | U106: =+E106 -> CASINO Galleta Chocolate 51gr x 6 x 8 | V106: =+H106 -> 17 | W106: =_xlfn.CONCAT(A106," ",B106) -> Peru Chef 08/28/2025 | Z106: =G106*H106 -> 102
A107: Peru Chef | B107: 11/14/2025 | C107: Bill | D107: 57055 | E107: CASINO Galleta Chocolate 51gr x 6 x 8 | F107: BELMONT - PERU - GOLOSINAS - DULCES - CASINO - Galleta Chocolate- 8 / 6x51g - CH118 | G107: 10 | H107: 15.3 | I107: 153 | J107: 37103.35 | K107: =COUNTIF($E$2:$E$1438,E107) -> 5 | L107: =IF(K107>1,_xlfn.CONCAT("Se repite ",K107," veces"),"No se repite") -> Se repite 5 veces | M107: =_xlfn.CONCAT(A107,"-",E107) -> Peru Chef-CASINO Galleta Chocolate 51gr x 6 x 8 | N107: =COUNTIF($M$2:$M$1438,M107) -> 3 | O107: =IF(N107>1,_xlfn.CONCAT("Se repite ",N107," veces en ",A107),"No se repite en proveedor") -> Se repite 3 veces en Peru Chef | P107: =_xlfn.CONCAT(A107,"-",E107,"-",H107) -> Peru Chef-CASINO Galleta Chocolate 51gr x 6 x 8-15.3 | Q107: =COUNTIF($P$2:$P$1438,P107) -> 1 | R107: =IF(Q107>1,_xlfn.CONCAT("Se repite ",Q107," veces el precio de ",H107),"No se repite") -> No se repite | S107: =_xlfn.CONCAT("El producto ",E107," ",O107,IF(R107="No se repite",_xlfn.CONCAT(" Una vez con el precio ",H107),_xlfn.CONCAT(", ",R107))) -> El producto CASINO Galleta Chocolate 51gr x 6 x 8 Se repite 3 veces en Peru Chef Una vez con el precio 15.3 | T107: =+A107 -> Peru Chef | U107: =+E107 -> CASINO Galleta Chocolate 51gr x 6 x 8 | V107: =+H107 -> 15.3 | W107: =_xlfn.CONCAT(A107," ",B107) -> Peru Chef 11/14/2025 | Z107: =G107*H107 -> 153
A108: Belmont International Trading Corp | B108: 04/28/2025 | C108: Bill | D108: 64308 | E108: CASINO Galleta Fresa 51gr x 6 x 8 | F108: BELMONT - PERU - GOLOSINAS - DULCES - CASINO - Galleta Fresa- 8 / 6x51g - CH116 | G108: 1 | H108: 16 | I108: 16 | J108: 4242.8 | K108: =COUNTIF($E$2:$E$1438,E108) -> 5 | L108: =IF(K108>1,_xlfn.CONCAT("Se repite ",K108," veces"),"No se repite") -> Se repite 5 veces | M108: =_xlfn.CONCAT(A108,"-",E108) -> Belmont International Trading Corp-CASINO Galleta Fresa 51gr x 6 x 8 | N108: =COUNTIF($M$2:$M$1438,M108) -> 2 | O108: =IF(N108>1,_xlfn.CONCAT("Se repite ",N108," veces en ",A108),"No se repite en proveedor") -> Se repite 2 veces en Belmont International Trading Corp | P108: =_xlfn.CONCAT(A108,"-",E108,"-",H108) -> Belmont International Trading Corp-CASINO Galleta Fresa 51gr x 6 x 8-16 | Q108: =COUNTIF($P$2:$P$1438,P108) -> 1 | R108: =IF(Q108>1,_xlfn.CONCAT("Se repite ",Q108," veces el precio de ",H108),"No se repite") -> No se repite | S108: =_xlfn.CONCAT("El producto ",E108," ",O108,IF(R108="No se repite",_xlfn.CONCAT(" Una vez con el precio ",H108),_xlfn.CONCAT(", ",R108))) -> El producto CASINO Galleta Fresa 51gr x 6 x 8 Se repite 2 veces en Belmont International Trading Corp Una vez con el precio 16 | T108: =+A108 -> Belmont International Trading Corp | U108: =+E108 -> CASINO Galleta Fresa 51gr x 6 x 8 | V108: =+H108 -> 16 | W108: =_xlfn.CONCAT(A108," ",B108) -> Belmont International Trading Corp 04/28/2025 | Z108: =G108*H108 -> 16
A109: Belmont International Trading Corp | B109: 05/16/2025 | C109: Bill | D109: 65207 | E109: CASINO Galleta Fresa 51gr x 6 x 8 | F109: BELMONT - PERU - GOLOSINAS - DULCES - CASINO - Galleta Fresa- 8 / 6x51g - CH116 | G109: 10 | H109: 17.6 | I109: 176 | J109: 10961.74 | K109: =COUNTIF($E$2:$E$1438,E109) -> 5 | L109: =IF(K109>1,_xlfn.CONCAT("Se repite ",K109," veces"),"No se repite") -> Se repite 5 veces | M109: =_xlfn.CONCAT(A109,"-",E109) -> Belmont International Trading Corp-CASINO Galleta Fresa 51gr x 6 x 8 | N109: =COUNTIF($M$2:$M$1438,M109) -> 2 | O109: =IF(N109>1,_xlfn.CONCAT("Se repite ",N109," veces en ",A109),"No se repite en proveedor") -> Se repite 2 veces en Belmont International Trading Corp | P109: =_xlfn.CONCAT(A109,"-",E109,"-",H109) -> Belmont International Trading Corp-CASINO Galleta Fresa 51gr x 6 x 8-17.6 | Q109: =COUNTIF($P$2:$P$1438,P109) -> 1 | R109: =IF(Q109>1,_xlfn.CONCAT("Se repite ",Q109," veces el precio de ",H109),"No se repite") -> No se repite | S109: =_xlfn.CONCAT("El producto ",E109," ",O109,IF(R109="No se repite",_xlfn.CONCAT(" Una vez con el precio ",H109),_xlfn.CONCAT(", ",R109))) -> El producto CASINO Galleta Fresa 51gr x 6 x 8 Se repite 2 veces en Belmont International Trading Corp Una vez con el precio 17.6 | T109: =+A109 -> Belmont International Trading Corp | U109: =+E109 -> CASINO Galleta Fresa 51gr x 6 x 8 | V109: =+H109 -> 17.6 | W109: =_xlfn.CONCAT(A109," ",B109) -> Belmont International Trading Corp 05/16/2025 | Z109: =G109*H109 -> 176
A110: Peru Chef | B110: 08/28/2025 | C110: Bill | D110: 2025001209 | E110: CASINO Galleta Fresa 51gr x 6 x 8 | F110: BELMONT - PERU - GOLOSINAS - DULCES - CASINO - Galleta Fresa- 8 / 6x51g - CH116 | G110: 4 | H110: 17 | I110: 68 | J110: 15038.5 | K110: =COUNTIF($E$2:$E$1438,E110) -> 5 | L110: =IF(K110>1,_xlfn.CONCAT("Se repite ",K110," veces"),"No se repite") -> Se repite 5 veces | M110: =_xlfn.CONCAT(A110,"-",E110) -> Peru Chef-CASINO Galleta Fresa 51gr x 6 x 8 | N110: =COUNTIF($M$2:$M$1438,M110) -> 2 | O110: =IF(N110>1,_xlfn.CONCAT("Se repite ",N110," veces en ",A110),"No se repite en proveedor") -> Se repite 2 veces en Peru Chef | P110: =_xlfn.CONCAT(A110,"-",E110,"-",H110) -> Peru Chef-CASINO Galleta Fresa 51gr x 6 x 8-17 | Q110: =COUNTIF($P$2:$P$1438,P110) -> 2 | R110: =IF(Q110>1,_xlfn.CONCAT("Se repite ",Q110," veces el precio de ",H110),"No se repite") -> Se repite 2 veces el precio de 17 | S110: =_xlfn.CONCAT("El producto ",E110," ",O110,IF(R110="No se repite",_xlfn.CONCAT(" Una vez con el precio ",H110),_xlfn.CONCAT(", ",R110))) -> El producto CASINO Galleta Fresa 51gr x 6 x 8 Se repite 2 veces en Peru Chef, Se repite 2 veces el precio de 17 | T110: =+A110 -> Peru Chef | U110: =+E110 -> CASINO Galleta Fresa 51gr x 6 x 8 | V110: =+H110 -> 17 | W110: =_xlfn.CONCAT(A110," ",B110) -> Peru Chef 08/28/2025 | Z110: =G110*H110 -> 68
A111: Peru Chef | B111: 09/11/2025 | C111: Bill | D111: 2025001378 | E111: CASINO Galleta Fresa 51gr x 6 x 8 | F111: BELMONT - PERU - GOLOSINAS - DULCES - CASINO - Galleta Fresa- 8 / 6x51g - CH116 | G111: 4 | H111: 17 | I111: 68 | J111: 19732 | K111: =COUNTIF($E$2:$E$1438,E111) -> 5 | L111: =IF(K111>1,_xlfn.CONCAT("Se repite ",K111," veces"),"No se repite") -> Se repite 5 veces | M111: =_xlfn.CONCAT(A111,"-",E111) -> Peru Chef-CASINO Galleta Fresa 51gr x 6 x 8 | N111: =COUNTIF($M$2:$M$1438,M111) -> 2 | O111: =IF(N111>1,_xlfn.CONCAT("Se repite ",N111," veces en ",A111),"No se repite en proveedor") -> Se repite 2 veces en Peru Chef | P111: =_xlfn.CONCAT(A111,"-",E111,"-",H111) -> Peru Chef-CASINO Galleta Fresa 51gr x 6 x 8-17 | Q111: =COUNTIF($P$2:$P$1438,P111) -> 2 | R111: =IF(Q111>1,_xlfn.CONCAT("Se repite ",Q111," veces el precio de ",H111),"No se repite") -> Se repite 2 veces el precio de 17 | S111: =_xlfn.CONCAT("El producto ",E111," ",O111,IF(R111="No se repite",_xlfn.CONCAT(" Una vez con el precio ",H111),_xlfn.CONCAT(", ",R111))) -> El producto CASINO Galleta Fresa 51gr x 6 x 8 Se repite 2 veces en Peru Chef, Se repite 2 veces el precio de 17 | T111: =+A111 -> Peru Chef | U111: =+E111 -> CASINO Galleta Fresa 51gr x 6 x 8 | V111: =+H111 -> 17 | W111: =_xlfn.CONCAT(A111," ",B111) -> Peru Chef 09/11/2025 | Z111: =G111*H111 -> 68
A112: Tradiciones Andinas | B112: 11/28/2025 | C112: Bill | D112: 492743 | E112: CASINO Galleta Fresa 51gr x 6 x 8 | F112: BELMONT - PERU - GOLOSINAS - DULCES - CASINO - Galleta Fresa- 8 / 6x51g - CH116 | G112: 10 | H112: 18.32 | I112: 183.2 | J112: 112050.02 | K112: =COUNTIF($E$2:$E$1438,E112) -> 5 | L112: =IF(K112>1,_xlfn.CONCAT("Se repite ",K112," veces"),"No se repite") -> Se repite 5 veces | M112: =_xlfn.CONCAT(A112,"-",E112) -> Tradiciones Andinas-CASINO Galleta Fresa 51gr x 6 x 8 | N112: =COUNTIF($M$2:$M$1438,M112) -> 1 | O112: =IF(N112>1,_xlfn.CONCAT("Se repite ",N112," veces en ",A112),"No se repite en proveedor") -> No se repite en proveedor | P112: =_xlfn.CONCAT(A112,"-",E112,"-",H112) -> Tradiciones Andinas-CASINO Galleta Fresa 51gr x 6 x 8-18.32 | Q112: =COUNTIF($P$2:$P$1438,P112) -> 1 | R112: =IF(Q112>1,_xlfn.CONCAT("Se repite ",Q112," veces el precio de ",H112),"No se repite") -> No se repite | S112: =_xlfn.CONCAT("El producto ",E112," ",O112,IF(R112="No se repite",_xlfn.CONCAT(" Una vez con el precio ",H112),_xlfn.CONCAT(", ",R112))) -> El producto CASINO Galleta Fresa 51gr x 6 x 8 No se repite en proveedor Una vez con el precio 18.32 | T112: =+A112 -> Tradiciones Andinas | U112: =+E112 -> CASINO Galleta Fresa 51gr x 6 x 8 | V112: =+H112 -> 18.32 | W112: =_xlfn.CONCAT(A112," ",B112) -> Tradiciones Andinas 11/28/2025 | Z112: =G112*H112 -> 183.2
A113: Belmont International Trading Corp | B113: 04/28/2025 | C113: Bill | D113: 64308 | E113: CASINO Galleta Lucuma 51gr x 6 x 8 | F113: BELMONT - PERU - GOLOSINAS - DULCES - CASINO - Galleta Lucuma- 8 / 6x51g - CH123 | G113: 1 | H113: 16 | I113: 16 | J113: 4274.8 | K113: =COUNTIF($E$2:$E$1438,E113) -> 3 | L113: =IF(K113>1,_xlfn.CONCAT("Se repite ",K113," veces"),"No se repite") -> Se repite 3 veces | M113: =_xlfn.CONCAT(A113,"-",E113) -> Belmont International Trading Corp-CASINO Galleta Lucuma 51gr x 6 x 8 | N113: =COUNTIF($M$2:$M$1438,M113) -> 1 | O113: =IF(N113>1,_xlfn.CONCAT("Se repite ",N113," veces en ",A113),"No se repite en proveedor") -> No se repite en proveedor | P113: =_xlfn.CONCAT(A113,"-",E113,"-",H113) -> Belmont International Trading Corp-CASINO Galleta Lucuma 51gr x 6 x 8-16 | Q113: =COUNTIF($P$2:$P$1438,P113) -> 1 | R113: =IF(Q113>1,_xlfn.CONCAT("Se repite ",Q113," veces el precio de ",H113),"No se repite") -> No se repite | S113: =_xlfn.CONCAT("El producto ",E113," ",O113,IF(R113="No se repite",_xlfn.CONCAT(" Una vez con el precio ",H113),_xlfn.CONCAT(", ",R113))) -> El producto CASINO Galleta Lucuma 51gr x 6 x 8 No se repite en proveedor Una vez con el precio 16 | T113: =+A113 -> Belmont International Trading Corp | U113: =+E113 -> CASINO Galleta Lucuma 51gr x 6 x 8 | V113: =+H113 -> 16 | W113: =_xlfn.CONCAT(A113," ",B113) -> Belmont International Trading Corp 04/28/2025 | Z113: =G113*H113 -> 16
A114: Peru Chef | B114: 08/28/2025 | C114: Bill | D114: 2025001209 | E114: CASINO Galleta Lucuma 51gr x 6 x 8 | F114: BELMONT - PERU - GOLOSINAS - DULCES - CASINO - Galleta Lucuma- 8 / 6x51g - CH123 | G114: 2 | H114: 17 | I114: 34 | J114: 19179.5 | K114: =COUNTIF($E$2:$E$1438,E114) -> 3 | L114: =IF(K114>1,_xlfn.CONCAT("Se repite ",K114," veces"),"No se repite") -> Se repite 3 veces | M114: =_xlfn.CONCAT(A114,"-",E114) -> Peru Chef-CASINO Galleta Lucuma 51gr x 6 x 8 | N114: =COUNTIF($M$2:$M$1438,M114) -> 2 | O114: =IF(N114>1,_xlfn.CONCAT("Se repite ",N114," veces en ",A114),"No se repite en proveedor") -> Se repite 2 veces en Peru Chef | P114: =_xlfn.CONCAT(A114,"-",E114,"-",H114) -> Peru Chef-CASINO Galleta Lucuma 51gr x 6 x 8-17 | Q114: =COUNTIF($P$2:$P$1438,P114) -> 1 | R114: =IF(Q114>1,_xlfn.CONCAT("Se repite ",Q114," veces el precio de ",H114),"No se repite") -> No se repite | S114: =_xlfn.CONCAT("El producto ",E114," ",O114,IF(R114="No se repite",_xlfn.CONCAT(" Una vez con el precio ",H114),_xlfn.CONCAT(", ",R114))) -> El producto CASINO Galleta Lucuma 51gr x 6 x 8 Se repite 2 veces en Peru Chef Una vez con el precio 17 | T114: =+A114 -> Peru Chef | U114: =+E114 -> CASINO Galleta Lucuma 51gr x 6 x 8 | V114: =+H114 -> 17 | W114: =_xlfn.CONCAT(A114," ",B114) -> Peru Chef 08/28/2025 | Z114: =G114*H114 -> 34
A115: Peru Chef | B115: 11/14/2025 | C115: Bill | D115: 57055 | E115: CASINO Galleta Lucuma 51gr x 6 x 8 | F115: BELMONT - PERU - GOLOSINAS - DULCES - CASINO - Galleta Lucuma- 8 / 6x51g - CH123 | G115: 10 | H115: 15.3 | I115: 153 | J115: 37256.35 | K115: =COUNTIF($E$2:$E$1438,E115) -> 3 | L115: =IF(K115>1,_xlfn.CONCAT("Se repite ",K115," veces"),"No se repite") -> Se repite 3 veces | M115: =_xlfn.CONCAT(A115,"-",E115) -> Peru Chef-CASINO Galleta Lucuma 51gr x 6 x 8 | N115: =COUNTIF($M$2:$M$1438,M115) -> 2 | O115: =IF(N115>1,_xlfn.CONCAT("Se repite ",N115," veces en ",A115),"No se repite en proveedor") -> Se repite 2 veces en Peru Chef | P115: =_xlfn.CONCAT(A115,"-",E115,"-",H115) -> Peru Chef-CASINO Galleta Lucuma 51gr x 6 x 8-15.3 | Q115: =COUNTIF($P$2:$P$1438,P115) -> 1 | R115: =IF(Q115>1,_xlfn.CONCAT("Se repite ",Q115," veces el precio de ",H115),"No se repite") -> No se repite | S115: =_xlfn.CONCAT("El producto ",E115," ",O115,IF(R115="No se repite",_xlfn.CONCAT(" Una vez con el precio ",H115),_xlfn.CONCAT(", ",R115))) -> El producto CASINO Galleta Lucuma 51gr x 6 x 8 Se repite 2 veces en Peru Chef Una vez con el precio 15.3 | T115: =+A115 -> Peru Chef | U115: =+E115 -> CASINO Galleta Lucuma 51gr x 6 x 8 | V115: =+H115 -> 15.3 | W115: =_xlfn.CONCAT(A115," ",B115) -> Peru Chef 11/14/2025 | Z115: =G115*H115 -> 153
A116: Belmont International Trading Corp | B116: 04/28/2025 | C116: Bill | D116: 64308 | E116: CASINO Galleta Menta 51gr x 6 x 8 | F116: BELMONT - PERU - GOLOSINAS - DULCES - CASINO - Galleta Menta- 8 / 6x51g - CH117 | G116: 1 | H116: 16 | I116: 16 | J116: 4226.8 | K116: =COUNTIF($E$2:$E$1438,E116) -> 7 | L116: =IF(K116>1,_xlfn.CONCAT("Se repite ",K116," veces"),"No se repite") -> Se repite 7 veces | M116: =_xlfn.CONCAT(A116,"-",E116) -> Belmont International Trading Corp-CASINO Galleta Menta 51gr x 6 x 8 | N116: =COUNTIF($M$2:$M$1438,M116) -> 3 | O116: =IF(N116>1,_xlfn.CONCAT("Se repite ",N116," veces en ",A116),"No se repite en proveedor") -> Se repite 3 veces en Belmont International Trading Corp | P116: =_xlfn.CONCAT(A116,"-",E116,"-",H116) -> Belmont International Trading Corp-CASINO Galleta Menta 51gr x 6 x 8-16 | Q116: =COUNTIF($P$2:$P$1438,P116) -> 1 | R116: =IF(Q116>1,_xlfn.CONCAT("Se repite ",Q116," veces el precio de ",H116),"No se repite") -> No se repite | S116: =_xlfn.CONCAT("El producto ",E116," ",O116,IF(R116="No se repite",_xlfn.CONCAT(" Una vez con el precio ",H116),_xlfn.CONCAT(", ",R116))) -> El producto CASINO Galleta Menta 51gr x 6 x 8 Se repite 3 veces en Belmont International Trading Corp Una vez con el precio 16 | T116: =+A116 -> Belmont International Trading Corp | U116: =+E116 -> CASINO Galleta Menta 51gr x 6 x 8 | V116: =+H116 -> 16 | W116: =_xlfn.CONCAT(A116," ",B116) -> Belmont International Trading Corp 04/28/2025 | Z116: =G116*H116 -> 16
A117: Belmont International Trading Corp | B117: 05/16/2025 | C117: Bill | D117: 65207 | E117: CASINO Galleta Menta 51gr x 6 x 8 | F117: BELMONT - PERU - GOLOSINAS - DULCES - CASINO - Galleta Menta- 8 / 6x51g - CH117 | G117: 10 | H117: 17.6 | I117: 176 | J117: 10785.74 | K117: =COUNTIF($E$2:$E$1438,E117) -> 7 | L117: =IF(K117>1,_xlfn.CONCAT("Se repite ",K117," veces"),"No se repite") -> Se repite 7 veces | M117: =_xlfn.CONCAT(A117,"-",E117) -> Belmont International Trading Corp-CASINO Galleta Menta 51gr x 6 x 8 | N117: =COUNTIF($M$2:$M$1438,M117) -> 3 | O117: =IF(N117>1,_xlfn.CONCAT("Se repite ",N117," veces en ",A117),"No se repite en proveedor") -> Se repite 3 veces en Belmont International Trading Corp | P117: =_xlfn.CONCAT(A117,"-",E117,"-",H117) -> Belmont International Trading Corp-CASINO Galleta Menta 51gr x 6 x 8-17.6 | Q117: =COUNTIF($P$2:$P$1438,P117) -> 2 | R117: =IF(Q117>1,_xlfn.CONCAT("Se repite ",Q117," veces el precio de ",H117),"No se repite") -> Se repite 2 veces el precio de 17.6 | S117: =_xlfn.CONCAT("El producto ",E117," ",O117,IF(R117="No se repite",_xlfn.CONCAT(" Una vez con el precio ",H117),_xlfn.CONCAT(", ",R117))) -> El producto CASINO Galleta Menta 51gr x 6 x 8 Se repite 3 veces en Belmont International Trading Corp, Se repite 2 veces el precio de 17.6 | T117: =+A117 -> Belmont International Trading Corp | U117: =+E117 -> CASINO Galleta Menta 51gr x 6 x 8 | V117: =+H117 -> 17.6 | W117: =_xlfn.CONCAT(A117," ",B117) -> Belmont International Trading Corp 05/16/2025 | Z117: =G117*H117 -> 176
A118: Belmont International Trading Corp | B118: 07/31/2025 | C118: Bill | D118: 68755 | E118: CASINO Galleta Menta 51gr x 6 x 8 | F118: BELMONT - PERU - GOLOSINAS - DULCES - CASINO - Galleta Menta- 8 / 6x51g - CH117 | G118: 1 | H118: 17.6 | I118: 17.6 | J118: 17795.44 | K118: =COUNTIF($E$2:$E$1438,E118) -> 7 | L118: =IF(K118>1,_xlfn.CONCAT("Se repite ",K118," veces"),"No se repite") -> Se repite 7 veces | M118: =_xlfn.CONCAT(A118,"-",E118) -> Belmont International Trading Corp-CASINO Galleta Menta 51gr x 6 x 8 | N118: =COUNTIF($M$2:$M$1438,M118) -> 3 | O118: =IF(N118>1,_xlfn.CONCAT("Se repite ",N118," veces en ",A118),"No se repite en proveedor") -> Se repite 3 veces en Belmont International Trading Corp | P118: =_xlfn.CONCAT(A118,"-",E118,"-",H118) -> Belmont International Trading Corp-CASINO Galleta Menta 51gr x 6 x 8-17.6 | Q118: =COUNTIF($P$2:$P$1438,P118) -> 2 | R118: =IF(Q118>1,_xlfn.CONCAT("Se repite ",Q118," veces el precio de ",H118),"No se repite") -> Se repite 2 veces el precio de 17.6 | S118: =_xlfn.CONCAT("El producto ",E118," ",O118,IF(R118="No se repite",_xlfn.CONCAT(" Una vez con el precio ",H118),_xlfn.CONCAT(", ",R118))) -> El producto CASINO Galleta Menta 51gr x 6 x 8 Se repite 3 veces en Belmont International Trading Corp, Se repite 2 veces el precio de 17.6 | T118: =+A118 -> Belmont International Trading Corp | U118: =+E118 -> CASINO Galleta Menta 51gr x 6 x 8 | V118: =+H118 -> 17.6 | W118: =_xlfn.CONCAT(A118," ",B118) -> Belmont International Trading Corp 07/31/2025 | Z118: =G118*H118 -> 17.6
A119: Peru Chef | B119: 03/26/2025 | C119: Bill | E119: CASINO Galleta Menta 51gr x 6 x 8 | F119: CASINO - Galleta Menta | G119: 1 | H119: 15.5 | I119: 15.5 | J119: 1379.7 | K119: =COUNTIF($E$2:$E$1438,E119) -> 7 | L119: =IF(K119>1,_xlfn.CONCAT("Se repite ",K119," veces"),"No se repite") -> Se repite 7 veces | M119: =_xlfn.CONCAT(A119,"-",E119) -> Peru Chef-CASINO Galleta Menta 51gr x 6 x 8 | N119: =COUNTIF($M$2:$M$1438,M119) -> 4 | O119: =IF(N119>1,_xlfn.CONCAT("Se repite ",N119," veces en ",A119),"No se repite en proveedor") -> Se repite 4 veces en Peru Chef | P119: =_xlfn.CONCAT(A119,"-",E119,"-",H119) -> Peru Chef-CASINO Galleta Menta 51gr x 6 x 8-15.5 | Q119: =COUNTIF($P$2:$P$1438,P119) -> 1 | R119: =IF(Q119>1,_xlfn.CONCAT("Se repite ",Q119," veces el precio de ",H119),"No se repite") -> No se repite | S119: =_xlfn.CONCAT("El producto ",E119," ",O119,IF(R119="No se repite",_xlfn.CONCAT(" Una vez con el precio ",H119),_xlfn.CONCAT(", ",R119))) -> El producto CASINO Galleta Menta 51gr x 6 x 8 Se repite 4 veces en Peru Chef Una vez con el precio 15.5 | T119: =+A119 -> Peru Chef | U119: =+E119 -> CASINO Galleta Menta 51gr x 6 x 8 | V119: =+H119 -> 15.5 | W119: =_xlfn.CONCAT(A119," ",B119) -> Peru Chef 03/26/2025 | Z119: =G119*H119 -> 15.5
A120: Peru Chef | B120: 08/28/2025 | C120: Bill | D120: 2025001209 | E120: CASINO Galleta Menta 51gr x 6 x 8 | F120: BELMONT - PERU - GOLOSINAS - DULCES - CASINO - Galleta Menta- 8 / 6x51g - CH117 | G120: 9 | H120: 17 | I120: 153 | J120: 14970.5 | K120: =COUNTIF($E$2:$E$1438,E120) -> 7 | L120: =IF(K120>1,_xlfn.CONCAT("Se repite ",K120," veces"),"No se repite") -> Se repite 7 veces | M120: =_xlfn.CONCAT(A120,"-",E120) -> Peru Chef-CASINO Galleta Menta 51gr x 6 x 8 | N120: =COUNTIF($M$2:$M$1438,M120) -> 4 | O120: =IF(N120>1,_xlfn.CONCAT("Se repite ",N120," veces en ",A120),"No se repite en proveedor") -> Se repite 4 veces en Peru Chef | P120: =_xlfn.CONCAT(A120,"-",E120,"-",H120) -> Peru Chef-CASINO Galleta Menta 51gr x 6 x 8-17 | Q120: =COUNTIF($P$2:$P$1438,P120) -> 2 | R120: =IF(Q120>1,_xlfn.CONCAT("Se repite ",Q120," veces el precio de ",H120),"No se repite") -> Se repite 2 veces el precio de 17 | S120: =_xlfn.CONCAT("El producto ",E120," ",O120,IF(R120="No se repite",_xlfn.CONCAT(" Una vez con el precio ",H120),_xlfn.CONCAT(", ",R120))) -> El producto CASINO Galleta Menta 51gr x 6 x 8 Se repite 4 veces en Peru Chef, Se repite 2 veces el precio de 17 | T120: =+A120 -> Peru Chef | U120: =+E120 -> CASINO Galleta Menta 51gr x 6 x 8 | V120: =+H120 -> 17 | W120: =_xlfn.CONCAT(A120," ",B120) -> Peru Chef 08/28/2025 | Z120: =G120*H120 -> 153
A121: Peru Chef | B121: 09/11/2025 | C121: Bill | D121: 2025001378 | E121: CASINO Galleta Menta 51gr x 6 x 8 | F121: BELMONT - PERU - GOLOSINAS - DULCES - CASINO - Galleta Menta- 8 / 6x51g - CH117 | G121: 4 | H121: 17 | I121: 68 | J121: 19664 | K121: =COUNTIF($E$2:$E$1438,E121) -> 7 | L121: =IF(K121>1,_xlfn.CONCAT("Se repite ",K121," veces"),"No se repite") -> Se repite 7 veces | M121: =_xlfn.CONCAT(A121,"-",E121) -> Peru Chef-CASINO Galleta Menta 51gr x 6 x 8 | N121: =COUNTIF($M$2:$M$1438,M121) -> 4 | O121: =IF(N121>1,_xlfn.CONCAT("Se repite ",N121," veces en ",A121),"No se repite en proveedor") -> Se repite 4 veces en Peru Chef | P121: =_xlfn.CONCAT(A121,"-",E121,"-",H121) -> Peru Chef-CASINO Galleta Menta 51gr x 6 x 8-17 | Q121: =COUNTIF($P$2:$P$1438,P121) -> 2 | R121: =IF(Q121>1,_xlfn.CONCAT("Se repite ",Q121," veces el precio de ",H121),"No se repite") -> Se repite 2 veces el precio de 17 | S121: =_xlfn.CONCAT("El producto ",E121," ",O121,IF(R121="No se repite",_xlfn.CONCAT(" Una vez con el precio ",H121),_xlfn.CONCAT(", ",R121))) -> El producto CASINO Galleta Menta 51gr x 6 x 8 Se repite 4 veces en Peru Chef, Se repite 2 veces el precio de 17 | T121: =+A121 -> Peru Chef | U121: =+E121 -> CASINO Galleta Menta 51gr x 6 x 8 | V121: =+H121 -> 17 | W121: =_xlfn.CONCAT(A121," ",B121) -> Peru Chef 09/11/2025 | Z121: =G121*H121 -> 68
A122: Peru Chef | B122: 11/14/2025 | C122: Bill | D122: 57055 | E122: CASINO Galleta Menta 51gr x 6 x 8 | F122: BELMONT - PERU - GOLOSINAS - DULCES - CASINO - Galleta Menta- 8 / 6x51g - CH117 | G122: 12 | H122: 15.3 | I122: 183.6 | J122: 36950.35 | K122: =COUNTIF($E$2:$E$1438,E122) -> 7 | L122: =IF(K122>1,_xlfn.CONCAT("Se repite ",K122," veces"),"No se repite") -> Se repite 7 veces | M122: =_xlfn.CONCAT(A122,"-",E122) -> Peru Chef-CASINO Galleta Menta 51gr x 6 x 8 | N122: =COUNTIF($M$2:$M$1438,M122) -> 4 | O122: =IF(N122>1,_xlfn.CONCAT("Se repite ",N122," veces en ",A122),"No se repite en proveedor") -> Se repite 4 veces en Peru Chef | P122: =_xlfn.CONCAT(A122,"-",E122,"-",H122) -> Peru Chef-CASINO Galleta Menta 51gr x 6 x 8-15.3 | Q122: =COUNTIF($P$2:$P$1438,P122) -> 1 | R122: =IF(Q122>1,_xlfn.CONCAT("Se repite ",Q122," veces el precio de ",H122),"No se repite") -> No se repite | S122: =_xlfn.CONCAT("El producto ",E122," ",O122,IF(R122="No se repite",_xlfn.CONCAT(" Una vez con el precio ",H122),_xlfn.CONCAT(", ",R122))) -> El producto CASINO Galleta Menta 51gr x 6 x 8 Se repite 4 veces en Peru Chef Una vez con el precio 15.3 | T122: =+A122 -> Peru Chef | U122: =+E122 -> CASINO Galleta Menta 51gr x 6 x 8 | V122: =+H122 -> 15.3 | W122: =_xlfn.CONCAT(A122," ",B122) -> Peru Chef 11/14/2025 | Z122: =G122*H122 -> 183.6
A123: Belmont International Trading Corp | B123: 07/31/2025 | C123: Bill | D123: 68755 | E123: Chocman 30G 6 x 14 | F123: Chocman 30G | G123: 1 | H123: 21.5 | I123: 21.5 | J123: 17777.84 | K123: =COUNTIF($E$2:$E$1438,E123) -> 3 | L123: =IF(K123>1,_xlfn.CONCAT("Se repite ",K123," veces"),"No se repite") -> Se repite 3 veces | M123: =_xlfn.CONCAT(A123,"-",E123) -> Belmont International Trading Corp-Chocman 30G 6 x 14 | N123: =COUNTIF($M$2:$M$1438,M123) -> 1 | O123: =IF(N123>1,_xlfn.CONCAT("Se repite ",N123," veces en ",A123),"No se repite en proveedor") -> No se repite en proveedor | P123: =_xlfn.CONCAT(A123,"-",E123,"-",H123) -> Belmont International Trading Corp-Chocman 30G 6 x 14-21.5 | Q123: =COUNTIF($P$2:$P$1438,P123) -> 1 | R123: =IF(Q123>1,_xlfn.CONCAT("Se repite ",Q123," veces el precio de ",H123),"No se repite") -> No se repite | S123: =_xlfn.CONCAT("El producto ",E123," ",O123,IF(R123="No se repite",_xlfn.CONCAT(" Una vez con el precio ",H123),_xlfn.CONCAT(", ",R123))) -> El producto Chocman 30G 6 x 14 No se repite en proveedor Una vez con el precio 21.5 | T123: =+A123 -> Belmont International Trading Corp | U123: =+E123 -> Chocman 30G 6 x 14 | V123: =+H123 -> 21.5 | W123: =_xlfn.CONCAT(A123," ",B123) -> Belmont International Trading Corp 07/31/2025 | Z123: =G123*H123 -> 21.5
A124: Peru Chef | B124: 04/10/2025 | C124: Bill | D124: 55130 | E124: Chocman 30G 6 x 14 | F124: Chocman 30G | G124: 1 | H124: 27 | I124: 27 | J124: 4441 | K124: =COUNTIF($E$2:$E$1438,E124) -> 3 | L124: =IF(K124>1,_xlfn.CONCAT("Se repite ",K124," veces"),"No se repite") -> Se repite 3 veces | M124: =_xlfn.CONCAT(A124,"-",E124) -> Peru Chef-Chocman 30G 6 x 14 | N124: =COUNTIF($M$2:$M$1438,M124) -> 2 | O124: =IF(N124>1,_xlfn.CONCAT("Se repite ",N124," veces en ",A124),"No se repite en proveedor") -> Se repite 2 veces en Peru Chef | P124: =_xlfn.CONCAT(A124,"-",E124,"-",H124) -> Peru Chef-Chocman 30G 6 x 14-27 | Q124: =COUNTIF($P$2:$P$1438,P124) -> 2 | R124: =IF(Q124>1,_xlfn.CONCAT("Se repite ",Q124," veces el precio de ",H124),"No se repite") -> Se repite 2 veces el precio de 27 | S124: =_xlfn.CONCAT("El producto ",E124," ",O124,IF(R124="No se repite",_xlfn.CONCAT(" Una vez con el precio ",H124),_xlfn.CONCAT(", ",R124))) -> El producto Chocman 30G 6 x 14 Se repite 2 veces en Peru Chef, Se repite 2 veces el precio de 27 | T124: =+A124 -> Peru Chef | U124: =+E124 -> Chocman 30G 6 x 14 | V124: =+H124 -> 27 | W124: =_xlfn.CONCAT(A124," ",B124) -> Peru Chef 04/10/2025 | Z124: =G124*H124 -> 27
A125: Peru Chef | B125: 04/13/2025 | C125: Bill | D125: 55164 | E125: Chocman 30G 6 x 14 | F125: Chocman 30G | G125: 3 | H125: 27 | I125: 81 | J125: 5498.6 | K125: =COUNTIF($E$2:$E$1438,E125) -> 3 | L125: =IF(K125>1,_xlfn.CONCAT("Se repite ",K125," veces"),"No se repite") -> Se repite 3 veces | M125: =_xlfn.CONCAT(A125,"-",E125) -> Peru Chef-Chocman 30G 6 x 14 | N125: =COUNTIF($M$2:$M$1438,M125) -> 2 | O125: =IF(N125>1,_xlfn.CONCAT("Se repite ",N125," veces en ",A125),"No se repite en proveedor") -> Se repite 2 veces en Peru Chef | P125: =_xlfn.CONCAT(A125,"-",E125,"-",H125) -> Peru Chef-Chocman 30G 6 x 14-27 | Q125: =COUNTIF($P$2:$P$1438,P125) -> 2 | R125: =IF(Q125>1,_xlfn.CONCAT("Se repite ",Q125," veces el precio de ",H125),"No se repite") -> Se repite 2 veces el precio de 27 | S125: =_xlfn.CONCAT("El producto ",E125," ",O125,IF(R125="No se repite",_xlfn.CONCAT(" Una vez con el precio ",H125),_xlfn.CONCAT(", ",R125))) -> El producto Chocman 30G 6 x 14 Se repite 2 veces en Peru Chef, Se repite 2 veces el precio de 27 | T125: =+A125 -> Peru Chef | U125: =+E125 -> Chocman 30G 6 x 14 | V125: =+H125 -> 27 | W125: =_xlfn.CONCAT(A125," ",B125) -> Peru Chef 04/13/2025 | Z125: =G125*H125 -> 81
A126: Peru Chef | B126: 08/11/2025 | C126: Bill | D126: 56352 | E126: Chocman Doble Manjar 53gr x 8 x 6 | F126: Chockman Doble Manjar 53 Gr X 8 X 6 | G126: 7 | H126: 22 | I126: 154 | J126: 13301.5 | K126: =COUNTIF($E$2:$E$1438,E126) -> 5 | L126: =IF(K126>1,_xlfn.CONCAT("Se repite ",K126," veces"),"No se repite") -> Se repite 5 veces | M126: =_xlfn.CONCAT(A126,"-",E126) -> Peru Chef-Chocman Doble Manjar 53gr x 8 x 6 | N126: =COUNTIF($M$2:$M$1438,M126) -> 5 | O126: =IF(N126>1,_xlfn.CONCAT("Se repite ",N126," veces en ",A126),"No se repite en proveedor") -> Se repite 5 veces en Peru Chef | P126: =_xlfn.CONCAT(A126,"-",E126,"-",H126) -> Peru Chef-Chocman Doble Manjar 53gr x 8 x 6-22 | Q126: =COUNTIF($P$2:$P$1438,P126) -> 3 | R126: =IF(Q126>1,_xlfn.CONCAT("Se repite ",Q126," veces el precio de ",H126),"No se repite") -> Se repite 3 veces el precio de 22 | S126: =_xlfn.CONCAT("El producto ",E126," ",O126,IF(R126="No se repite",_xlfn.CONCAT(" Una vez con el precio ",H126),_xlfn.CONCAT(", ",R126))) -> El producto Chocman Doble Manjar 53gr x 8 x 6 Se repite 5 veces en Peru Chef, Se repite 3 veces el precio de 22 | T126: =+A126 -> Peru Chef | U126: =+E126 -> Chocman Doble Manjar 53gr x 8 x 6 | V126: =+H126 -> 22 | W126: =_xlfn.CONCAT(A126," ",B126) -> Peru Chef 08/11/2025 | Z126: =G126*H126 -> 154
A127: Peru Chef | B127: 08/28/2025 | C127: Bill | D127: 2025001209 | E127: Chocman Doble Manjar 53gr x 8 x 6 | F127: GOLOSINAS Y DULCES - - CHOCKMAN DOBLE MANJAR 53 GR X 8 X 6- / 8 | G127: 5 | H127: 22 | I127: 110 | J127: 15250.5 | K127: =COUNTIF($E$2:$E$1438,E127) -> 5 | L127: =IF(K127>1,_xlfn.CONCAT("Se repite ",K127," veces"),"No se repite") -> Se repite 5 veces | M127: =_xlfn.CONCAT(A127,"-",E127) -> Peru Chef-Chocman Doble Manjar 53gr x 8 x 6 | N127: =COUNTIF($M$2:$M$1438,M127) -> 5 | O127: =IF(N127>1,_xlfn.CONCAT("Se repite ",N127," veces en ",A127),"No se repite en proveedor") -> Se repite 5 veces en Peru Chef | P127: =_xlfn.CONCAT(A127,"-",E127,"-",H127) -> Peru Chef-Chocman Doble Manjar 53gr x 8 x 6-22 | Q127: =COUNTIF($P$2:$P$1438,P127) -> 3 | R127: =IF(Q127>1,_xlfn.CONCAT("Se repite ",Q127," veces el precio de ",H127),"No se repite") -> Se repite 3 veces el precio de 22 | S127: =_xlfn.CONCAT("El producto ",E127," ",O127,IF(R127="No se repite",_xlfn.CONCAT(" Una vez con el precio ",H127),_xlfn.CONCAT(", ",R127))) -> El producto Chocman Doble Manjar 53gr x 8 x 6 Se repite 5 veces en Peru Chef, Se repite 3 veces el precio de 22 | T127: =+A127 -> Peru Chef | U127: =+E127 -> Chocman Doble Manjar 53gr x 8 x 6 | V127: =+H127 -> 22 | W127: =_xlfn.CONCAT(A127," ",B127) -> Peru Chef 08/28/2025 | Z127: =G127*H127 -> 110
A128: Peru Chef | B128: 10/09/2025 | C128: Bill | D128: 2025001691 | E128: Chocman Doble Manjar 53gr x 8 x 6 | F128: GOLOSINAS Y DULCES - - CHOCKMAN DOBLE MANJAR 53 GR X 8 X 6- / 8 | G128: 15 | H128: 22 | I128: 330 | J128: 28041.5 | K128: =COUNTIF($E$2:$E$1438,E128) -> 5 | L128: =IF(K128>1,_xlfn.CONCAT("Se repite ",K128," veces"),"No se repite") -> Se repite 5 veces | M128: =_xlfn.CONCAT(A128,"-",E128) -> Peru Chef-Chocman Doble Manjar 53gr x 8 x 6 | N128: =COUNTIF($M$2:$M$1438,M128) -> 5 | O128: =IF(N128>1,_xlfn.CONCAT("Se repite ",N128," veces en ",A128),"No se repite en proveedor") -> Se repite 5 veces en Peru Chef | P128: =_xlfn.CONCAT(A128,"-",E128,"-",H128) -> Peru Chef-Chocman Doble Manjar 53gr x 8 x 6-22 | Q128: =COUNTIF($P$2:$P$1438,P128) -> 3 | R128: =IF(Q128>1,_xlfn.CONCAT("Se repite ",Q128," veces el precio de ",H128),"No se repite") -> Se repite 3 veces el precio de 22 | S128: =_xlfn.CONCAT("El producto ",E128," ",O128,IF(R128="No se repite",_xlfn.CONCAT(" Una vez con el precio ",H128),_xlfn.CONCAT(", ",R128))) -> El producto Chocman Doble Manjar 53gr x 8 x 6 Se repite 5 veces en Peru Chef, Se repite 3 veces el precio de 22 | T128: =+A128 -> Peru Chef | U128: =+E128 -> Chocman Doble Manjar 53gr x 8 x 6 | V128: =+H128 -> 22 | W128: =_xlfn.CONCAT(A128," ",B128) -> Peru Chef 10/09/2025 | Z128: =G128*H128 -> 330
A129: Peru Chef | B129: 10/28/2025 | C129: Bill | D129: 2025001895 | E129: Chocman Doble Manjar 53gr x 8 x 6 | F129: GOLOSINAS Y DULCES - - CHOCKMAN DOBLE MANJAR 53 GR X 8 X 6- / 8 | G129: 3 | H129: 19.8 | I129: 59.4 | J129: 30357.4 | K129: =COUNTIF($E$2:$E$1438,E129) -> 5 | L129: =IF(K129>1,_xlfn.CONCAT("Se repite ",K129," veces"),"No se repite") -> Se repite 5 veces | M129: =_xlfn.CONCAT(A129,"-",E129) -> Peru Chef-Chocman Doble Manjar 53gr x 8 x 6 | N129: =COUNTIF($M$2:$M$1438,M129) -> 5 | O129: =IF(N129>1,_xlfn.CONCAT("Se repite ",N129," veces en ",A129),"No se repite en proveedor") -> Se repite 5 veces en Peru Chef | P129: =_xlfn.CONCAT(A129,"-",E129,"-",H129) -> Peru Chef-Chocman Doble Manjar 53gr x 8 x 6-19.8 | Q129: =COUNTIF($P$2:$P$1438,P129) -> 2 | R129: =IF(Q129>1,_xlfn.CONCAT("Se repite ",Q129," veces el precio de ",H129),"No se repite") -> Se repite 2 veces el precio de 19.8 | S129: =_xlfn.CONCAT("El producto ",E129," ",O129,IF(R129="No se repite",_xlfn.CONCAT(" Una vez con el precio ",H129),_xlfn.CONCAT(", ",R129))) -> El producto Chocman Doble Manjar 53gr x 8 x 6 Se repite 5 veces en Peru Chef, Se repite 2 veces el precio de 19.8 | T129: =+A129 -> Peru Chef | U129: =+E129 -> Chocman Doble Manjar 53gr x 8 x 6 | V129: =+H129 -> 19.8 | W129: =_xlfn.CONCAT(A129," ",B129) -> Peru Chef 10/28/2025 | Z129: =G129*H129 -> 59.4
A130: Peru Chef | B130: 12/09/2025 | C130: Bill | D130: 2025002373 | E130: Chocman Doble Manjar 53gr x 8 x 6 | F130: GOLOSINAS Y DULCES - - CHOCKMAN DOBLE MANJAR 53 GR X 8 X 6- / 8 | G130: 6 | H130: 19.8 | I130: 118.8 | J130: 39698.05 | K130: =COUNTIF($E$2:$E$1438,E130) -> 5 | L130: =IF(K130>1,_xlfn.CONCAT("Se repite ",K130," veces"),"No se repite") -> Se repite 5 veces | M130: =_xlfn.CONCAT(A130,"-",E130) -> Peru Chef-Chocman Doble Manjar 53gr x 8 x 6 | N130: =COUNTIF($M$2:$M$1438,M130) -> 5 | O130: =IF(N130>1,_xlfn.CONCAT("Se repite ",N130," veces en ",A130),"No se repite en proveedor") -> Se repite 5 veces en Peru Chef | P130: =_xlfn.CONCAT(A130,"-",E130,"-",H130) -> Peru Chef-Chocman Doble Manjar 53gr x 8 x 6-19.8 | Q130: =COUNTIF($P$2:$P$1438,P130) -> 2 | R130: =IF(Q130>1,_xlfn.CONCAT("Se repite ",Q130," veces el precio de ",H130),"No se repite") -> Se repite 2 veces el precio de 19.8 | S130: =_xlfn.CONCAT("El producto ",E130," ",O130,IF(R130="No se repite",_xlfn.CONCAT(" Una vez con el precio ",H130),_xlfn.CONCAT(", ",R130))) -> El producto Chocman Doble Manjar 53gr x 8 x 6 Se repite 5 veces en Peru Chef, Se repite 2 veces el precio de 19.8 | T130: =+A130 -> Peru Chef | U130: =+E130 -> Chocman Doble Manjar 53gr x 8 x 6 | V130: =+H130 -> 19.8 | W130: =_xlfn.CONCAT(A130," ",B130) -> Peru Chef 12/09/2025 | Z130: =G130*H130 -> 118.8
A131: Belmont International Trading Corp | B131: 04/28/2025 | C131: Bill | D131: 64308 | E131: Chocolate Cuzco con canela y clavo 4 x 12 | F131: Chocolate Cuzco con canela y clavo 4 x 12 | G131: 1 | H131: 30 | I131: 30 | J131: 1115.8 | K131: =COUNTIF($E$2:$E$1438,E131) -> 1 | L131: =IF(K131>1,_xlfn.CONCAT("Se repite ",K131," veces"),"No se repite") -> No se repite | M131: =_xlfn.CONCAT(A131,"-",E131) -> Belmont International Trading Corp-Chocolate Cuzco con canela y clavo 4 x 12 | N131: =COUNTIF($M$2:$M$1438,M131) -> 1 | O131: =IF(N131>1,_xlfn.CONCAT("Se repite ",N131," veces en ",A131),"No se repite en proveedor") -> No se repite en proveedor | P131: =_xlfn.CONCAT(A131,"-",E131,"-",H131) -> Belmont International Trading Corp-Chocolate Cuzco con canela y clavo 4 x 12-30 | Q131: =COUNTIF($P$2:$P$1438,P131) -> 1 | R131: =IF(Q131>1,_xlfn.CONCAT("Se repite ",Q131," veces el precio de ",H131),"No se repite") -> No se repite | S131: =_xlfn.CONCAT("El producto ",E131," ",O131,IF(R131="No se repite",_xlfn.CONCAT(" Una vez con el precio ",H131),_xlfn.CONCAT(", ",R131))) -> El producto Chocolate Cuzco con canela y clavo 4 x 12 No se repite en proveedor Una vez con el precio 30 | T131: =+A131 -> Belmont International Trading Corp | U131: =+E131 -> Chocolate Cuzco con canela y clavo 4 x 12 | V131: =+H131 -> 30 | W131: =_xlfn.CONCAT(A131," ",B131) -> Belmont International Trading Corp 04/28/2025 | Z131: =G131*H131 -> 30
A132: Belmont International Trading Corp | B132: 04/28/2025 | C132: Bill | D132: 64308 | E132: Chocolate Cuzco regular 4 x 12 | F132: Chocolate Cuzco regular 4 x 12 / 859174003672 / AB-07 | G132: 1 | H132: 30 | I132: 30 | J132: 1145.8 | K132: =COUNTIF($E$2:$E$1438,E132) -> 2 | L132: =IF(K132>1,_xlfn.CONCAT("Se repite ",K132," veces"),"No se repite") -> Se repite 2 veces | M132: =_xlfn.CONCAT(A132,"-",E132) -> Belmont International Trading Corp-Chocolate Cuzco regular 4 x 12 | N132: =COUNTIF($M$2:$M$1438,M132) -> 2 | O132: =IF(N132>1,_xlfn.CONCAT("Se repite ",N132," veces en ",A132),"No se repite en proveedor") -> Se repite 2 veces en Belmont International Trading Corp | P132: =_xlfn.CONCAT(A132,"-",E132,"-",H132) -> Belmont International Trading Corp-Chocolate Cuzco regular 4 x 12-30 | Q132: =COUNTIF($P$2:$P$1438,P132) -> 1 | R132: =IF(Q132>1,_xlfn.CONCAT("Se repite ",Q132," veces el precio de ",H132),"No se repite") -> No se repite | S132: =_xlfn.CONCAT("El producto ",E132," ",O132,IF(R132="No se repite",_xlfn.CONCAT(" Una vez con el precio ",H132),_xlfn.CONCAT(", ",R132))) -> El producto Chocolate Cuzco regular 4 x 12 Se repite 2 veces en Belmont International Trading Corp Una vez con el precio 30 | T132: =+A132 -> Belmont International Trading Corp | U132: =+E132 -> Chocolate Cuzco regular 4 x 12 | V132: =+H132 -> 30 | W132: =_xlfn.CONCAT(A132," ",B132) -> Belmont International Trading Corp 04/28/2025 | Z132: =G132*H132 -> 30
A133: Belmont International Trading Corp | B133: 04/28/2025 | C133: Bill | D133: 64308 | E133: Chocolate Cuzco regular 4 x 12 | F133: Chocolate Cuzco regular 4 x 12 / 859174003672 / AB-07 | G133: 1 | H133: 4 | I133: 4 | J133: 5472.44 | K133: =COUNTIF($E$2:$E$1438,E133) -> 2 | L133: =IF(K133>1,_xlfn.CONCAT("Se repite ",K133," veces"),"No se repite") -> Se repite 2 veces | M133: =_xlfn.CONCAT(A133,"-",E133) -> Belmont International Trading Corp-Chocolate Cuzco regular 4 x 12 | N133: =COUNTIF($M$2:$M$1438,M133) -> 2 | O133: =IF(N133>1,_xlfn.CONCAT("Se repite ",N133," veces en ",A133),"No se repite en proveedor") -> Se repite 2 veces en Belmont International Trading Corp | P133: =_xlfn.CONCAT(A133,"-",E133,"-",H133) -> Belmont International Trading Corp-Chocolate Cuzco regular 4 x 12-4 | Q133: =COUNTIF($P$2:$P$1438,P133) -> 1 | R133: =IF(Q133>1,_xlfn.CONCAT("Se repite ",Q133," veces el precio de ",H133),"No se repite") -> No se repite | S133: =_xlfn.CONCAT("El producto ",E133," ",O133,IF(R133="No se repite",_xlfn.CONCAT(" Una vez con el precio ",H133),_xlfn.CONCAT(", ",R133))) -> El producto Chocolate Cuzco regular 4 x 12 Se repite 2 veces en Belmont International Trading Corp Una vez con el precio 4 | T133: =+A133 -> Belmont International Trading Corp | U133: =+E133 -> Chocolate Cuzco regular 4 x 12 | V133: =+H133 -> 4 | W133: =_xlfn.CONCAT(A133," ",B133) -> Belmont International Trading Corp 04/28/2025 | X133: Repetido con el mismo precio en la misma lista | Y133: Al sobreescribir el precio lo pone como descuento | Z133: =G133*H133 -> 4
A134: Peru Chef | B134: 04/13/2025 | C134: Bill | D134: 55164 | E134: Chocolate Triangulo x 22 | F134: Chocolate Triangulo | G134: 5 | H134: 15.5 | I134: 77.5 | J134: 5201.6 | K134: =COUNTIF($E$2:$E$1438,E134) -> 6 | L134: =IF(K134>1,_xlfn.CONCAT("Se repite ",K134," veces"),"No se repite") -> Se repite 6 veces | M134: =_xlfn.CONCAT(A134,"-",E134) -> Peru Chef-Chocolate Triangulo x 22 | N134: =COUNTIF($M$2:$M$1438,M134) -> 6 | O134: =IF(N134>1,_xlfn.CONCAT("Se repite ",N134," veces en ",A134),"No se repite en proveedor") -> Se repite 6 veces en Peru Chef | P134: =_xlfn.CONCAT(A134,"-",E134,"-",H134) -> Peru Chef-Chocolate Triangulo x 22-15.5 | Q134: =COUNTIF($P$2:$P$1438,P134) -> 4 | R134: =IF(Q134>1,_xlfn.CONCAT("Se repite ",Q134," veces el precio de ",H134),"No se repite") -> Se repite 4 veces el precio de 15.5 | S134: =_xlfn.CONCAT("El producto ",E134," ",O134,IF(R134="No se repite",_xlfn.CONCAT(" Una vez con el precio ",H134),_xlfn.CONCAT(", ",R134))) -> El producto Chocolate Triangulo x 22 Se repite 6 veces en Peru Chef, Se repite 4 veces el precio de 15.5 | T134: =+A134 -> Peru Chef | U134: =+E134 -> Chocolate Triangulo x 22 | V134: =+H134 -> 15.5 | W134: =_xlfn.CONCAT(A134," ",B134) -> Peru Chef 04/13/2025 | Z134: =G134*H134 -> 77.5
A135: Peru Chef | B135: 04/24/2025 | C135: Bill | D135: 55372 | E135: Chocolate Triangulo x 22 | F135: Chocolate Triangulo | G135: 25 | H135: 15.5 | I135: 387.5 | J135: 8716.7 | K135: =COUNTIF($E$2:$E$1438,E135) -> 6 | L135: =IF(K135>1,_xlfn.CONCAT("Se repite ",K135," veces"),"No se repite") -> Se repite 6 veces | M135: =_xlfn.CONCAT(A135,"-",E135) -> Peru Chef-Chocolate Triangulo x 22 | N135: =COUNTIF($M$2:$M$1438,M135) -> 6 | O135: =IF(N135>1,_xlfn.CONCAT("Se repite ",N135," veces en ",A135),"No se repite en proveedor") -> Se repite 6 veces en Peru Chef | P135: =_xlfn.CONCAT(A135,"-",E135,"-",H135) -> Peru Chef-Chocolate Triangulo x 22-15.5 | Q135: =COUNTIF($P$2:$P$1438,P135) -> 4 | R135: =IF(Q135>1,_xlfn.CONCAT("Se repite ",Q135," veces el precio de ",H135),"No se repite") -> Se repite 4 veces el precio de 15.5 | S135: =_xlfn.CONCAT("El producto ",E135," ",O135,IF(R135="No se repite",_xlfn.CONCAT(" Una vez con el precio ",H135),_xlfn.CONCAT(", ",R135))) -> El producto Chocolate Triangulo x 22 Se repite 6 veces en Peru Chef, Se repite 4 veces el precio de 15.5 | T135: =+A135 -> Peru Chef | U135: =+E135 -> Chocolate Triangulo x 22 | V135: =+H135 -> 15.5 | W135: =_xlfn.CONCAT(A135," ",B135) -> Peru Chef 04/24/2025 | Z135: =G135*H135 -> 387.5
A136: Peru Chef | B136: 09/11/2025 | C136: Bill | D136: 2025001378 | E136: Chocolate Triangulo x 22 | F136: Chocolate Triangulo | G136: 5 | H136: 15.5 | I136: 77.5 | J136: 19447 | K136: =COUNTIF($E$2:$E$1438,E136) -> 6 | L136: =IF(K136>1,_xlfn.CONCAT("Se repite ",K136," veces"),"No se repite") -> Se repite 6 veces | M136: =_xlfn.CONCAT(A136,"-",E136) -> Peru Chef-Chocolate Triangulo x 22 | N136: =COUNTIF($M$2:$M$1438,M136) -> 6 | O136: =IF(N136>1,_xlfn.CONCAT("Se repite ",N136," veces en ",A136),"No se repite en proveedor") -> Se repite 6 veces en Peru Chef | P136: =_xlfn.CONCAT(A136,"-",E136,"-",H136) -> Peru Chef-Chocolate Triangulo x 22-15.5 | Q136: =COUNTIF($P$2:$P$1438,P136) -> 4 | R136: =IF(Q136>1,_xlfn.CONCAT("Se repite ",Q136," veces el precio de ",H136),"No se repite") -> Se repite 4 veces el precio de 15.5 | S136: =_xlfn.CONCAT("El producto ",E136," ",O136,IF(R136="No se repite",_xlfn.CONCAT(" Una vez con el precio ",H136),_xlfn.CONCAT(", ",R136))) -> El producto Chocolate Triangulo x 22 Se repite 6 veces en Peru Chef, Se repite 4 veces el precio de 15.5 | T136: =+A136 -> Peru Chef | U136: =+E136 -> Chocolate Triangulo x 22 | V136: =+H136 -> 15.5 | W136: =_xlfn.CONCAT(A136," ",B136) -> Peru Chef 09/11/2025 | Z136: =G136*H136 -> 77.5
A137: Peru Chef | B137: 10/09/2025 | C137: Bill | D137: 2025001691 | E137: Chocolate Triangulo x 22 | F137: Chocolate Triangulo | G137: 10 | H137: 15.5 | I137: 155 | J137: 26719 | K137: =COUNTIF($E$2:$E$1438,E137) -> 6 | L137: =IF(K137>1,_xlfn.CONCAT("Se repite ",K137," veces"),"No se repite") -> Se repite 6 veces | M137: =_xlfn.CONCAT(A137,"-",E137) -> Peru Chef-Chocolate Triangulo x 22 | N137: =COUNTIF($M$2:$M$1438,M137) -> 6 | O137: =IF(N137>1,_xlfn.CONCAT("Se repite ",N137," veces en ",A137),"No se repite en proveedor") -> Se repite 6 veces en Peru Chef | P137: =_xlfn.CONCAT(A137,"-",E137,"-",H137) -> Peru Chef-Chocolate Triangulo x 22-15.5 | Q137: =COUNTIF($P$2:$P$1438,P137) -> 4 | R137: =IF(Q137>1,_xlfn.CONCAT("Se repite ",Q137," veces el precio de ",H137),"No se repite") -> Se repite 4 veces el precio de 15.5 | S137: =_xlfn.CONCAT("El producto ",E137," ",O137,IF(R137="No se repite",_xlfn.CONCAT(" Una vez con el precio ",H137),_xlfn.CONCAT(", ",R137))) -> El producto Chocolate Triangulo x 22 Se repite 6 veces en Peru Chef, Se repite 4 veces el precio de 15.5 | T137: =+A137 -> Peru Chef | U137: =+E137 -> Chocolate Triangulo x 22 | V137: =+H137 -> 15.5 | W137: =_xlfn.CONCAT(A137," ",B137) -> Peru Chef 10/09/2025 | Z137: =G137*H137 -> 155
A138: Peru Chef | B138: 10/28/2025 | C138: Bill | D138: 2025001895 | E138: Chocolate Triangulo x 22 | F138: Chocolate Triangulo | G138: 6 | H138: 13.95 | I138: 83.7 | J138: 29963.2 | K138: =COUNTIF($E$2:$E$1438,E138) -> 6 | L138: =IF(K138>1,_xlfn.CONCAT("Se repite ",K138," veces"),"No se repite") -> Se repite 6 veces | M138: =_xlfn.CONCAT(A138,"-",E138) -> Peru Chef-Chocolate Triangulo x 22 | N138: =COUNTIF($M$2:$M$1438,M138) -> 6 | O138: =IF(N138>1,_xlfn.CONCAT("Se repite ",N138," veces en ",A138),"No se repite en proveedor") -> Se repite 6 veces en Peru Chef | P138: =_xlfn.CONCAT(A138,"-",E138,"-",H138) -> Peru Chef-Chocolate Triangulo x 22-13.95 | Q138: =COUNTIF($P$2:$P$1438,P138) -> 2 | R138: =IF(Q138>1,_xlfn.CONCAT("Se repite ",Q138," veces el precio de ",H138),"No se repite") -> Se repite 2 veces el precio de 13.95 | S138: =_xlfn.CONCAT("El producto ",E138," ",O138,IF(R138="No se repite",_xlfn.CONCAT(" Una vez con el precio ",H138),_xlfn.CONCAT(", ",R138))) -> El producto Chocolate Triangulo x 22 Se repite 6 veces en Peru Chef, Se repite 2 veces el precio de 13.95 | T138: =+A138 -> Peru Chef | U138: =+E138 -> Chocolate Triangulo x 22 | V138: =+H138 -> 13.95 | W138: =_xlfn.CONCAT(A138," ",B138) -> Peru Chef 10/28/2025 | Z138: =G138*H138 -> 83.7
A139: Peru Chef | B139: 11/14/2025 | C139: Bill | D139: 57055 | E139: Chocolate Triangulo x 22 | F139: GOLOSINAS Y DULCES - - CHOCOLATE TRIANGULO- DISPLAY X 22 / 1 | G139: 20 | H139: 13.95 | I139: 279 | J139: 36151.15 | K139: =COUNTIF($E$2:$E$1438,E139) -> 6 | L139: =IF(K139>1,_xlfn.CONCAT("Se repite ",K139," veces"),"No se repite") -> Se repite 6 veces | M139: =_xlfn.CONCAT(A139,"-",E139) -> Peru Chef-Chocolate Triangulo x 22 | N139: =COUNTIF($M$2:$M$1438,M139) -> 6 | O139: =IF(N139>1,_xlfn.CONCAT("Se repite ",N139," veces en ",A139),"No se repite en proveedor") -> Se repite 6 veces en Peru Chef | P139: =_xlfn.CONCAT(A139,"-",E139,"-",H139) -> Peru Chef-Chocolate Triangulo x 22-13.95 | Q139: =COUNTIF($P$2:$P$1438,P139) -> 2 | R139: =IF(Q139>1,_xlfn.CONCAT("Se repite ",Q139," veces el precio de ",H139),"No se repite") -> Se repite 2 veces el precio de 13.95 | S139: =_xlfn.CONCAT("El producto ",E139," ",O139,IF(R139="No se repite",_xlfn.CONCAT(" Una vez con el precio ",H139),_xlfn.CONCAT(", ",R139))) -> El producto Chocolate Triangulo x 22 Se repite 6 veces en Peru Chef, Se repite 2 veces el precio de 13.95 | T139: =+A139 -> Peru Chef | U139: =+E139 -> Chocolate Triangulo x 22 | V139: =+H139 -> 13.95 | W139: =_xlfn.CONCAT(A139," ",B139) -> Peru Chef 11/14/2025 | Z139: =G139*H139 -> 279
A140: Tradiciones Andinas | B140: 07/21/2025 | C140: Bill | D140: 483292 | E140: Coco Milk Drink with Nata de Coco MANGO | F140: Coco Milk Drink with Nata de Coco MANGO | G140: 3 | H140: 23.76 | I140: 71.28 | J140: 63230.9 | K140: =COUNTIF($E$2:$E$1438,E140) -> 1 | L140: =IF(K140>1,_xlfn.CONCAT("Se repite ",K140," veces"),"No se repite") -> No se repite | M140: =_xlfn.CONCAT(A140,"-",E140) -> Tradiciones Andinas-Coco Milk Drink with Nata de Coco MANGO | N140: =COUNTIF($M$2:$M$1438,M140) -> 1 | O140: =IF(N140>1,_xlfn.CONCAT("Se repite ",N140," veces en ",A140),"No se repite en proveedor") -> No se repite en proveedor | P140: =_xlfn.CONCAT(A140,"-",E140,"-",H140) -> Tradiciones Andinas-Coco Milk Drink with Nata de Coco MANGO-23.76 | Q140: =COUNTIF($P$2:$P$1438,P140) -> 1 | R140: =IF(Q140>1,_xlfn.CONCAT("Se repite ",Q140," veces el precio de ",H140),"No se repite") -> No se repite | S140: =_xlfn.CONCAT("El producto ",E140," ",O140,IF(R140="No se repite",_xlfn.CONCAT(" Una vez con el precio ",H140),_xlfn.CONCAT(", ",R140))) -> El producto Coco Milk Drink with Nata de Coco MANGO No se repite en proveedor Una vez con el precio 23.76 | T140: =+A140 -> Tradiciones Andinas | U140: =+E140 -> Coco Milk Drink with Nata de Coco MANGO | V140: =+H140 -> 23.76 | W140: =_xlfn.CONCAT(A140," ",B140) -> Tradiciones Andinas 07/21/2025 | Z140: =G140*H140 -> 71.28
A141: Tradiciones Andinas | B141: 07/21/2025 | C141: Bill | D141: 483292 | E141: Coco Milk Drink with Nata de Coco ORIGINAL | F141: Coco Milk Drink with Nata de Coco ORIGINAL | G141: 3 | H141: 23.76 | I141: 71.28 | J141: 63088.34 | K141: =COUNTIF($E$2:$E$1438,E141) -> 1 | L141: =IF(K141>1,_xlfn.CONCAT("Se repite ",K141," veces"),"No se repite") -> No se repite | M141: =_xlfn.CONCAT(A141,"-",E141) -> Tradiciones Andinas-Coco Milk Drink with Nata de Coco ORIGINAL | N141: =COUNTIF($M$2:$M$1438,M141) -> 1 | O141: =IF(N141>1,_xlfn.CONCAT("Se repite ",N141," veces en ",A141),"No se repite en proveedor") -> No se repite en proveedor | P141: =_xlfn.CONCAT(A141,"-",E141,"-",H141) -> Tradiciones Andinas-Coco Milk Drink with Nata de Coco ORIGINAL-23.76 | Q141: =COUNTIF($P$2:$P$1438,P141) -> 1 | R141: =IF(Q141>1,_xlfn.CONCAT("Se repite ",Q141," veces el precio de ",H141),"No se repite") -> No se repite | S141: =_xlfn.CONCAT("El producto ",E141," ",O141,IF(R141="No se repite",_xlfn.CONCAT(" Una vez con el precio ",H141),_xlfn.CONCAT(", ",R141))) -> El producto Coco Milk Drink with Nata de Coco ORIGINAL No se repite en proveedor Una vez con el precio 23.76 | T141: =+A141 -> Tradiciones Andinas | U141: =+E141 -> Coco Milk Drink with Nata de Coco ORIGINAL | V141: =+H141 -> 23.76 | W141: =_xlfn.CONCAT(A141," ",B141) -> Tradiciones Andinas 07/21/2025 | Z141: =G141*H141 -> 71.28
A142: Tradiciones Andinas | B142: 07/21/2025 | C142: Bill | D142: 483292 | E142: Coco Milk Drink with Nata de Coco STRAWBERRY | F142: Coco Milk Drink with Nata de Coco STRAWBERRY | G142: 3 | H142: 23.76 | I142: 71.28 | J142: 63159.62 | K142: =COUNTIF($E$2:$E$1438,E142) -> 1 | L142: =IF(K142>1,_xlfn.CONCAT("Se repite ",K142," veces"),"No se repite") -> No se repite | M142: =_xlfn.CONCAT(A142,"-",E142) -> Tradiciones Andinas-Coco Milk Drink with Nata de Coco STRAWBERRY | N142: =COUNTIF($M$2:$M$1438,M142) -> 1 | O142: =IF(N142>1,_xlfn.CONCAT("Se repite ",N142," veces en ",A142),"No se repite en proveedor") -> No se repite en proveedor | P142: =_xlfn.CONCAT(A142,"-",E142,"-",H142) -> Tradiciones Andinas-Coco Milk Drink with Nata de Coco STRAWBERRY-23.76 | Q142: =COUNTIF($P$2:$P$1438,P142) -> 1 | R142: =IF(Q142>1,_xlfn.CONCAT("Se repite ",Q142," veces el precio de ",H142),"No se repite") -> No se repite | S142: =_xlfn.CONCAT("El producto ",E142," ",O142,IF(R142="No se repite",_xlfn.CONCAT(" Una vez con el precio ",H142),_xlfn.CONCAT(", ",R142))) -> El producto Coco Milk Drink with Nata de Coco STRAWBERRY No se repite en proveedor Una vez con el precio 23.76 | T142: =+A142 -> Tradiciones Andinas | U142: =+E142 -> Coco Milk Drink with Nata de Coco STRAWBERRY | V142: =+H142 -> 23.76 | W142: =_xlfn.CONCAT(A142," ",B142) -> Tradiciones Andinas 07/21/2025 | Z142: =G142*H142 -> 71.28
A143: La Sorpresa Store | B143: 08/26/2025 | C143: Bill | E143: Conaprole - Dulce de Leche - Milk Caramel Spread | F143: Conaprole - Dulce de Leche - Milk Caramel Spread | G143: 1 | H143: 148 | I143: 148 | J143: 223 | K143: =COUNTIF($E$2:$E$1438,E143) -> 1 | L143: =IF(K143>1,_xlfn.CONCAT("Se repite ",K143," veces"),"No se repite") -> No se repite | M143: =_xlfn.CONCAT(A143,"-",E143) -> La Sorpresa Store-Conaprole - Dulce de Leche - Milk Caramel Spread | N143: =COUNTIF($M$2:$M$1438,M143) -> 1 | O143: =IF(N143>1,_xlfn.CONCAT("Se repite ",N143," veces en ",A143),"No se repite en proveedor") -> No se repite en proveedor | P143: =_xlfn.CONCAT(A143,"-",E143,"-",H143) -> La Sorpresa Store-Conaprole - Dulce de Leche - Milk Caramel Spread-148 | Q143: =COUNTIF($P$2:$P$1438,P143) -> 1 | R143: =IF(Q143>1,_xlfn.CONCAT("Se repite ",Q143," veces el precio de ",H143),"No se repite") -> No se repite | S143: =_xlfn.CONCAT("El producto ",E143," ",O143,IF(R143="No se repite",_xlfn.CONCAT(" Una vez con el precio ",H143),_xlfn.CONCAT(", ",R143))) -> El producto Conaprole - Dulce de Leche - Milk Caramel Spread No se repite en proveedor Una vez con el precio 148 | T143: =+A143 -> La Sorpresa Store | U143: =+E143 -> Conaprole - Dulce de Leche - Milk Caramel Spread | V143: =+H143 -> 148 | W143: =_xlfn.CONCAT(A143," ",B143) -> La Sorpresa Store 08/26/2025 | Z143: =G143*H143 -> 148
A144: Belmont International Trading Corp | B144: 04/28/2025 | C144: Bill | D144: 64308 | E144: CORONITA - Galleta de Chocolate x 6 x 28 | F144: TA- PERU - GOLOSINAS - DULCES - CORONITA - Galleta de Chocolate- 28 / 38gr - CH131 | G144: 1 | H144: 56 | I144: 56 | J144: 3414.3 | K144: =COUNTIF($E$2:$E$1438,E144) -> 2 | L144: =IF(K144>1,_xlfn.CONCAT("Se repite ",K144," veces"),"No se repite") -> Se repite 2 veces | M144: =_xlfn.CONCAT(A144,"-",E144) -> Belmont International Trading Corp-CORONITA - Galleta de Chocolate x 6 x 28 | N144: =COUNTIF($M$2:$M$1438,M144) -> 2 | O144: =IF(N144>1,_xlfn.CONCAT("Se repite ",N144," veces en ",A144),"No se repite en proveedor") -> Se repite 2 veces en Belmont International Trading Corp | P144: =_xlfn.CONCAT(A144,"-",E144,"-",H144) -> Belmont International Trading Corp-CORONITA - Galleta de Chocolate x 6 x 28-56 | Q144: =COUNTIF($P$2:$P$1438,P144) -> 1 | R144: =IF(Q144>1,_xlfn.CONCAT("Se repite ",Q144," veces el precio de ",H144),"No se repite") -> No se repite | S144: =_xlfn.CONCAT("El producto ",E144," ",O144,IF(R144="No se repite",_xlfn.CONCAT(" Una vez con el precio ",H144),_xlfn.CONCAT(", ",R144))) -> El producto CORONITA - Galleta de Chocolate x 6 x 28 Se repite 2 veces en Belmont International Trading Corp Una vez con el precio 56 | T144: =+A144 -> Belmont International Trading Corp | U144: =+E144 -> CORONITA - Galleta de Chocolate x 6 x 28 | V144: =+H144 -> 56 | W144: =_xlfn.CONCAT(A144," ",B144) -> Belmont International Trading Corp 04/28/2025 | Z144: =G144*H144 -> 56
A145: Belmont International Trading Corp | B145: 05/16/2025 | C145: Bill | D145: 65207 | E145: CORONITA - Galleta de Chocolate x 6 x 28 | F145: TA- PERU - GOLOSINAS - DULCES - CORONITA - Galleta de Chocolate- 28 / 38gr - CH131 | G145: 10 | H145: 61.6 | I145: 616 | J145: 10433.74 | K145: =COUNTIF($E$2:$E$1438,E145) -> 2 | L145: =IF(K145>1,_xlfn.CONCAT("Se repite ",K145," veces"),"No se repite") -> Se repite 2 veces | M145: =_xlfn.CONCAT(A145,"-",E145) -> Belmont International Trading Corp-CORONITA - Galleta de Chocolate x 6 x 28 | N145: =COUNTIF($M$2:$M$1438,M145) -> 2 | O145: =IF(N145>1,_xlfn.CONCAT("Se repite ",N145," veces en ",A145),"No se repite en proveedor") -> Se repite 2 veces en Belmont International Trading Corp | P145: =_xlfn.CONCAT(A145,"-",E145,"-",H145) -> Belmont International Trading Corp-CORONITA - Galleta de Chocolate x 6 x 28-61.6 | Q145: =COUNTIF($P$2:$P$1438,P145) -> 1 | R145: =IF(Q145>1,_xlfn.CONCAT("Se repite ",Q145," veces el precio de ",H145),"No se repite") -> No se repite | S145: =_xlfn.CONCAT("El producto ",E145," ",O145,IF(R145="No se repite",_xlfn.CONCAT(" Una vez con el precio ",H145),_xlfn.CONCAT(", ",R145))) -> El producto CORONITA - Galleta de Chocolate x 6 x 28 Se repite 2 veces en Belmont International Trading Corp Una vez con el precio 61.6 | T145: =+A145 -> Belmont International Trading Corp | U145: =+E145 -> CORONITA - Galleta de Chocolate x 6 x 28 | V145: =+H145 -> 61.6 | W145: =_xlfn.CONCAT(A145," ",B145) -> Belmont International Trading Corp 05/16/2025 | Z145: =G145*H145 -> 616
A146: Belmont International Trading Corp | B146: 04/28/2025 | C146: Bill | D146: 64308 | E146: Cua Cua 9 x 24 | F146: TA- PERU - GOLOSINAS - DULCES - Cua Cua 18g x 9 x 24 / CH105 | G146: 2 | H146: 63 | I146: 126 | J146: 3218.3 | K146: =COUNTIF($E$2:$E$1438,E146) -> 9 | L146: =IF(K146>1,_xlfn.CONCAT("Se repite ",K146," veces"),"No se repite") -> Se repite 9 veces | M146: =_xlfn.CONCAT(A146,"-",E146) -> Belmont International Trading Corp-Cua Cua 9 x 24 | N146: =COUNTIF($M$2:$M$1438,M146) -> 1 | O146: =IF(N146>1,_xlfn.CONCAT("Se repite ",N146," veces en ",A146),"No se repite en proveedor") -> No se repite en proveedor | P146: =_xlfn.CONCAT(A146,"-",E146,"-",H146) -> Belmont International Trading Corp-Cua Cua 9 x 24-63 | Q146: =COUNTIF($P$2:$P$1438,P146) -> 1 | R146: =IF(Q146>1,_xlfn.CONCAT("Se repite ",Q146," veces el precio de ",H146),"No se repite") -> No se repite | S146: =_xlfn.CONCAT("El producto ",E146," ",O146,IF(R146="No se repite",_xlfn.CONCAT(" Una vez con el precio ",H146),_xlfn.CONCAT(", ",R146))) -> El producto Cua Cua 9 x 24 No se repite en proveedor Una vez con el precio 63 | T146: =+A146 -> Belmont International Trading Corp | U146: =+E146 -> Cua Cua 9 x 24 | V146: =+H146 -> 63 | W146: =_xlfn.CONCAT(A146," ",B146) -> Belmont International Trading Corp 04/28/2025 | Z146: =G146*H146 -> 126
A147: Peru Chef | B147: 04/13/2025 | C147: Bill | D147: 55164 | E147: Cua Cua 9 x 24 | F147: TA- PERU - GOLOSINAS - DULCES - Cua Cua 18g x 9 x 24 / CH105 | G147: 1 | H147: 68 | I147: 68 | J147: 5417.6 | K147: =COUNTIF($E$2:$E$1438,E147) -> 9 | L147: =IF(K147>1,_xlfn.CONCAT("Se repite ",K147," veces"),"No se repite") -> Se repite 9 veces | M147: =_xlfn.CONCAT(A147,"-",E147) -> Peru Chef-Cua Cua 9 x 24 | N147: =COUNTIF($M$2:$M$1438,M147) -> 1 | O147: =IF(N147>1,_xlfn.CONCAT("Se repite ",N147," veces en ",A147),"No se repite en proveedor") -> No se repite en proveedor | P147: =_xlfn.CONCAT(A147,"-",E147,"-",H147) -> Peru Chef-Cua Cua 9 x 24-68 | Q147: =COUNTIF($P$2:$P$1438,P147) -> 1 | R147: =IF(Q147>1,_xlfn.CONCAT("Se repite ",Q147," veces el precio de ",H147),"No se repite") -> No se repite | S147: =_xlfn.CONCAT("El producto ",E147," ",O147,IF(R147="No se repite",_xlfn.CONCAT(" Una vez con el precio ",H147),_xlfn.CONCAT(", ",R147))) -> El producto Cua Cua 9 x 24 No se repite en proveedor Una vez con el precio 68 | T147: =+A147 -> Peru Chef | U147: =+E147 -> Cua Cua 9 x 24 | V147: =+H147 -> 68 | W147: =_xlfn.CONCAT(A147," ",B147) -> Peru Chef 04/13/2025 | Z147: =G147*H147 -> 68
A148: Tradiciones Andinas | B148: 04/10/2025 | C148: Bill | E148: Cua Cua 9 x 24 | F148: Cua Cua | G148: 5 | H148: 47.76 | I148: 238.8 | J148: 5767.44 | K148: =COUNTIF($E$2:$E$1438,E148) -> 9 | L148: =IF(K148>1,_xlfn.CONCAT("Se repite ",K148," veces"),"No se repite") -> Se repite 9 veces | M148: =_xlfn.CONCAT(A148,"-",E148) -> Tradiciones Andinas-Cua Cua 9 x 24 | N148: =COUNTIF($M$2:$M$1438,M148) -> 7 | O148: =IF(N148>1,_xlfn.CONCAT("Se repite ",N148," veces en ",A148),"No se repite en proveedor") -> Se repite 7 veces en Tradiciones Andinas | P148: =_xlfn.CONCAT(A148,"-",E148,"-",H148) -> Tradiciones Andinas-Cua Cua 9 x 24-47.76 | Q148: =COUNTIF($P$2:$P$1438,P148) -> 2 | R148: =IF(Q148>1,_xlfn.CONCAT("Se repite ",Q148," veces el precio de ",H148),"No se repite") -> Se repite 2 veces el precio de 47.76 | S148: =_xlfn.CONCAT("El producto ",E148," ",O148,IF(R148="No se repite",_xlfn.CONCAT(" Una vez con el precio ",H148),_xlfn.CONCAT(", ",R148))) -> El producto Cua Cua 9 x 24 Se repite 7 veces en Tradiciones Andinas, Se repite 2 veces el precio de 47.76 | T148: =+A148 -> Tradiciones Andinas | U148: =+E148 -> Cua Cua 9 x 24 | V148: =+H148 -> 47.76 | W148: =_xlfn.CONCAT(A148," ",B148) -> Tradiciones Andinas 04/10/2025 | Z148: =G148*H148 -> 238.8
A149: Tradiciones Andinas | B149: 04/25/2025 | C149: Bill | D149: 476974 | E149: Cua Cua 9 x 24 | F149: Cua Cua | G149: 12 | H149: 47.76 | I149: 573.12 | J149: 19237.2 | K149: =COUNTIF($E$2:$E$1438,E149) -> 9 | L149: =IF(K149>1,_xlfn.CONCAT("Se repite ",K149," veces"),"No se repite") -> Se repite 9 veces | M149: =_xlfn.CONCAT(A149,"-",E149) -> Tradiciones Andinas-Cua Cua 9 x 24 | N149: =COUNTIF($M$2:$M$1438,M149) -> 7 | O149: =IF(N149>1,_xlfn.CONCAT("Se repite ",N149," veces en ",A149),"No se repite en proveedor") -> Se repite 7 veces en Tradiciones Andinas | P149: =_xlfn.CONCAT(A149,"-",E149,"-",H149) -> Tradiciones Andinas-Cua Cua 9 x 24-47.76 | Q149: =COUNTIF($P$2:$P$1438,P149) -> 2 | R149: =IF(Q149>1,_xlfn.CONCAT("Se repite ",Q149," veces el precio de ",H149),"No se repite") -> Se repite 2 veces el precio de 47.76 | S149: =_xlfn.CONCAT("El producto ",E149," ",O149,IF(R149="No se repite",_xlfn.CONCAT(" Una vez con el precio ",H149),_xlfn.CONCAT(", ",R149))) -> El producto Cua Cua 9 x 24 Se repite 7 veces en Tradiciones Andinas, Se repite 2 veces el precio de 47.76 | T149: =+A149 -> Tradiciones Andinas | U149: =+E149 -> Cua Cua 9 x 24 | V149: =+H149 -> 47.76 | W149: =_xlfn.CONCAT(A149," ",B149) -> Tradiciones Andinas 04/25/2025 | Z149: =G149*H149 -> 573.12
A150: Tradiciones Andinas | B150: 05/19/2025 | C150: Bill | D150: 478734 | E150: Cua Cua 9 x 24 | F150: TA- PERU - GOLOSINAS - DULCES - Cua Cua 18g x 9 x 24 / CH105 | G150: 4 | H150: 51.1 | I150: 204.4 | J150: 31054.39 | K150: =COUNTIF($E$2:$E$1438,E150) -> 9 | L150: =IF(K150>1,_xlfn.CONCAT("Se repite ",K150," veces"),"No se repite") -> Se repite 9 veces | M150: =_xlfn.CONCAT(A150,"-",E150) -> Tradiciones Andinas-Cua Cua 9 x 24 | N150: =COUNTIF($M$2:$M$1438,M150) -> 7 | O150: =IF(N150>1,_xlfn.CONCAT("Se repite ",N150," veces en ",A150),"No se repite en proveedor") -> Se repite 7 veces en Tradiciones Andinas | P150: =_xlfn.CONCAT(A150,"-",E150,"-",H150) -> Tradiciones Andinas-Cua Cua 9 x 24-51.1 | Q150: =COUNTIF($P$2:$P$1438,P150) -> 3 | R150: =IF(Q150>1,_xlfn.CONCAT("Se repite ",Q150," veces el precio de ",H150),"No se repite") -> Se repite 3 veces el precio de 51.1 | S150: =_xlfn.CONCAT("El producto ",E150," ",O150,IF(R150="No se repite",_xlfn.CONCAT(" Una vez con el precio ",H150),_xlfn.CONCAT(", ",R150))) -> El producto Cua Cua 9 x 24 Se repite 7 veces en Tradiciones Andinas, Se repite 3 veces el precio de 51.1 | T150: =+A150 -> Tradiciones Andinas | U150: =+E150 -> Cua Cua 9 x 24 | V150: =+H150 -> 51.1 | W150: =_xlfn.CONCAT(A150," ",B150) -> Tradiciones Andinas 05/19/2025 | Z150: =G150*H150 -> 204.4
...

Sheet Base para lista de precios
A1: Final | B1: Vendor | C1: Product | D1: Price
A2: El producto Agua Ozarka Texas, 8 fl oz, Paquete de 48 Botellas de Plástico No se repite en proveedor Una vez con el precio 7.98 | B2: =VLOOKUP(A2,'Base Sin Negativos'!S2:V1438,2,0) -> #N/A | C2: =VLOOKUP(A2,'Base Sin Negativos'!S2:V1438,3,0) -> #N/A | D2: =VLOOKUP(A2,'Base Sin Negativos'!S2:V1438,4,0) -> #N/A
A3: El producto Aji Panca Seco sin pepa 2.04kg Se repite 2 veces en Peru Chef Una vez con el precio 180 | B3: =VLOOKUP(A3,'Base Sin Negativos'!S3:V1439,2,0) -> Peru Chef | C3: =VLOOKUP(A3,'Base Sin Negativos'!S3:V1439,3,0) -> Aji Panca Seco sin pepa 2.04kg | D3: =VLOOKUP(A3,'Base Sin Negativos'!S3:V1439,4,0) -> 180
A4: El producto Aji Panca Seco sin pepa 2.04kg Se repite 2 veces en Peru Chef Una vez con el precio 40 | B4: =VLOOKUP(A4,'Base Sin Negativos'!S4:V1440,2,0) -> Peru Chef | C4: =VLOOKUP(A4,'Base Sin Negativos'!S4:V1440,3,0) -> Aji Panca Seco sin pepa 2.04kg | D4: =VLOOKUP(A4,'Base Sin Negativos'!S4:V1440,4,0) -> 40
A5: El producto AjiNomoto Bolsa 1Kg x 18 No se repite en proveedor Una vez con el precio 109 | B5: =VLOOKUP(A5,'Base Sin Negativos'!S5:V1441,2,0) -> Belmont International Trading Corp | C5: =VLOOKUP(A5,'Base Sin Negativos'!S5:V1441,3,0) -> AjiNomoto Bolsa 1Kg x 18 | D5: =VLOOKUP(A5,'Base Sin Negativos'!S5:V1441,4,0) -> 109
A6: El producto AjiNomoto Bolsa 1Kg x 18 Se repite 4 veces en Tradiciones Andinas, Se repite 4 veces el precio de 85 | B6: =VLOOKUP(A6,'Base Sin Negativos'!S6:V1442,2,0) -> Tradiciones Andinas | C6: =VLOOKUP(A6,'Base Sin Negativos'!S6:V1442,3,0) -> AjiNomoto Bolsa 1Kg x 18 | D6: =VLOOKUP(A6,'Base Sin Negativos'!S6:V1442,4,0) -> 85
A7: El producto Ajinomoto Bolsa 250gr x 60 No se repite en proveedor Una vez con el precio 90 | B7: =VLOOKUP(A7,'Base Sin Negativos'!S7:V1443,2,0) -> Belmont International Trading Corp | C7: =VLOOKUP(A7,'Base Sin Negativos'!S7:V1443,3,0) -> Ajinomoto Bolsa 250gr x 60 | D7: =VLOOKUP(A7,'Base Sin Negativos'!S7:V1443,4,0) -> 90
A8: El producto Ajinomoto Bolsa 250gr x 60 Se repite 2 veces en Peru Chef, Se repite 2 veces el precio de 99 | B8: =VLOOKUP(A8,'Base Sin Negativos'!S8:V1444,2,0) -> Peru Chef | C8: =VLOOKUP(A8,'Base Sin Negativos'!S8:V1444,3,0) -> Ajinomoto Bolsa 250gr x 60 | D8: =VLOOKUP(A8,'Base Sin Negativos'!S8:V1444,4,0) -> 99
A9: El producto Ajinomoto Bolsa 250gr x 60 Se repite 4 veces en Tradiciones Andinas Una vez con el precio 69 | B9: =VLOOKUP(A9,'Base Sin Negativos'!S9:V1445,2,0) -> Tradiciones Andinas | C9: =VLOOKUP(A9,'Base Sin Negativos'!S9:V1445,3,0) -> Ajinomoto Bolsa 250gr x 60 | D9: =VLOOKUP(A9,'Base Sin Negativos'!S9:V1445,4,0) -> 69
A10: El producto Ajinomoto Bolsa 250gr x 60 Se repite 4 veces en Tradiciones Andinas, Se repite 3 veces el precio de 73.8 | B10: =VLOOKUP(A10,'Base Sin Negativos'!S10:V1446,2,0) -> Tradiciones Andinas | C10: =VLOOKUP(A10,'Base Sin Negativos'!S10:V1446,3,0) -> Ajinomoto Bolsa 250gr x 60 | D10: =VLOOKUP(A10,'Base Sin Negativos'!S10:V1446,4,0) -> 73.8
A11: El producto AjiNomoto Bolsa 500g x 30 Se repite 5 veces en Tradiciones Andinas Una vez con el precio 71 | B11: =VLOOKUP(A11,'Base Sin Negativos'!S11:V1447,2,0) -> Tradiciones Andinas | C11: =VLOOKUP(A11,'Base Sin Negativos'!S11:V1447,3,0) -> AjiNomoto Bolsa 500g x 30 | D11: =VLOOKUP(A11,'Base Sin Negativos'!S11:V1447,4,0) -> 71
A12: El producto AjiNomoto Bolsa 500g x 30 Se repite 5 veces en Tradiciones Andinas, Se repite 4 veces el precio de 75.97 | B12: =VLOOKUP(A12,'Base Sin Negativos'!S12:V1448,2,0) -> Tradiciones Andinas | C12: =VLOOKUP(A12,'Base Sin Negativos'!S12:V1448,3,0) -> AjiNomoto Bolsa 500g x 30 | D12: =VLOOKUP(A12,'Base Sin Negativos'!S12:V1448,4,0) -> 75.97
A13: El producto AJINOSIYAO 500ml x 24 No se repite en proveedor Una vez con el precio 50.4 | B13: =VLOOKUP(A13,'Base Sin Negativos'!S13:V1449,2,0) -> Belmont International Trading Corp | C13: =VLOOKUP(A13,'Base Sin Negativos'!S13:V1449,3,0) -> AJINOSIYAO 500ml x 24 | D13: =VLOOKUP(A13,'Base Sin Negativos'!S13:V1449,4,0) -> 50.4
... A746: El producto Yuca Family Pack / Cassava Family Pack 5lb x 6 Se repite 3 veces en Tradiciones Andinas, Se repite 2 veces el precio de 36 | B746: =VLOOKUP(A746,'Base Sin Negativos'!S746:V2182,2,0) -> Tradiciones Andinas | C746: =VLOOKUP(A746,'Base Sin Negativos'!S746:V2182,3,0) -> Yuca Family Pack / Cassava Family Pack 5lb x 6 | D746: =VLOOKUP(A746,'Base Sin Negativos'!S746:V2182,4,0) -> 36

Sheet Lista de precios Versiones
A1: Vendor | B1: Product | C1: Price | D1: x
A2: Amazon | B2: Display Strip | C2: 5.41 | D2: =COUNTIF($B$2:$B$746,B2) -> 1
A3: Arjo Vision Trading Company LLC | B3: Volt yellow Guarana 16fl oz /15 | C3: 16.0226 | D3: =COUNTIF($B$2:$B$746,B3) -> 1
A4: Belmont International Trading Corp | B4: Belmont Aceituna Bidon 104oz x 6 | C4: 106 | D4: =COUNTIF($B$2:$B$746,B4) -> 1
A5: Belmont International Trading Corp | B5: Belmont Aceituna Botija 20oz x 12 | C5: 39 | D5: =COUNTIF($B$2:$B$746,B5) -> 1
A6: Belmont International Trading Corp | B6: Belmont Aji Amarillo desvenado FROZEN 12oz x 10 | C6: 30.9 | D6: =COUNTIF($B$2:$B$746,B6) -> 1
A7: Belmont International Trading Corp | B7: Belmont Aji Amarillo desvenado FROZEN 2Lb x 8 | C7: 56 | D7: =COUNTIF($B$2:$B$746,B7) -> 1
A8: Belmont International Trading Corp | B8: Belmont Aji Amarillo en Salmuera 20oz x 12 | C8: 36.75 | D8: =COUNTIF($B$2:$B$746,B8) -> 1
A9: Belmont International Trading Corp | B9: Belmont Aji Amarillo entero 1Lb x 18 FROZEN | C9: 45 | D9: =COUNTIF($B$2:$B$746,B9) -> 1
A10: Belmont International Trading Corp | B10: Belmont Aji Amarillo pasta 16oz x 12 | C10: 44 | D10: =COUNTIF($B$2:$B$746,B10) -> 1
A11: Belmont International Trading Corp | B11: Belmont Aji Amarillo pasta 8oz x 12 | C11: 23.5 | D11: =COUNTIF($B$2:$B$746,B11) -> 1
A12: Belmont International Trading Corp | B12: Belmont Aji Limo 14oz x 9 FROZEN | C12: 20.9 | D12: =COUNTIF($B$2:$B$746,B12) -> 1
A13: Belmont International Trading Corp | B13: Belmont Aji Panca pasta 16Oz x 12 | C13: 44 | D13: =COUNTIF($B$2:$B$746,B13) -> 1
... A746: Tradiciones Andinas | B746: Yuca Family Pack / Cassava Family Pack 5lb x 6 | C746: 36 | D746: =COUNTIF($B$2:$B$746,B746) -> 6

Sheet Tabla
D3: Valores
A4: Transaction date | B4: Vendor | C4: Product/Service full name | D4: Suma de Quantity | E4: Mín. de Rate | F4: Máx. de Rate
A5: 06/02/2025 | B5: Amazon | C5: Display Strip | D5: 8 | E5: 5.41 | F5: 5.41
A6: 06/04/2025 | B6: Amazon | C6: Display Strip | D6: 8 | E6: 5.41 | F6: 5.41
A7: Total general | D7: 16 | E7: 5.41 | F7: 5.41

Sheet Resumen
A1: Productos | B1: =COUNTA(A2:A4471) -> 446 | D1: Proveedores | E1: =COUNTA(D2:D4471) -> 12 | G1: Lista precios | H1: =COUNTA(G2:G4471) -> 12 | J1: Versiones Listas de precios | K1: =COUNTA(J2:J4471) -> 59
A2: Agua Ozarka Texas, 8 fl oz, Paquete de 48 Botellas de Plástico | D2: Sam's Club | G2: Sam's Club | J2: Amazon-06/02/2025
A3: Aji Panca Seco sin pepa 2.04kg | D3: Peru Chef | G3: Peru Chef | J3: Amazon-06/04/2025
A4: AjiNomoto Bolsa 1Kg x 18 | D4: Belmont International Trading Corp | G4: Belmont International Trading Corp | J4: Arjo Vision Trading Company LLC-03/19/2025
A5: Ajinomoto Bolsa 250gr x 60 | D5: Tradiciones Andinas | G5: Tradiciones Andinas | J5: Belmont International Trading Corp-04/28/2025
A6: AjiNomoto Bolsa 500g x 30 | D6: La Sorpresa Store | G6: La Sorpresa Store | J6: Belmont International Trading Corp-05/16/2025
A7: AJINOSIYAO 500ml x 24 | D7: Amazon | G7: Amazon | J7: Belmont International Trading Corp-06/12/2025
A8: Arrocito Atomico 150gr x 20 (5.3oz) x 20 | D8: Continental Food and Beverage, inc | G8: Continental Food and Beverage, inc | J8: Belmont International Trading Corp-07/31/2025
A9: Atun Florida Solido en aceite 6 oz X 48 | D9: Lam's Foods Inc. | G9: Lam's Foods Inc. | J9: Belmont International Trading Corp-10/20/2025
A10: Belmont Aceituna Bidon 104oz x 6 | D10: Fiesta Mart #60 | G10: Fiesta Mart #60 | J10: Belmont International Trading Corp-12/11/2025
A11: Belmont Aceituna Botija 20oz x 12 | D11: GUIXENS FOOD GROUP, INC. | G11: GUIXENS FOOD GROUP, INC. | J11: Continental Food and Beverage, inc-03/03/2025
A12: Belmont Aderezo de Anticucho 16oz x 12 | D12: Arjo Vision Trading Company LLC | G12: Arjo Vision Trading Company LLC | J12: Continental Food and Beverage, inc-04/09/2025
A13: Belmont Aji Amarillo desvenado FROZEN 12oz x 10 | D13: SAVERS SUPERMERCADO COST + PLUS | G13: SAVERS SUPERMERCADO COST + PLUS | J13: Continental Food and Beverage, inc-04/28/2025
A14: Belmont Aji Amarillo desvenado FROZEN 2Lb x 8 | J14: Continental Food and Beverage, inc-07/08/2025
A15: Belmont Aji Amarillo en Salmuera 20oz x 12 | J15: Continental Food and Beverage, inc-08/21/2025
A16: Belmont Aji Amarillo entero 1Lb x 18 FROZEN | J16: Continental Food and Beverage, inc-10/01/2025
A17: Belmont Aji Amarillo pasta 16oz x 12 | J17: Continental Food and Beverage, inc-11/04/2025
A18: Belmont Aji Amarillo pasta 8oz x 12 | J18: Fiesta Mart #60-11/13/2025
A19: Belmont Aji Limo 14oz x 9 FROZEN | J19: Fiesta Mart #60-12/18/2025
A20: Belmont Aji Panca pasta 16Oz x 12 | J20: GUIXENS FOOD GROUP, INC.-10/29/2025
A21: Belmont Aji Panca pasta 8oz x 12 | J21: La Sorpresa Store-08/26/2025
A22: Belmont Aji Panca pasta Bidon 7Lb | J22: Lam's Foods Inc.-10/03/2025
A23: Belmont Chicha de Jora | J23: Peru Chef-03/26/2025
A24: Belmont Chicha Morada 16oz x 12 | J24: Peru Chef-04/10/2025
A25: Belmont Chicha Morada 1Lt x 6 | J25: Peru Chef-04/13/2025
... A60: Chocolate Triangulo x 22 | J60: Tradiciones Andinas-12/03/2025
A61: Coco Milk Drink with Nata de Coco MANGO
A62: Coco Milk Drink with Nata de Coco ORIGINAL
A63: Coco Milk Drink with Nata de Coco STRAWBERRY
A64: Conaprole - Dulce de Leche - Milk Caramel Spread
A65: CORONITA - Galleta de Chocolate x 6 x 28
A66: Cua Cua 9 x 24
A67: DEL VALLE - Boldo Filtrante 25gr x 25 x 32
A68: DEL VALLE - Chancapiedra filtrante 25 x 32
A69: DEL VALLE Una de Gato filtrante 25 x 32
A70: Display Strip
A71: Doña Pepa 23gr 6 x 36
A72: D'Onofrio Chocolate Sublime 26 G x 24
... A447: Yuca Family Pack / Cassava Family Pack 5lb x 6

Sheet Products
A1: Valor de busqueda | B1: Nombre | C1: Descripcion | D1: SKU
A2: Agua Ozarka Texas, 8 fl oz, Paquete de 4 | B2: Agua Ozarka Texas, 8 fl oz, Paquete de 48 Botellas de Plástico | C2: Agua Ozarka Texas, 8 fl oz, Paquete de 48 Botellas de Plástico | D2: 77867428
A3: Aji Panca Seco sin pepa 2.04kg | B3: Aji Panca Seco sin pepa 2.04kg | C3: Aji Panca Seco sin pepa 2.04kg | D3: 77687079
A4: AjiNomoto Bolsa 1Kg x 18 | B4: AjiNomoto Bolsa 1Kg x 18 | C4: AjiNomoto Bolsa 1Kg x 18 | D4: 77732377
A5: Ajinomoto Bolsa 250gr x 60 | B5: Ajinomoto Bolsa 250gr x 60 | C5: Ajinomoto Bolsa 250gr x 60 | D5: 77164391
A6: AjiNomoto Bolsa 500g x 30 | B6: AjiNomoto Bolsa 500g x 30 | C6: AjiNomoto Bolsa 500g x 30 | D6: 77755049
A7: AJINOSIYAO 500ml x 24 | B7: AJINOSIYAO 500ml x 24 | C7: AJINOSIYAO 500ml x 24 | D7: 77739024
A8: Arrocito Atomico 150gr x 20 (5.3oz) x 2 | B8: Arrocito Atomico 150gr x 20 (5.3oz) x 20 | C8: Arrocito Atomico 150gr x 20 (5.3oz) x 20 | D8: 77177011
A9: Atun Florida Solido en aceite 6 oz X 48 | B9: Atun Florida Solido en aceite 6 oz X 48 | C9: Atun Florida Solido en aceite 6 oz X 48 | D9: 77917115
A10: Belmont Aceituna Bidon 104oz x 6 | B10: Belmont Aceituna Bidon 104oz x 6 | C10: Belmont Aceituna Bidon 104oz x 6 | D10: 77401688
A11: Belmont Aceituna Botija 20oz x 12 | B11: Belmont Aceituna Botija 20oz x 12 | C11: Belmont Aceituna Botija 20oz x 12 | D11: 77185650
A12: Belmont Aderezo de Anticucho 16oz x 12 | B12: Belmont Aderezo de Anticucho 16oz x 12 | C12: Belmont Aderezo de Anticucho 16oz x 12 | D12: 77268225
